Workbook

Sheet 2. Reglas de Calidad (2)
A1: Integración de la info de inversión a través de Google Sheet | B1: ID Regla de calidad | C1: Nombre del Entidad de Dato | D1: Descripción de Regla de calidad | E1: Priorizada | F1: Motivo | G1: Tipo de regla de calidad | H1: Principio de calidad asociado | I1: Umbral Superior | J1: Umbral Inferior | K1: Periodicidad | L1: Fecha de creación | M1: Validado por Data Owner | N1: Código de Entidad del Dato
A2: Caso de uso que corresponde | B2: Identificador de Regla de Calidad | C2: Nombre único con el cual el Negocio identifica al Entidad de Dato | D2: Descripción detallada de la regla de calidad que se quiere aplicar sobre el dato | G2: Indica si se trata de una regla básica o una regla experta | H2: Se debe indicar el principio de calidad al que se hace referencia (Consistencia, completitud, etc) | I2: Indica el límite superior sobre los valores que puede tomar el dato | J2: Indica el límite inferior sobre los valores que puede tomar el dato | K2: Frecuencia con la que se aplica | L2: Indica la fecha de creación | M2: Una vez revisado por el Data Owner se coloca Sí en señal de conformidad con la definición | N2: Código de Entidad del Dato
A3: Gente Imparable | B3: =+UPPER(MID(A3,1,3))&"00"&COUNTA(A$3) -> GEN001 | C3: Índice de Engagement | D3: Se mide entre un rango del 1 al 7, no deben existir valores negativos: 1, 2,3 Negativo 4 Neutro 5,6,7 Positivo | E3: Priorizada | F3: Regla obligatoria | G3: Básica | H3: Validez | N3: -
A4: Gente Imparable | B4: =+UPPER(MID(A4,1,3))&"00"&COUNTA(A$3:A4) -> GEN002 | C4: Índice de Engagement | D4: Los valores se categorizan de la siguiente manera: Percepción Negativa Alta (1) Percepción Negativa Media (2) Percepción Negativa Baja (3) Percepción Neutro (4) Percepción Positiva Baja (5) Percepción Positiva Media (6) Percepción Positiva Alta (7) | E4: Priorizada | F4: Regla obligatoria | G4: Experta | H4: Consistencia | N4: -
A5: CRM | B5: =+UPPER(MID(A5,1,3))&"00"&COUNTA(A$3:A5) -> CRM003 | C5: Id Cliente | D5: No debe existir duplicados, son valores únicos. | E5: Priorizada | F5: Regla obligatoria | G5: Básica | H5: Integridad | I5: 1 | J5: 1 | K5: A demanda | L5: - | M5: No revisado | N5: CRM00001
A6: CRM | B6: =+UPPER(MID(A6,1,3))&"00"&COUNTA(A$3:A6) -> CRM004 | C6: Tipo de cliente | D6: Los valores aceptados son, de tipo númerico: Valor 1 : PERSONA NATURAL Valor 2: PERSONA JURIDICA | E6: Priorizada | F6: Regla obligatoria | G6: Básica | H6: Validez | I6: 1 | J6: 1 | K6: A demanda | M6: No revisado | N6: CRM00002
A7: CRM | B7: =+UPPER(MID(A7,1,3))&"00"&COUNTA(A$3:A7) -> CRM005 | C7: Razón social | D7: No deberia contener caracteres especiales, tampoco saltos de linea ni tabuladores, tampoco el caracter de palote (|), tener cuidado, ya que los valores aceptados pueden ser: &, -, ., ", / | E7: Priorizada | F7: Regla obligatoria | G7: Básica | H7: Validez | I7: 1 | J7: 1 | K7: A demanda | M7: No revisado | N7: CRM00003
A8: CRM | B8: =+UPPER(MID(A8,1,3))&"00"&COUNTA(A$3:A8) -> CRM006 | C8: Nombre | D8: Esta regla valida que los valores en el campo NOMBRE cumplan con los estándares adecuados, evitando caracteres no permitidos, nombres incorrectos o datos inválidos. Se consideran valores incorrectos aquellos que: Contienen caracteres especiales no permitidos, como |, !, ", /, :, $, &, ?, ¡, ¿, =, {, [, +, *, ~, ^, }, ], \, ;, °, #, (, ), ,, <, >, ¬, --, entre otros. Son nombres inválidos o placeholders, como --, NO REP, ,, ., :. Tienen menos de 2 caracteres, lo que indicaría un posible error en la captura. Empiezan con un número (0-9), lo cual no es válido para un nombre. No corresponden a nombres reales, excluyendo abreviaturas incorrectas (A, B, C... hasta Z) y sus versiones con punto (A., B., C....). | E8: Priorizada | F8: Regla obligatoria | G8: Básica | H8: Validez | I8: 1 | J8: 1 | K8: A demanda | M8: No revisado | N8: CRM00004
A9: CRM | B9: =+UPPER(MID(A9,1,3))&"00"&COUNTA(A$3:A9) -> CRM007 | C9: Apellido Paterno | D9: Esta regla valida que los valores en el campo APELLIDO_PATERNO cumplan con los estándares adecuados, evitando caracteres no permitidos, nombres incorrectos o datos inválidos. Se consideran valores incorrectos aquellos que: Contienen caracteres especiales no permitidos, como |, !, ", /, :, $, &, ?, ¡, ¿, =, {, [, +, *, ~, ^, }, ], \, ;, °, #, (, ), ,, <, >, ¬, --, entre otros. Son nombres inválidos o placeholders, como --, NO REP, ,, ., :. Tienen menos de 2 caracteres, lo que indicaría un posible error en la captura. Empiezan con un número (0-9), lo cual no es válido para un nombre. No corresponden a nombres reales, excluyendo abreviaturas incorrectas (A, B, C... hasta Z) y sus versiones con punto (A., B., C....). | E9: Priorizada | F9: Regla obligatoria | G9: Básica | H9: Validez | I9: 1 | J9: 1 | K9: A demanda | M9: No revisado | N9: CRM00005
A10: CRM | B10: =+UPPER(MID(A10,1,3))&"00"&COUNTA(A$3:A10) -> CRM008 | C10: Apellido Materno | D10: Esta regla valida que los valores en el campo APELLIDO_MATERNO cumplan con los estándares adecuados, evitando caracteres no permitidos, nombres incorrectos o datos inválidos. Se consideran valores incorrectos aquellos que: Contienen caracteres especiales no permitidos, como |, !, ", /, :, $, &, ?, ¡, ¿, =, {, [, +, *, ~, ^, }, ], \, ;, °, #, (, ), ,, <, >, ¬, --, entre otros. Son nombres inválidos o placeholders, como --, NO REP, ,, ., :. Tienen menos de 2 caracteres, lo que indicaría un posible error en la captura. Empiezan con un número (0-9), lo cual no es válido para un nombre. No corresponden a nombres reales, excluyendo abreviaturas incorrectas (A, B, C... hasta Z) y sus versiones con punto (A., B., C....). | E10: Priorizada | F10: Regla obligatoria | G10: Básica | H10: Validez | I10: 1 | J10: 1 | K10: A demanda | M10: No revisado | N10: CRM00006
A11: CRM | B11: =+UPPER(MID(A11,1,3))&"00"&COUNTA(A$3:A11) -> CRM009 | C11: Nombre de contacto de la empresa | D11: "Esta regla valida que los valores en el campo NOMBRE_CONTACTO_EMPRESA cumplan con los estándares adecuados, evitando caracteres no permitidos, nombres incorrectos o datos inválidos. Se consideran valores incorrectos aquellos que: Contienen caracteres especiales no permitidos, como |, !, "", /, :, $, &, ?, ¡, ¿, =, {, [, +, *, ~, ^, }, ], \, ;, °, #, (, ), ,, <, >, ¬, --, entre otros. Son nombres inválidos o placeholders, como --, NO REP, ,, ., :. Tienen menos de 2 caracteres, lo que indicaría un posible error en la captura. Empiezan con un número (0-9), lo cual no es válido para un nombre. No corresponden a nombres reales, excluyendo abreviaturas incorrectas (A, B, C... hasta Z) y sus versiones con punto (A., B., C....)." | E11: Priorizada | F11: Regla obligatoria | G11: Básica | H11: Validez | I11: 1 | J11: 1 | K11: A demanda | M11: No revisado | N11: CRM00007
A12: CRM | B12: =+UPPER(MID(A12,1,3))&"00"&COUNTA(A$3:A12) -> CRM0010 | C12: Apellido paterno de contacto de la empresa | D12: Esta regla valida que los valores en el campo APELLIDO_PATERNO_CONTACTO_EMPRESA cumplan con los estándares adecuados, evitando caracteres no permitidos, nombres incorrectos o datos inválidos. Se consideran valores incorrectos aquellos que: Contienen caracteres especiales no permitidos, como |, !, ", /, :, $, &, ?, ¡, ¿, =, {, [, +, *, ~, ^, }, ], \, ;, °, #, (, ), ,, <, >, ¬, --, entre otros. Son nombres inválidos o placeholders, como --, NO REP, ,, ., :. Tienen menos de 2 caracteres, lo que indicaría un posible error en la captura. Empiezan con un número (0-9), lo cual no es válido para un nombre. No corresponden a nombres reales, excluyendo abreviaturas incorrectas (A, B, C... hasta Z) y sus versiones con punto (A., B., C....). | E12: Priorizada | F12: Regla obligatoria | G12: Básica | H12: Validez | I12: 1 | J12: 1 | K12: A demanda | M12: No revisado | N12: CRM00008
A13: CRM | B13: =+UPPER(MID(A13,1,3))&"00"&COUNTA(A$3:A13) -> CRM0011 | C13: Apellido materno de contacto de la empresa | D13: Esta regla valida que los valores en el campo APELLIDO_MATERNO_CONTACTO_EMPRESA cumplan con los estándares adecuados, evitando caracteres no permitidos, nombres incorrectos o datos inválidos. Se consideran valores incorrectos aquellos que: Contienen caracteres especiales no permitidos, como |, !, ", /, :, $, &, ?, ¡, ¿, =, {, [, +, *, ~, ^, }, ], \, ;, °, #, (, ), ,, <, >, ¬, --, entre otros. Son nombres inválidos o placeholders, como --, NO REP, ,, ., :. Tienen menos de 2 caracteres, lo que indicaría un posible error en la captura. Empiezan con un número (0-9), lo cual no es válido para un nombre. No corresponden a nombres reales, excluyendo abreviaturas incorrectas (A, B, C... hasta Z) y sus versiones con punto (A., B., C....). | E13: Priorizada | F13: Regla obligatoria | G13: Básica | H13: Validez | I13: 1 | J13: 1 | K13: A demanda | M13: No revisado | N13: CRM00009
A14: CRM | B14: =+UPPER(MID(A14,1,3))&"00"&COUNTA(A$3:A14) -> CRM0012 | C14: Tipo Documento | D14: Puede ser 1 = PERSONA NATURAL, 2 = PERSONA JURIDICA, pero estos se pueden abrir por 1 DNI 1 CARNET DE EXTRANJERÍA 1 PASAPORTE 2 TIN 2 RUC PJ | E14: Priorizada | F14: Regla obligatoria | G14: Básica | H14: Validez | I14: 1 | J14: 1 | K14: A demanda | M14: No revisado | N14: CRM00010
A15: CRM | B15: =+UPPER(MID(A15,1,3))&"00"&COUNTA(A$3:A15) -> CRM0013 | C15: Número Documento | D15: El campo es de tipo texto, las longitudes maximas permitidas son: 1 DNI : 8, minima = 8, maxima = 8 1 CARNET DE EXTRANJERÍA 14, minima = 9, maxima = 14 1 PASAPORTE 13, minima = 9, maxima = 13 2 TIN: 14, minima = 9, maxima = 14 2 RUC PJ : 11, minima = 11, maxima = 11 | E15: Priorizada | F15: Regla obligatoria | G15: Básica | H15: Validez | I15: 1 | J15: 1 | K15: A demanda | M15: No revisado | N15: CRM00011
A16: CRM | B16: =+UPPER(MID(A16,1,3))&"00"&COUNTA(A$3:A16) -> CRM0014 | C16: RUC de persona natural | D16: El campo es de tipo texto, las longitudes maximas permitidas son: RUC : 11, minima = 11, maxima = 11 | E16: Priorizada | F16: Regla obligatoria | G16: Básica | H16: Validez | I16: 1 | J16: 1 | K16: A demanda | M16: No revisado | N16: CRM00012
A17: CRM | B17: =+UPPER(MID(A17,1,3))&"00"&COUNTA(A$3:A17) -> CRM0015 | C17: Grupo económico | D17: Valor de tipo texto, descripcion de grupo economico, maximo valor de caracteres: 100, minimo: 3 | E17: Priorizada | F17: Regla obligatoria | G17: Básica | H17: Validez | I17: 1 | J17: 1 | K17: A demanda | M17: No revisado | N17: CRM00013
... A34: CRM | B34: =+UPPER(MID(A34,1,3))&"00"&COUNTA(A$3:A34) -> CRM0032 | C34: Tipo de participante de póliza | D34: Regla tabla insis, Tipo de participante de poliza, dato de tipo texto, considerar una longitud maxima de 50 caracteres, para mayor detalle revisar tabla INSIS_PEOPLE_V10.HT_PEOPLE_ROLE, campo NAME | E34: Priorizada | F34: Regla obligatoria | G34: Básica | H34: Validez | I34: 1 | J34: 1 | K34: A demanda | M34: No revisado | N34: CRM00030

Sheet 0. Leyenda del Diccionario
B1: Tipo de Metadato | C1: Responsables
B2: Metadatos funcionales | C2: Data Owner | S2: Decisión | T2: Tipo de Dato | U2: Tipo | V2: Prioridad
B3: Control de cambios | C3: Data Officer | S3: SÍ | T3: Origen | U3: Indicador | V3: Alta
B4: Metadatos de la oficina del CDO | C4: Data Officer | S4: NO | T4: Calculado | U4: Dimensión | V4: Media
B5: Validaciones | C5: Data Owner y Data Custodian | V5: Baja
B6: Metadatos funcionales con soporte técnico | C6: Data Custodian
B7: Metadatos técnicos | C7: Data Custodian
B8: Campo formulado | C8: Data Officer

Sheet 1. Conceptos de Negocio
B1: Caso de Uso | C1: Codigo de dominio | D1: Nombre del dominio | E1: Codigo del subdominio | F1: Nombre del subdominio | G1: Nombre del subdominio OMG | H1: Concepto de negocio | I1: Término de Negocio | J1: Código de Entidad del Dato | K1: Data Owner | L1: Dato Critico | M1: Personal | N1: Sensible | O1: Definición de negocio | P1: Tipo de Dato | Q1: Indicadores empleados en el cálculo | R1: Lógica de cálculo | S1: Ejemplo de valores del Entidad del Dato | T1: Prioridad del Entidad de Dato | U1: ¿Indicador/ Dimensión? | V1: Periodicidad de Generación | W1: Áreas usuarias del dato | X1: Validado por Data Owner | Y1: Responsable de la actualización en el Diccionario Negocio
B2: Caso de uso que corresponde / Proyecto estratégico | C2: Código del dominio de datos al cual pertenece el Entidad de Dato | D2: Nombre del dominio de datos al cual pertenece el Concepto de Negocio | E2: Código del subdominio de datos al cual pertenece el Concepto de Negocio | F2: Nombre del subdominio de datos al cual pertenece el Concepto de Negocio | G2: Nombre del subdominio de datos en OMG | H2: Nombre asignado a cierta definición por la unidad de Negocio | I2: Nombre único con el cual el Negocio identifica al Entidad de Dato | J2: Identificador único secuencial, asignado al Entidad de Dato por Data Officer | K2: Nombre de la persona responsable de la gestión del dato. | L2: Dato critico: Si el dato es de uso Transversal/Regulado/Toma de decisiones. | M2: Es dato personal si me permite identificar directamente a una persona natural. | N2: Tipificación de datos que requieren un tratamiento especial por su sinsibilidad. Ej: diagnóstico médico, N°tarjeta, sueldo del colaborador/cliente. | O2: Concepto definido por el negocio para la Entidad de dato. Contiene las propiedades, características y exclusiones relacionadas al dato, y lógicas necesarias para su entendimiento. | P2: Definir si el dato es Origen: No sufre ninguna transformación Calculado: Resultado de alguna transformación | Q2: Datos utilizados en el cálculo de un indicador. | R2: Descripción resumida del cálculo realizado | S2: Valores del concepto como ejemplo y/o referencia | T2: Indica la prioridad de acuerdo a: Alta: Dato se envía a un ente regulador o algún comité directivo Media: El dato se comparte con otras áreas Baja: El dato es de uso interno | U2: Define si el Concepto de Negocio es un indicador o una dimensión | V2: Frecuencia de generación del dato | W2: Lista de áreas que solicitan el dato. | X2: Una vez revisado por el Data Owner se coloca Sí en señal de conformidad con la definición | Y2: Nombre del colaborador que actualizó el dato
A3: =TEXT(ROW()-2, "00000") -> 00001 | B3: CRM | C3: D001 | D3: Persona | E3: S001 | F3: Cliente | G3: Party Role | H3: Información del cliente | I3: Cliente | J3: =B3&A3 -> CRM00001 | K3: Gaudy Sanchez | L3: SÍ | M3: SÍ | N3: NO | O3: Contratante, asegurado o beneficiario incluido en Póliza vigente de algún producto de la empresa. | P3: Origen | Q3: No aplica | R3: No aplica | S3: María Uriarte Suárez | T3: Alta | U3: Dimensión | V3: A demanda | W3: - NO | X3: SÍ | Y3: Gobierno de Datos
A4: =TEXT(ROW()-2, "00000") -> 00002 | B4: CRM | C4: D001 | D4: Persona | E4: S001 | F4: Cliente | G4: Party | H4: Información del cliente | I4: Tipo de persona | J4: =B4&A4 -> CRM00002 | K4: Gaudy Sanchez | L4: SÍ | M4: NO | N4: NO | O4: Clasificación de cualquier individuo (persona natural) u organización (persona jurídica) de interés para el análisis de los negocios que desarrolla la Compañía. | P4: Origen | Q4: No aplica | R4: No aplica | S4: 1: Persona natural 2: Persona jurídica | T4: Alta | U4: Dimensión | V4: A demanda | W4: - Marketing - FFVV - Retención de cartera - CX | X4: SÍ | Y4: Gobierno de Datos
A5: =TEXT(ROW()-2, "00000") -> 00003 | B5: CRM | C5: D001 | D5: Persona | E5: S001 | F5: Cliente | G5: Party | H5: Información del cliente | I5: Documento de Identidad | J5: =B5&A5 -> CRM00003 | K5: Gaudy Sanchez | L5: SÍ | M5: SÍ | N5: NO | O5: Toda mención a documento de identidad deberá ser considerado dependiendo de lo detallado seguidamente: Tipo de persona - Documento de identidad. - Natural Peruano: Documento Nacional de Identidad (DNI). - Natural Extranjero: Carné de extranjería - Natural Extranjero no residente: Pasaporte. - Jurídica Peruano: Registro Único de Contribuyente (RUC). | P5: Origen | Q5: No aplica | R5: No aplica | S5: DNI: 10318698 RUC: 20123456789 CE: 12345678 Pasaporte: Y12345678 | T5: Alta | U5: Dimensión | V5: A demanda | W5: - Marketing - FFVV - Retencion de cartera - CX | X5: SÍ | Y5: Gobierno de Datos
A6: =TEXT(ROW()-2, "00000") -> 00004 | B6: CRM | C6: D001 | D6: Persona | E6: S001 | F6: Cliente | G6: Grouping | H6: Información empresarial | I6: Grupo económico | J6: =B6&A6 -> CRM00004 | K6: Gaudy Sanchez | L6: NO | M6: NO | N6: NO | O6: Conjunto de personas jurídicas, en la que alguna de ellas ejerce control sobre la o las demás, o cuando el control sobre las personas jurídicas corresponde a una o varias personas naturales que actúan como una unidad de decisión. | P6: Origen | Q6: No aplica | R6: No aplica | S6: EXPLOT MINA, CANTERA, PETR GAS | T6: Baja | U6: Dimensión | V6: A demanda | W6: - NO | X6: SÍ | Y6: Gobierno de Datos
A7: =TEXT(ROW()-2, "00000") -> 00005 | B7: CRM | C7: D001 | D7: Persona | E7: S001 | F7: Cliente | G7: Person | H7: Información del cliente | I7: Género | J7: =B7&A7 -> CRM00005 | K7: Gaudy Sanchez | L7: SÍ | M7: SÍ | N7: NO | O7: Identidad biológica de la persona natural. | P7: Origen | Q7: No aplica | R7: No aplica | S7: Masculino Femenino | T7: Media | U7: Dimensión | V7: A demanda | W7: - Marketing | X7: SÍ | Y7: Gobierno de Datos
A8: =TEXT(ROW()-2, "00000") -> 00006 | B8: CRM | C8: D001 | D8: Persona | E8: S001 | F8: Cliente | G8: Person | H8: Información del cliente | I8: Fecha Nacimiento | J8: =B8&A8 -> CRM00006 | K8: Gaudy Sanchez | L8: SÍ | M8: SÍ | N8: NO | O8: Tiempo específico que indica el día de nacimiento de la persona natural. | P8: Origen | Q8: No aplica | R8: No aplica | S8: 36192 | T8: Alta | U8: Dimensión | V8: A demanda | W8: - Marketing | X8: SÍ | Y8: Gobierno de Datos
A9: =TEXT(ROW()-2, "00000") -> 00007 | B9: CRM | C9: D001 | D9: Persona | E9: S001 | F9: Cliente | G9: Organization | H9: Información empresarial | I9: Tipo de compañía | J9: =B9&A9 -> CRM00007 | K9: Gaudy Sanchez | L9: SÍ | M9: NO | N9: NO | O9: Identifica si la empresa es privada o del estado | P9: Origen | Q9: No aplica | R9: No aplica | S9: Empresa estatal Empresa privada | T9: Baja | U9: Dimensión | V9: A demanda | W9: - NO | X9: SÍ | Y9: Gobierno de Datos
A10: =TEXT(ROW()-2, "00000") -> 00008 | B10: CRM | C10: D001 | D10: Persona | E10: S001 | F10: Cliente | G10: Organization | H10: Información empresarial | I10: Actividad económica | J10: =B10&A10 -> CRM00008 | K10: Gaudy Sanchez | L10: SÍ | M10: NO | N10: NO | O10: Es la ocupación formal desarrollada por una entidad, persona natural con negocio o persona jurídica, mediante la cual ofrece bienes o servicios. | P10: Origen | Q10: No aplica | R10: No aplica | S10: 4630: VENTA AL POR MAYOR DE ALIMENTO 4641: VENTA AL POR MAYOR DE PRODUCTO | T10: Baja | U10: Dimensión | V10: A demanda | W10: - NO | X10: SÍ | Y10: Gobierno de Datos
A11: =TEXT(ROW()-2, "00000") -> 00009 | B11: CRM | C11: D001 | D11: Persona | E11: S001 | F11: Cliente | G11: Party Role | H11: Información del cliente | I11: Estado del Cliente | J11: =B11&A11 -> CRM00009 | K11: Gaudy Sanchez | L11: SÍ | M11: NO | N11: NO | O11: El estado refleja la situación, o condición, de una entidad relacionada en un momento dado o durante una duración determinada. | P11: Origen | Q11: No aplica | R11: No aplica | S11: 1: Activo 2. Inactivo 3: Bloqueado | T11: Alta | U11: Dimensión | V11: A demanda | W11: - Marketing - FFVV - Retencion de cartera | X11: SÍ | Y11: Gobierno de Datos
A12: =TEXT(ROW()-2, "00000") -> 00010 | B12: CRM | C12: D001 | D12: Persona | E12: S001 | F12: Cliente | G12: Party Role | H12: Información del cliente | I12: Motivo de bloqueo | J12: =B12&A12 -> CRM00010 | K12: Gaudy Sanchez | L12: SÍ | M12: NO | N12: NO | O12: Es la razón registrada para restringir temporalmente o de manera permanente la operatividad del cliente en los sistemas internos. Este motivo explica por qué el cliente no puede realizar ciertos procesos comerciales o transaccionales. | P12: Origen | Q12: No aplica | R12: No aplica | S12: Fraude Muerte | T12: Media | U12: Dimensión | V12: A demanda | W12: - NO | X12: SÍ | Y12: Gobierno de Datos
A13: =TEXT(ROW()-2, "00000") -> 00011 | B13: CRM | C13: D001 | D13: Persona | E13: S001 | F13: Cliente | G13: Party Communication​ | H13: Información del cliente | I13: Correo electrónico | J13: =B13&A13 -> CRM00011 | K13: Gaudy Sanchez | L13: SÍ | M13: SÍ | N13: NO | O13: Es un servicio de red que permite a los usuarios enviar y recibir mensajes mediante redes de comunicación electrónica. | P13: Origen | Q13: No aplica | R13: No aplica | S13: aaaa@gmail.com | T13: Alta | U13: Dimensión | V13: A demanda | W13: - Marketing - FFVV - Retencion de cartera - CX | X13: SÍ | Y13: Gobierno de Datos
A14: =TEXT(ROW()-2, "00000") -> 00012 | B14: CRM | C14: D001 | D14: Persona | E14: S001 | F14: Cliente | G14: Party Communication​ | H14: Información del cliente | I14: Teléfono | J14: =B14&A14 -> CRM00012 | K14: Gaudy Sanchez | L14: SÍ | M14: SÍ | N14: NO | O14: El teléfono es un tipo de Punto de Contacto que es un instrumento para reproducir sonidos a distancia; específicamente, uno en el que el sonido se convierte en impulsos eléctricos para su transmisión (ya sea por cable o ondas de radio) y luego se vuelve a convertir en sonido para ser utilizado por el punto de contacto receptor. | P14: Origen | Q14: No aplica | R14: No aplica | S14: 922927471 | T14: Alta | U14: Dimensión | V14: A demanda | W14: - Marketing - FFVV - Retencion de cartera - CX | X14: SÍ | Y14: Gobierno de Datos
A15: =TEXT(ROW()-2, "00000") -> 00013 | B15: CRM | C15: D001 | D15: Persona | E15: S001 | F15: Cliente | G15: Party Communication​ | H15: Información del cliente | I15: Dirección | J15: =B15&A15 -> CRM00013 | K15: Gaudy Sanchez | L15: SÍ | M15: SÍ | N15: NO | O15: Punto dentro de la geografía en donde se ubica una entidad. | P15: Origen | Q15: No aplica | R15: No aplica | S15: Mz. L, Lt. 21, Av. Miguel iglesias, Lima, SJM | T15: Alta | U15: Dimensión | V15: A demanda | W15: - Marketing - FFVV | X15: SÍ | Y15: Gobierno de Datos
A16: =TEXT(ROW()-2, "00000") -> 00014 | B16: CRM | C16: D001 | D16: Persona | E16: S002 | F16: Corredor | G16: Party Role | H16: Relación comercial | I16: Intermediario | J16: =B16&A16 -> CRM00014 | K16: Arturo Yaipen | L16: SÍ | M16: NO | N16: NO | O16: Persona natural o jurídica que intermedia en la colocación de productos emitidos por compañías de seguros, con clientes personas naturales o jurídicas. Su relación con la compañía es mediante un contrato de intermediación o agenciamiento. | P16: Origen | Q16: No aplica | R16: No aplica | S16: ADRIGAS E.I.R.L Ramirez Rojas, Ronaldo Hugo | T16: Alta | U16: Dimensión | V16: A demanda | W16: - Comercial - Emisión - Riesgos - Tecnica | X16: SÍ | Y16: Gobierno de Datos
A17: =TEXT(ROW()-2, "00000") -> 00015 | B17: CRM | C17: D001 | D17: Persona | E17: S001 | F17: Cliente | G17: Party Role | H17: Información del cliente | I17: Rol persona | J17: =B17&A17 -> CRM00015 | K17: Gaudy Sanchez | L17: NO | M17: NO | N17: NO | O17: Definido como el rol que desempeña la persona en la empresa, si es colaborador, cliente y/o agente (bróker o comercializador). | P17: Origen | Q17: No aplica | R17: No aplica | S17: Cliente Personal Agente | T17: Media | U17: Dimensión | V17: A demanda | W17: - Marketing - FFVV - Retencion de cartera - CX | X17: SÍ | Y17: Gobierno de Datos
A18: =TEXT(ROW()-2, "00000") -> 00016 | B18: CRM | C18: D001 | D18: Persona | E18: S001 | F18: Cliente | G18: Party Role | H18: Información del cliente | I18: Rol cliente | J18: =B18&A18 -> CRM00016 | K18: Gaudy Sanchez | L18: NO | M18: NO | N18: NO | O18: Indica el rol que cumple el cliente ante una póliza. | P18: Origen | Q18: No aplica | R18: No aplica | S18: 1. Asegurado 2. Contratante 3. Pagador 4. Beneficiario 5. Dependiente 6. Agrupador 7. Beneficiario Contingente | T18: Media | U18: Dimensión | V18: A demanda | W18: - NO | X18: SÍ | Y18: Gobierno de Datos
A19: 00013 | B19: CRM | C19: D001 | D19: Persona | E19: S001 | F19: Cliente | G19: Party Role | H19: Participante de la póliza | I19: Asegurado | J19: CRM00013 | K19: Gaudy Sanchez | L19: SÍ | M19: NO | N19: NO | O19: Persona o bien que, mediante el pago de una prima, recibe la protección del Asegurador, quien se obliga a indemnizar las pérdidas o los perjuicios que puedan sobrevenir a la otra parte en casos determinados, fortuitos o de fuerza mayor. Es menester aclarar que en el Seguro de Vida, la persona a quien se le llama "Asegurado" es aquella cuya cabeza se contrata el seguro, la cual no tiene que ser forzosamente la misma que la del contratante o persona que estipula el seguro o firma la Póliza con el Asegurador obligándose a pagar las primas del seguro. | P19: Origen | Q19: No aplica | R19: No aplica | S19: María Uriarte Suárez | T19: Alta | U19: Dimensión | V19: A demanda | W19: - NO | X19: SÍ | Y19: Gobierno de Datos
A20: 00014 | B20: CRM | C20: D001 | D20: Persona | E20: S001 | F20: Cliente | G20: Party Role | H20: Participante de la póliza | I20: Contratante | J20: CRM00014 | K20: Gaudy Sanchez | L20: NO | M20: NO | N20: NO | O20: Persona natural o jurídica u organismo del Estado determinado en las condiciones particulares de la póliza, que contrata el seguro y se obliga al pago de la prima. Puede ser también el Asegurado. El contratante es el único que puede solicitar modificaciones a la póliza, asimismo es el que propone los montos asegurados y los riesgos que necesita. En el caso de un seguro individual puede además tener la calidad de asegurado. | P20: Origen | Q20: No aplica | R20: No aplica | S20: María Uriarte Suárez La Positiva Seguros | T20: Media | U20: Dimensión | V20: A demanda | W20: - NO | X20: SÍ | Y20: Gobierno de Datos
A21: 00015 | B21: CRM | C21: D001 | D21: Persona | E21: S001 | F21: Cliente | G21: Party Role | H21: Participante de la póliza | I21: Pagador | J21: CRM00015 | K21: Gaudy Sanchez | L21: NO | M21: NO | N21: NO | O21: Persona responsable del pago de la prima (puede o no coincidir con el contratante). | P21: Origen | Q21: No aplica | R21: No aplica | S21: María Uriarte Suárez La Positiva Seguros | T21: Media | U21: Dimensión | V21: A demanda | W21: - NO | X21: SÍ | Y21: Gobierno de Datos
A22: 00016 | B22: CRM | C22: D001 | D22: Persona | E22: S001 | F22: Cliente | G22: Party Role | H22: Participante de la póliza | I22: Benficiario | J22: CRM00016 | K22: Gaudy Sanchez | L22: SÍ | M22: NO | N22: NO | O22: En los seguros que cubran el riesgo de fallecimiento de una persona, el plazo de prescripción para el beneficiario se computa desde que este conoce la existencia del beneficio. | P22: Origen | Q22: No aplica | R22: No aplica | S22: María Uriarte Suárez | T22: Alta | U22: Dimensión | V22: A demanda | W22: - NO | X22: SÍ | Y22: Gobierno de Datos
A23: 00018 | B23: CRM | C23: D001 | D23: Persona | E23: S001 | F23: Cliente | G23: Party Role | H23: Participante de la póliza | I23: Agrupador | J23: CRM00018 | K23: Gaudy Sanchez | L23: NO | M23: NO | N23: NO | O23: Identificador que agrupa pólizas bajo un mismo grupo económico. | P23: Origen | Q23: No aplica | R23: No aplica | S23: G.E. Marina de Guerra del Perú | T23: Media | U23: Dimensión | V23: A demanda | W23: - NO | X23: SÍ | Y23: Gobierno de Datos
A24: 00018 | B24: CRM | C24: D001 | D24: Persona | E24: S001 | F24: Cliente | G24: Party Relationship | H24: Relación entre personas | I24: Parentesco | J24: CRM00018 | K24: Gaudy Sanchez | L24: SÍ | M24: NO | N24: NO | O24: Relación familiar o vínculo legal que existe entre el titular de la póliza y otra persona asociada a ella, como un beneficiario, dependiente o asegurado adicional. | P24: Origen | Q24: No aplica | R24: No aplica | S24: Hermano/a Padre Madre Hijo Concubina | T24: Alta | U24: Dimensión | V24: A demanda | W24: - NO | X24: NO | Y24: Gobierno de Datos
A25: =TEXT(ROW()-2, "00000") -> 00023 | B25: CRM | C25: D002 | D25: Persona | E25: S012 | F25: Cliente | G25: Person | H25: Información de la persona | I25: Fecha de fallecimiento | J25: =B25&A25 -> CRM00023 | K25: RRGG (Patricia Paredes) SOAT (C. Illanes) VIDA (Victor Lazo) | L25: SÍ | M25: SÍ | N25: NO | O25: Fecha en la que falleció la persona asegurada y/o afectada. | P25: Origen | Q25: No aplica | R25: No aplica | S25: 36192 | T25: Alta | U25: Dimensión | V25: A demanda | X25: SÍ | Y25: Gobierno de Datos
A26: =TEXT(ROW()-2, "00000") -> 00024 | B26: CRM | C26: D002 | D26: Persona | E26: S015 | F26: Cliente | G26: Party_Role | H26: Participante del siniestro | I26: Persona afectada | J26: =B26&A26 -> CRM00024 | K26: RRGG (Patricia Paredes) SALUD (Eva Tomas) AUTOS (C. Illanes) SOAT (C. Illanes) VIDA (Victor Lazo) | L26: SÍ | M26: SÍ | N26: NO | O26: Persona natural y/o jurídica afectada que sufrió un accidente, daño o pérdida. | P26: Origen | Q26: No aplica | R26: No aplica | S26: Ana Rivas Uriarte | T26: Alta | U26: Dimensión | V26: A demanda | X26: SÍ | Y26: Gobierno de Datos
A27: =TEXT(ROW()-2, "00000") -> 00025 | B27: CRM | C27: D002 | D27: Persona | E27: S018 | F27: Cliente | G27: Party_Role | H27: Participante del siniestro | I27: Conductor | J27: =B27&A27 -> CRM00025 | K27: AUTOS (C. Illanes) SOAT (C. Illanes) | L27: SÍ | M27: SÍ | N27: NO | O27: Nombre del conductor del vehiculo participante en el siniestro. | P27: Origen | Q27: No aplica | R27: No aplica | S27: Ana Rivas Uriarte | T27: Alta | U27: Dimensión | V27: A demanda | X27: SÍ | Y27: Gobierno de Datos
A28: =TEXT(ROW()-2, "00000") -> 00026 | B28: CRM | C28: D002 | D28: Persona | E28: S021 | F28: Proveedor | G28: Party_Role | H28: Participante del siniestro | I28: Médico | J28: =B28&A28 -> CRM00026 | K28: SALUD (Eva Tomas) VIDA (Victor Lazo) | L28: NO | M28: SÍ | N28: NO | O28: Profesional de la salud que certifica oficialmente el fallecimiento o la invalidez del asegurado. | P28: Origen | Q28: No aplica | R28: No aplica | S28: Ana Rivas Uriarte | T28: Baja | U28: Dimensión | V28: A demanda | X28: SÍ | Y28: Gobierno de Datos
A29: =TEXT(ROW()-2, "00000") -> 00027 | B29: CRM | C29: D002 | D29: Persona | E29: S022 | F29: Cliente | G29: Organization | H29: Información del participante en el siniestro | I29: Actividad SCTR | J29: =B29&A29 -> CRM00027 | K29: VIDA (Victor Lazo) | L29: SÍ | M29: NO | N29: NO | O29: Clasificación de la actividad económica del asegurado, según lo establecido en el Seguro Complementario de Trabajo de Riesgo (SCTR), indicando si corresponde a minería o no minería. | P29: Calculado | Q29: CIIU --> Código CIIU M --> Minería o No minería | R29: CASE WHEN substr(CIIU,1,2) IN ('05','06','07','08','09') THEN 'Minería' ELSE 'No minería' END AS M | S29: Minería No minería | T29: Alta | U29: Dimensión | V29: A demanda | X29: SÍ | Y29: Gobierno de Datos
A30: =TEXT(ROW()-2, "00000") -> 00028 | B30: CRM | C30: D002 | D30: Póliza | E30: S003 | F30: Emisión y Transformación Colocaciones | G30: Party Role | H30: Relación comercial | I30: Canal de venta | J30: =B30&A30 -> CRM00028 | K30: VIDA (Victor Lazo) SALUD (Juan Camayoc) | L30: NO | M30: NO | N30: NO | O30: Medio o vía a través del cual se concretó la venta de la póliza. | P30: Origen | Q30: No aplica | R30: No tiene cálculo | S30: FFVV | T30: Media | U30: Dimensión | V30: A demanda | X30: SÍ | Y30: Gobierno de Datos
A31: =TEXT(ROW()-2, "00000") -> 00029 | B31: CRM | C31: D002 | D31: Póliza | E31: S003 | F31: Emisión y Transformación Colocaciones | G31: Organization | H31: Información de póliza | I31: Oficina | J31: =B31&A31 -> CRM00029 | K31: VIDA (Victor Lazo) RRGG (Daniel Iwamoto) SALUD (Juan Camayoc) AUTOS (Juan Calixtro) SOAT (Jorge Shimizu) | L31: SÍ | M31: NO | N31: NO | O31: Establecimientos físicos a través de los cuales la empresa atiende al público para realizar la gestión de la póliza. | P31: Origen | Q31: No aplica | R31: No tiene cálculo | S31: San Isidro Oficina | T31: Media | U31: Dimensión | V31: A demanda | X31: SÍ | Y31: Gobierno de Datos
A32: =TEXT(ROW()-2, "00000") -> 00030 | B32: MidlleTier | C32: D002 | D32: Persona | E32: S022 | F32: Cliente | H32: Información del cliente | I32: País | J32: =B32&A32 -> MidlleTier00030 | K32: Gaudy Sanchez | L32: NO | M32: SÍ | N32: NO | O32: Entidad geopolítica que identifica el Estado soberano donde se encuentra ubicado el domicilio principal del cliente o de la persona registrada en el sistema. | P32: Origen | Q32: No aplica | R32: No aplica | S32: Perú | T32: Baja | U32: Dimensión | V32: A demanda | W32: No aplica | X32: NO | Y32: Gobierno de Datos
A33: =TEXT(ROW()-2, "00000") -> 00031 | B33: MidlleTier | C33: D002 | D33: Persona | E33: S022 | F33: Cliente | H33: Información del cliente | I33: Departamento | J33: =B33&A33 -> MidlleTier00031 | K33: Gaudy Sanchez | L33: SÍ | M33: SÍ | N33: NO | O33: División administrativa de primer nivel que identifica la región del estado peruano donde se encuentra ubicado el domicilio del cliente o de la persona registrada. | P33: Origen | Q33: No aplica | R33: No aplica | S33: Lima | T33: Media | U33: Dimensión | V33: A demanda | W33: Marketing, Experiencia del cliente, Plataforma, Televentas, FFVV Digital | X33: NO | Y33: Gobierno de Datos
A34: =TEXT(ROW()-2, "00000") -> 00032 | B34: MidlleTier | C34: D002 | D34: Persona | E34: S022 | F34: Cliente | H34: Información del cliente | I34: Provincia | J34: =B34&A34 -> MidlleTier00032 | K34: Gaudy Sanchez | L34: SÍ | M34: SÍ | N34: NO | O34: División administrativa de segundo nivel que identifica la provincia del estado peruano donde se encuentra ubicado el domicilio del cliente o de la persona registrada. | P34: Origen | Q34: No aplica | R34: No aplica | S34: Lima | T34: Media | U34: Dimensión | V34: A demanda | W34: Marketing, Experiencia del cliente | X34: NO | Y34: Gobierno de Datos
A35: =TEXT(ROW()-2, "00000") -> 00033 | B35: MidlleTier | C35: D002 | D35: Persona | E35: S022 | F35: Cliente | H35: Información del cliente | I35: Distrito | J35: =B35&A35 -> MidlleTier00033 | K35: Gaudy Sanchez | L35: SÍ | M35: SÍ | N35: NO | O35: División administrativa de tercer nivel que identifica el distrito del estado peruano donde se encuentra ubicado el domicilio del cliente o de la persona registrada. | P35: Origen | Q35: No aplica | R35: No aplica | S35: Surco | T35: Media | U35: Dimensión | V35: A demanda | W35: Marketing, Experiencia del cliente | X35: NO | Y35: Gobierno de Datos
A36: =TEXT(ROW()-2, "00000") -> 00034 | B36: MidlleTier | C36: D002 | D36: Persona | E36: S022 | F36: Cliente | G36: Person | H36: Información del cliente | I36: Edad | J36: =B36&A36 -> MidlleTier00034 | K36: Gaudy Sanchez | L36: SÍ | M36: SÍ | N36: NO | O36: Cantidad de años cumplidos de la persona, calculada a partir de su fecha de nacimiento a la fecha actual. | P36: Calculado | Q36: - FN: Fecha de nacimiento, - FA: Fecha actual | R36: FA - FN | S36: 20 | T36: Baja | U36: Dimensión | V36: A demanda | W36: No aplica | X36: NO | Y36: Gobierno de Datos
A37: =TEXT(ROW()-2, "00000") -> 00035 | B37: MidlleTier | C37: D002 | D37: Persona | E37: S022 | F37: Cliente | G37: Person | H37: Información del cliente | I37: Estado Civil | J37: =B37&A37 -> MidlleTier00035 | K37: Gaudy Sanchez | L37: NO | M37: SÍ | N37: NO | O37: Condición legal que identifica la situación civil de la persona (soltero, casado, conviviente, divorciado, viudo, entre otros), conforme a la normativa vigente. | P37: Origen | Q37: No aplica | R37: No aplica | S37: Soltero | T37: Baja | U37: Dimensión | V37: A demanda | W37: No aplica | X37: NO | Y37: Gobierno de Datos
A38: =TEXT(ROW()-2, "00000") -> 00036 | B38: MidlleTier | C38: D002 | D38: Persona | E38: S022 | F38: Corredor | G38: Party_Role | H38: Relación comercial | I38: Comercializador | J38: =B38&A38 -> MidlleTier00036 | K38: Arturo Yaipen | L38: SÍ | M38: NO | N38: NO | O38: Persona jurídica que participa en la colocación y venta de pólizas de seguros, actuando como intermediario en el proceso de distribución de productos aseguradores. | P38: Origen | Q38: No aplica | R38: No aplica | S38: Bodega ABC | T38: Baja | U38: Dimensión | V38: A demanda | W38: No aplica | X38: SÍ | Y38: Gobierno de Datos
A39: =TEXT(ROW()-2, "00000") -> 00037 | B39: MidlleTier | C39: D002 | D39: Persona | E39: S022 | F39: Corredor | H39: Relación comercial | I39: Banca-Seguros | J39: =B39&A39 -> MidlleTier00037 | K39: Arturo Yaipen | L39: SÍ | M39: NO | N39: NO | O39: Canal de distribución mediante el cual una entidad financiera comercializa productos de seguros a través de su red de agencias, plataformas o medios digitales, en virtud de un convenio con la aseguradora. | P39: Origen | Q39: No aplica | R39: No aplica | S39: BBVA Perú | T39: Alta | U39: Dimensión | V39: Trimestral | W39: - Suscripción - Emisión - Cobranzas - Comercial - CNT - Auditoría | X39: SÍ | Y39: Gobierno de Datos
A40: =TEXT(ROW()-2, "00000") -> 00038 | B40: MidlleTier | C40: D002 | D40: Persona | E40: S022 | F40: Proveedor | G40: Party_Role | H40: Información del proveedor | I40: Proveedor | J40: =B40&A40 -> MidlleTier00038 | K40: Alvaro Kutsuma | L40: SÍ | M40: SÍ | N40: NO | O40: Persona natural o jurídica que brinda a La Positiva servicios de carácter administrativo o técnico indispensables para la operación del negocio, atención de los clientes, procesos de suscripción, gestión de siniestros o servicios complementarios. | P40: Origen | Q40: No aplica | R40: No aplica | S40: Navarrete Flexo Impresiones Hospital Rebagliati | T40: Media | U40: Dimensión | V40: A demanda | W40: - Toda LP | X40: SÍ | Y40: Gobierno de Datos
A41: =TEXT(ROW()-2, "00000") -> 00039 | B41: MidlleTier | C41: D002 | D41: Persona | E41: S022 | F41: Organismo Regulador | G41: Party_Role | H41: Información del representante legal | I41: Representante Legal Proveedores | J41: =B41&A41 -> MidlleTier00039 | K41: Fiorella Leva Vanessa Toribio | L41: SÍ | M41: SÍ | N41: NO | O41: Es aquel que cuenta con facultades de representación ya sea de una persona natural o de una persona jurídica. Estas facultades permiten que el representante actúe como si se tratase del propio titular de los derechos, contando con facultades para suscribir contratos. | P41: Origen | Q41: No aplica | R41: No aplica | S41: Abogado Juan Pérez Apoderado de Seguros XYZ SAC | T41: Baja | U41: Dimensión | V41: A demanda | W41: No aplica | X41: SÍ | Y41: Gobierno de Datos
O55: Legal Intiucional y negacio
O57: CLIENTES EMPRESAS --> REPRESNETANTE LEGAL | P57: DE ACUERDO A DOCUMENTO DE IDENTIDAD
O58: PERSONA NATURAL -- NOMBRES PAELLIDOS --> | P58: DE ACUERDO A DOCUMENTO DE IDENTIDAD
O59: PERSONA JURIDCA -- RAZON SOCIAL
O60: FORMALIDADES : UNA CARTA PODER ANTE NOTARIA O ALGUN REGISTRO PUBLICO
O61: FIRMA LEGALIZADA ANTE NOATRIO O REGISTROS PUBLICOS, NO ES NECESARIO NI ESTA PREDEFINIDIA Y DEPENDE DEL TRAMITE PADRES CON PARENSTSCO CONYIGAL DE ESPOSO Q LOS 2 HACEN DE RESPRESENTACION LEGAL

Sheet 2. Reglas de Calidad
A1: Iniciativa | B1: Caso de uso | C1: ID Regla de calidad | D1: Término de Negocio | E1: Tabla del Entidad de Dato (OMG) | F1: Campo del Entidad de Dato (OMG) | G1: Nombre del Entidad de Dato | H1: Descripción de Regla de calidad | I1: Tipo de regla de calidad | J1: Cumplimiento regla de Calidad (CORE) | K1: Principio de calidad asociado | L1: Umbral Superior | M1: Umbral Inferior | N1: Periodicidad | O1: Aplicación | P1: Data Owner | Q1: Validado por Data Owner
A2: Iniciativa | B2: Caso de uso que corresponde | C2: Identificador de Regla de Calidad | E2: Nombre de la entidad que se visualiza en la documentación de OMG | F2: Campo de la entidad que se visualiza en la documentación de OMG | G2: Nombre único con el cual el Negocio identifica a la Entidad de Dato | H2: Describir las propiedades, características y exclusiones relacionadas al dato, y lógicas necesarias para su entendimiento | I2: Indica si se trata de una regla básica o una regla experta | J2: Validar si la regla se cumple dentro del CORE. | K2: Se debe indicar el principio de calidad al que se hace referencia (Consistencia, completitud, etc) | L2: Indica el límite superior sobre los valores que puede tomar el dato | M2: Indica el límite inferior sobre los valores que puede tomar el dato | N2: Frecuencia con la que se aplica | O2: Nombre del aplicativo en el que se consulta/visualiza el dato | P2: Nombre de la persona responsable de la gestión del dato. | Q2: Una vez revisado por el Data Owner se coloca Sí en señal de conformidad con la definición
A3: CRM | B3: CRM | C3: =+UPPER(MID(B3,1,3))&"00"&COUNTA(B$3:B3) -> CRM001 | D3: Cliente | E3: Customer | F3: Party_Identifier | G3: Id Cliente | H3: Sin duplicidad (Valor único). | I3: Básica | J3: SÍ | K3: Consistencia | L3: 1 | M3: 0.98 | N3: A demanda | O3: INSIS, VTIME, INSUNIX | P3: Gaudy Sanchez | Q3: SÍ
A4: CRM | C4: =+UPPER(MID(B4,1,3))&"00"&COUNTA(B$3:B4) -> 001 | D4: Cliente | E4: Customer | F4: Party_Identifier | G4: Id Cliente | H4: Debe ser entero positivo.(Dependiendo del Core el Id de cliente tiene letras) | I4: Básica | J4: SÍ | K4: Validez | L4: 1 | M4: 0.98 | N4: A demanda | O4: INSIS, VTIME, INSUNIX | P4: Gaudy Sanchez | Q4: SÍ
A5: CRM | C5: =+UPPER(MID(B5,1,3))&"00"&COUNTA(B$3:B5) -> 001 | D5: Cliente | E5: Customer | F5: Party_Identifier | G5: Id Cliente | H5: No debe modificarse una vez creado. | I5: Básica | J5: SÍ | K5: Integridad | L5: 1 | M5: 0.98 | N5: A demanda | O5: INSIS, VTIME, INSUNIX | P5: Gaudy Sanchez | Q5: SÍ
A6: CRM | C6: =+UPPER(MID(B6,1,3))&"00"&COUNTA(B$3:B6) -> 001 | D6: Cliente | E6: Customer | F6: Party_Identifier | G6: Id Cliente | H6: No se permiten valores vacíos o nulos. | I6: Básica | J6: SÍ | K6: Completitud | L6: 1 | M6: 0.98 | N6: A demanda | O6: INSIS, VTIME, INSUNIX | P6: Gaudy Sanchez | Q6: SÍ
A7: CRM | C7: =+UPPER(MID(B7,1,3))&"00"&COUNTA(B$3:B7) -> 001 | D7: Cliente | E7: Customer | F7: Party_Identifier | G7: Id Cliente | H7: No acepta carácteres especiales. | I7: Básica | J7: NO | K7: Validez | L7: 1 | M7: 0.98 | N7: A demanda | O7: INSIS, VTIME, INSUNIX | P7: Gaudy Sanchez | Q7: SÍ
A8: CRM | B8: CRM | C8: =+UPPER(MID(B8,1,3))&"00"&COUNTA(B$3:B8) -> CRM002 | D8: Cliente | E8: Person | F8: First_Name | G8: Primer Nombre | H8: Longitud de 40 caracteres | I8: Básica | J8: NO | K8: Validez | L8: 1 | M8: 0.98 | N8: A demanda | O8: INSIS, VTIME, INSUNIX | P8: Gaudy Sanchez | Q8: SÍ
A9: CRM | C9: =+UPPER(MID(B9,1,3))&"00"&COUNTA(B$3:B9) -> 002 | D9: Cliente | E9: Person | F9: First_Name | G9: Primer Nombre | H9: No se acepta números (0-9). | I9: Básica | J9: NO | K9: Validez | L9: 1 | M9: 0.98 | N9: A demanda | O9: INSIS, VTIME, INSUNIX | P9: Gaudy Sanchez | Q9: SÍ
A10: CRM | C10: =+UPPER(MID(B10,1,3))&"00"&COUNTA(B$3:B10) -> 002 | D10: Cliente | E10: Person | F10: First_Name | G10: Primer Nombre | H10: No se permiten valores vacíos o nulos. | I10: Básica | J10: SÍ | K10: Completitud | L10: 1 | M10: 0.98 | N10: A demanda | O10: INSIS, VTIME, INSUNIX | P10: Gaudy Sanchez | Q10: SÍ
A11: CRM | C11: =+UPPER(MID(B11,1,3))&"00"&COUNTA(B$3:B11) -> 002 | D11: Cliente | E11: Person | F11: First_Name | G11: Primer Nombre | H11: No acepta carácteres especiales, excepto: Apostrofe(') y Guiones (-). | I11: Básica | J11: NO | K11: Validez | L11: 1 | M11: 0.98 | N11: A demanda | O11: INSIS, VTIME, INSUNIX | P11: Gaudy Sanchez | Q11: SÍ
A12: CRM | C12: =+UPPER(MID(B12,1,3))&"00"&COUNTA(B$3:B12) -> 002 | D12: Cliente | E12: Person | F12: First_Name | G12: Primer Nombre | H12: No se acepta nombres de menos de 2 carácteres. | I12: Básica | J12: NO | K12: Validez | L12: 1 | M12: 0.98 | N12: A demanda | O12: INSIS, VTIME, INSUNIX | P12: Gaudy Sanchez | Q12: SÍ
A13: CRM | C13: =+UPPER(MID(B13,1,3))&"00"&COUNTA(B$3:B13) -> 002 | D13: Cliente | E13: Person | F13: First_Name | G13: Primer Nombre | H13: No se acepta saltos de línea. | I13: Básica | J13: SÍ | K13: Validez | L13: 1 | M13: 0.98 | N13: A demanda | O13: INSIS, VTIME, INSUNIX | P13: Gaudy Sanchez | Q13: SÍ
A14: CRM | C14: =+UPPER(MID(B14,1,3))&"00"&COUNTA(B$3:B14) -> 002 | D14: Cliente | E14: Person | F14: First_Name | G14: Primer Nombre | H14: No se acepta tabulaciones. | I14: Básica | J14: NO | K14: Validez | L14: 1 | M14: 0.98 | N14: A demanda | O14: INSIS, VTIME, INSUNIX | P14: Gaudy Sanchez | Q14: SÍ
A15: CRM | C15: =+UPPER(MID(B15,1,3))&"00"&COUNTA(B$3:B15) -> 002 | D15: Cliente | E15: Person | F15: First_Name | G15: Primer Nombre | H15: No debe haber más de 2 tíldes | I15: Básica | J15: NO | K15: Validez | L15: 1 | M15: 0.98 | N15: A demanda | O15: INSIS, VTIME, INSUNIX | P15: Gaudy Sanchez | Q15: SÍ
A16: CRM | C16: =+UPPER(MID(B16,1,3))&"00"&COUNTA(B$3:B16) -> 002 | D16: Cliente | E16: Person | F16: First_Name | G16: Primer Nombre | H16: Se aceptan nombres compuestos como O’BRYAN | I16: Básica | J16: NO | K16: Validez | L16: 1 | M16: 0.98 | N16: A demanda | O16: INSIS, VTIME, INSUNIX | P16: Gaudy Sanchez | Q16: SÍ
A17: CRM | C17: =+UPPER(MID(B17,1,3))&"00"&COUNTA(B$3:B17) -> 002 | D17: Cliente | E17: Person | F17: First_Name | G17: Primer Nombre | H17: Debe coincidir con documento de identifidad registrado. | I17: Experta | J17: SÍ | K17: Precisión | L17: 1 | M17: 0.98 | N17: A demanda | O17: INSIS, VTIME, INSUNIX | P17: Gaudy Sanchez | Q17: SÍ
A18: CRM | C18: =+UPPER(MID(B18,1,3))&"00"&COUNTA(B$3:B18) -> 002 | D18: Cliente | E18: Person | F18: First_Name | G18: Primer Nombre | H18: Solo aplica para persona natural. | I18: Básica | J18: SÍ | K18: Integridad | L18: 1 | M18: 0.98 | N18: A demanda | O18: INSIS, VTIME, INSUNIX | P18: Gaudy Sanchez | Q18: SÍ
A19: CRM | C19: =+UPPER(MID(B19,1,3))&"00"&COUNTA(B$3:B19) -> 002 | D19: Cliente | E19: Person | F19: First_Name | G19: Primer Nombre | H19: Los nombres no alternan mayúsculas/minúsculas de forma errática. Todo mayúsculas. | I19: Básica | J19: NO | K19: Validez | L19: 1 | M19: 0.98 | N19: A demanda | O19: INSIS, VTIME, INSUNIX | P19: Gaudy Sanchez | Q19: SÍ
A20: CRM | C20: =+UPPER(MID(B20,1,3))&"00"&COUNTA(B$3:B20) -> 002 | D20: Cliente | E20: Person | F20: First_Name | G20: Primer Nombre | H20: Un nombre no comienza con símbolos. | I20: Básica | J20: NO | K20: Validez | L20: 1 | M20: 0.98 | N20: A demanda | O20: INSIS, VTIME, INSUNIX | P20: Gaudy Sanchez | Q20: SÍ
A21: CRM | B21: CRM | C21: =+UPPER(MID(B21,1,3))&"00"&COUNTA(B$3:B21) -> CRM003 | D21: Cliente | E21: Person | F21: Middle_Name | G21: Segundo Nombre | H21: Longitud de 40 caracteres | I21: Básica | J21: NO | K21: Validez | L21: 1 | M21: 0.98 | N21: A demanda | O21: INSIS, VTIME, INSUNIX | P21: Gaudy Sanchez | Q21: SÍ
A22: CRM | C22: =+UPPER(MID(B22,1,3))&"00"&COUNTA(B$3:B22) -> 003 | D22: Cliente | E22: Person | F22: Middle_Name | G22: Segundo Nombre | H22: No se acepta números (0-9). | I22: Básica | J22: NO | K22: Validez | L22: 1 | M22: 0.98 | N22: A demanda | O22: INSIS, VTIME, INSUNIX | P22: Gaudy Sanchez | Q22: SÍ
A23: CRM | C23: =+UPPER(MID(B23,1,3))&"00"&COUNTA(B$3:B23) -> 003 | D23: Cliente | E23: Person | F23: Middle_Name | G23: Segundo Nombre | H23: Se permiten valores vacíos o nulos. | I23: Básica | J23: SÍ | K23: Completitud | L23: 1 | M23: 0.98 | N23: A demanda | O23: INSIS, VTIME, INSUNIX | P23: Gaudy Sanchez | Q23: SÍ
A24: CRM | C24: =+UPPER(MID(B24,1,3))&"00"&COUNTA(B$3:B24) -> 003 | D24: Cliente | E24: Person | F24: Middle_Name | G24: Segundo Nombre | H24: No acepta carácteres especiales, excepto: Apostrofe(') y Guiones (-). | I24: Básica | J24: NO | K24: Validez | L24: 1 | M24: 0.98 | N24: A demanda | O24: INSIS, VTIME, INSUNIX | P24: Gaudy Sanchez | Q24: SÍ
A25: CRM | C25: =+UPPER(MID(B25,1,3))&"00"&COUNTA(B$3:B25) -> 003 | D25: Cliente | E25: Person | F25: Middle_Name | G25: Segundo Nombre | H25: No se acepta nombres de menos de 2 carácteres. | I25: Básica | J25: NO | K25: Validez | L25: 1 | M25: 0.98 | N25: A demanda | O25: INSIS, VTIME, INSUNIX | P25: Gaudy Sanchez | Q25: SÍ
A26: CRM | C26: =+UPPER(MID(B26,1,3))&"00"&COUNTA(B$3:B26) -> 003 | D26: Cliente | E26: Person | F26: Middle_Name | G26: Segundo Nombre | H26: No se acepta saltos de línea. | I26: Básica | J26: SÍ | K26: Validez | L26: 1 | M26: 0.98 | N26: A demanda | O26: INSIS, VTIME, INSUNIX | P26: Gaudy Sanchez | Q26: SÍ
A27: CRM | C27: =+UPPER(MID(B27,1,3))&"00"&COUNTA(B$3:B27) -> 003 | D27: Cliente | E27: Person | F27: Middle_Name | G27: Segundo Nombre | H27: No se acepta tabulaciones. | I27: Básica | J27: NO | K27: Validez | L27: 1 | M27: 0.98 | N27: A demanda | O27: INSIS, VTIME, INSUNIX | P27: Gaudy Sanchez | Q27: SÍ
A28: CRM | C28: =+UPPER(MID(B28,1,3))&"00"&COUNTA(B$3:B28) -> 003 | D28: Cliente | E28: Person | F28: Middle_Name | G28: Segundo Nombre | H28: No debe haber más de 2 tíldes | I28: Básica | J28: NO | K28: Validez | L28: 1 | M28: 0.98 | N28: A demanda | O28: INSIS, VTIME, INSUNIX | P28: Gaudy Sanchez | Q28: SÍ
A29: CRM | C29: =+UPPER(MID(B29,1,3))&"00"&COUNTA(B$3:B29) -> 003 | D29: Cliente | E29: Person | F29: Middle_Name | G29: Segundo Nombre | H29: Se aceptan nombres compuestos como O’BRYAN | I29: Básica | J29: SÍ | K29: Validez | L29: 1 | M29: 0.98 | N29: A demanda | O29: INSIS, VTIME, INSUNIX | P29: Gaudy Sanchez | Q29: SÍ
A30: CRM | C30: =+UPPER(MID(B30,1,3))&"00"&COUNTA(B$3:B30) -> 003 | D30: Cliente | E30: Person | F30: Middle_Name | G30: Segundo Nombre | H30: Debe coincidir con documento de identifidad registrado. | I30: Experta | J30: SÍ | K30: Precisión | L30: 1 | M30: 0.98 | N30: A demanda | O30: INSIS, VTIME, INSUNIX | P30: Gaudy Sanchez | Q30: SÍ
A31: CRM | C31: =+UPPER(MID(B31,1,3))&"00"&COUNTA(B$3:B31) -> 003 | D31: Cliente | E31: Person | F31: Middle_Name | G31: Segundo Nombre | H31: Solo aplica para persona natural. | I31: Básica | J31: SÍ | K31: Integridad | L31: 1 | M31: 0.98 | N31: A demanda | O31: INSIS, VTIME, INSUNIX | P31: Gaudy Sanchez | Q31: SÍ
A32: CRM | C32: =+UPPER(MID(B32,1,3))&"00"&COUNTA(B$3:B32) -> 003 | D32: Cliente | E32: Person | F32: Middle_Name | G32: Segundo Nombre | H32: Los nombres no alternan mayúsculas/minúsculas de forma errática. Todo mayúsculas. | I32: Básica | J32: NO | K32: Validez | L32: 1 | M32: 0.98 | N32: A demanda | O32: INSIS, VTIME, INSUNIX | P32: Gaudy Sanchez | Q32: SÍ
A33: CRM | B33: CRM | C33: =+UPPER(MID(B33,1,3))&"00"&COUNTA(B$3:B33) -> CRM004 | D33: Cliente | E33: Person | F33: Last_Name | G33: Apellido Paterno | H33: Longitud de 40 caracteres | I33: Básica | J33: NO | K33: Validez | L33: 1 | M33: 0.98 | N33: A demanda | O33: INSIS, VTIME, INSUNIX | P33: Gaudy Sanchez | Q33: SÍ
A34: CRM | C34: =+UPPER(MID(B34,1,3))&"00"&COUNTA(B$3:B34) -> 004 | D34: Cliente | E34: Person | F34: Last_Name | G34: Apellido Paterno | H34: No se acepta números (0-9). | I34: Básica | J34: NO | K34: Validez | L34: 1 | M34: 0.98 | N34: A demanda | O34: INSIS, VTIME, INSUNIX | P34: Gaudy Sanchez | Q34: SÍ
A35: CRM | C35: =+UPPER(MID(B35,1,3))&"00"&COUNTA(B$3:B35) -> 004 | D35: Cliente | E35: Person | F35: Last_Name | G35: Apellido Paterno | H35: No se permiten valores vacíos o nulos. | I35: Básica | J35: SÍ | K35: Completitud | L35: 1 | M35: 0.98 | N35: A demanda | O35: INSIS, VTIME, INSUNIX | P35: Gaudy Sanchez | Q35: SÍ
A36: CRM | C36: =+UPPER(MID(B36,1,3))&"00"&COUNTA(B$3:B36) -> 004 | D36: Cliente | E36: Person | F36: Last_Name | G36: Apellido Paterno | H36: No acepta carácteres especiales, excepto: Apostrofe(') y Guiones (-). | I36: Básica | J36: NO | K36: Validez | L36: 1 | M36: 0.98 | N36: A demanda | O36: INSIS, VTIME, INSUNIX | P36: Gaudy Sanchez | Q36: SÍ
A37: CRM | C37: =+UPPER(MID(B37,1,3))&"00"&COUNTA(B$3:B37) -> 004 | D37: Cliente | E37: Person | F37: Last_Name | G37: Apellido Paterno | H37: No se acepta apellidos de menos de 2 carácteres. | I37: Básica | J37: NO | K37: Validez | L37: 1 | M37: 0.98 | N37: A demanda | O37: INSIS, VTIME, INSUNIX | P37: Gaudy Sanchez | Q37: SÍ
A38: CRM | C38: =+UPPER(MID(B38,1,3))&"00"&COUNTA(B$3:B38) -> 004 | D38: Cliente | E38: Person | F38: Last_Name | G38: Apellido Paterno | H38: No se acepta saltos de línea. | I38: Básica | J38: SÍ | K38: Validez | L38: 1 | M38: 0.98 | N38: A demanda | O38: INSIS, VTIME, INSUNIX | P38: Gaudy Sanchez | Q38: SÍ
A39: CRM | C39: =+UPPER(MID(B39,1,3))&"00"&COUNTA(B$3:B39) -> 004 | D39: Cliente | E39: Person | F39: Last_Name | G39: Apellido Paterno | H39: No se acepta tabulaciones. | I39: Básica | J39: NO | K39: Validez | L39: 1 | M39: 0.98 | N39: A demanda | O39: INSIS, VTIME, INSUNIX | P39: Gaudy Sanchez | Q39: SÍ
A40: CRM | C40: =+UPPER(MID(B40,1,3))&"00"&COUNTA(B$3:B40) -> 004 | D40: Cliente | E40: Person | F40: Last_Name | G40: Apellido Paterno | H40: Se aceptan apellidos compuestos. Ej: Suárez-Martínez o Del Río | I40: Experta | J40: SÍ | K40: Validez | L40: 1 | M40: 0.98 | N40: A demanda | O40: INSIS, VTIME, INSUNIX | P40: Gaudy Sanchez | Q40: SÍ
A41: CRM | C41: =+UPPER(MID(B41,1,3))&"00"&COUNTA(B$3:B41) -> 004 | D41: Cliente | E41: Person | F41: Last_Name | G41: Apellido Paterno | H41: Entre cada palabra debe haber un solo espacio. | I41: Básica | J41: NO | K41: Validez | L41: 1 | M41: 0.98 | N41: A demanda | O41: INSIS, VTIME, INSUNIX | P41: Gaudy Sanchez | Q41: SÍ
A42: CRM | C42: =+UPPER(MID(B42,1,3))&"00"&COUNTA(B$3:B42) -> 004 | D42: Cliente | E42: Person | F42: Last_Name | G42: Apellido Paterno | H42: Debe coincidir con documento de identifidad registrado. | I42: Experta | J42: SÍ | K42: Precisión | L42: 1 | M42: 0.98 | N42: A demanda | O42: INSIS, VTIME, INSUNIX | P42: Gaudy Sanchez | Q42: SÍ
A43: CRM | C43: =+UPPER(MID(B43,1,3))&"00"&COUNTA(B$3:B43) -> 004 | D43: Cliente | E43: Person | F43: Last_Name | G43: Apellido Paterno | H43: Solo aplica para persona natural. | I43: Básica | J43: SÍ | K43: Integridad | L43: 1 | M43: 0.98 | N43: A demanda | O43: INSIS, VTIME, INSUNIX | P43: Gaudy Sanchez | Q43: SÍ
A44: CRM | C44: =+UPPER(MID(B44,1,3))&"00"&COUNTA(B$3:B44) -> 004 | D44: Cliente | E44: Person | F44: Last_Name | G44: Apellido Paterno | H44: Los nombres no alternan mayúsculas/minúsculas de forma errática. Todo mayúsculas. | I44: Básica | J44: NO | K44: Validez | L44: 1 | M44: 0.98 | N44: A demanda | O44: INSIS, VTIME, INSUNIX | P44: Gaudy Sanchez | Q44: SÍ
A45: CRM | B45: CRM | C45: =+UPPER(MID(B45,1,3))&"00"&COUNTA(B$3:B45) -> CRM005 | D45: Cliente | E45: Person | F45: Last_Name | G45: Apellido Materno | H45: Longitud de 40 caracteres | I45: Básica | J45: NO | K45: Validez | L45: 1 | M45: 0.98 | N45: A demanda | O45: INSIS, VTIME, INSUNIX | P45: Gaudy Sanchez | Q45: SÍ
A46: CRM | C46: =+UPPER(MID(B46,1,3))&"00"&COUNTA(B$3:B46) -> 005 | D46: Cliente | E46: Person | F46: Last_Name | G46: Apellido Materno | H46: No se acepta números (0-9). | I46: Básica | J46: NO | K46: Validez | L46: 1 | M46: 0.98 | N46: A demanda | O46: INSIS, VTIME, INSUNIX | P46: Gaudy Sanchez | Q46: SÍ
A47: CRM | C47: =+UPPER(MID(B47,1,3))&"00"&COUNTA(B$3:B47) -> 005 | D47: Cliente | E47: Person | F47: Last_Name | G47: Apellido Materno | H47: No se permiten valores Nulos o Vacios. | I47: Básica | J47: SÍ | K47: Completitud | L47: 1 | M47: 0.98 | N47: A demanda | O47: INSIS, VTIME, INSUNIX | P47: Gaudy Sanchez | Q47: SÍ
A48: CRM | C48: =+UPPER(MID(B48,1,3))&"00"&COUNTA(B$3:B48) -> 005 | D48: Cliente | E48: Person | F48: Last_Name | G48: Apellido Materno | H48: No acepta carácteres especiales, excepto: Apostrofe(') y Guiones (-). | I48: Básica | J48: NO | K48: Validez | L48: 1 | M48: 0.98 | N48: A demanda | O48: INSIS, VTIME, INSUNIX | P48: Gaudy Sanchez | Q48: SÍ
A49: CRM | C49: =+UPPER(MID(B49,1,3))&"00"&COUNTA(B$3:B49) -> 005 | D49: Cliente | E49: Person | F49: Last_Name | G49: Apellido Materno | H49: No se acepta apellidos de menos de 2 carácteres. | I49: Básica | J49: NO | K49: Validez | L49: 1 | M49: 0.98 | N49: A demanda | O49: INSIS, VTIME, INSUNIX | P49: Gaudy Sanchez | Q49: SÍ
A50: CRM | C50: =+UPPER(MID(B50,1,3))&"00"&COUNTA(B$3:B50) -> 005 | D50: Cliente | E50: Person | F50: Last_Name | G50: Apellido Materno | H50: No se acepta saltos de línea. | I50: Básica | J50: SÍ | K50: Validez | L50: 1 | M50: 0.98 | N50: A demanda | O50: INSIS, VTIME, INSUNIX | P50: Gaudy Sanchez | Q50: SÍ
A51: CRM | C51: =+UPPER(MID(B51,1,3))&"00"&COUNTA(B$3:B51) -> 005 | D51: Cliente | E51: Person | F51: Last_Name | G51: Apellido Materno | H51: No se acepta tabulaciones. | I51: Básica | J51: NO | K51: Validez | L51: 1 | M51: 0.98 | N51: A demanda | O51: INSIS, VTIME, INSUNIX | P51: Gaudy Sanchez | Q51: SÍ
A52: CRM | C52: =+UPPER(MID(B52,1,3))&"00"&COUNTA(B$3:B52) -> 005 | D52: Cliente | E52: Person | F52: Last_Name | G52: Apellido Materno | H52: Se aceptan apellidos compuestos. Ej: Suárez-Martínez o Del Río | I52: Experta | J52: SÍ | K52: Validez | L52: 1 | M52: 0.98 | N52: A demanda | O52: INSIS, VTIME, INSUNIX | P52: Gaudy Sanchez | Q52: SÍ
A53: CRM | C53: =+UPPER(MID(B53,1,3))&"00"&COUNTA(B$3:B53) -> 005 | D53: Cliente | E53: Person | F53: Last_Name | G53: Apellido Materno | H53: Entre cada palabra debe haber un solo espacio. | I53: Básica | J53: NO | K53: Validez | L53: 1 | M53: 0.98 | N53: A demanda | O53: INSIS, VTIME, INSUNIX | P53: Gaudy Sanchez | Q53: SÍ
A54: CRM | C54: =+UPPER(MID(B54,1,3))&"00"&COUNTA(B$3:B54) -> 005 | D54: Cliente | E54: Person | F54: Last_Name | G54: Apellido Materno | H54: Debe coincidir con documento de identifidad registrado. | I54: Experta | J54: SÍ | K54: Precisión | L54: 1 | M54: 0.98 | N54: A demanda | O54: INSIS, VTIME, INSUNIX | P54: Gaudy Sanchez | Q54: SÍ
A55: CRM | C55: =+UPPER(MID(B55,1,3))&"00"&COUNTA(B$3:B55) -> 005 | D55: Cliente | E55: Person | F55: Last_Name | G55: Apellido Materno | H55: Solo aplica para persona natural. | I55: Básica | J55: SÍ | K55: Integridad | L55: 1 | M55: 0.98 | N55: A demanda | O55: INSIS, VTIME, INSUNIX | P55: Gaudy Sanchez | Q55: SÍ
A56: CRM | C56: =+UPPER(MID(B56,1,3))&"00"&COUNTA(B$3:B56) -> 005 | D56: Cliente | E56: Person | F56: Last_Name | G56: Apellido Materno | H56: Los nombres no alternan mayúsculas/minúsculas de forma errática. Todo mayúsculas. | I56: Básica | J56: NO | K56: Validez | L56: 1 | M56: 0.98 | N56: A demanda | O56: INSIS, VTIME, INSUNIX | P56: Gaudy Sanchez | Q56: SÍ
A57: CRM | B57: CRM | C57: =+UPPER(MID(B57,1,3))&"00"&COUNTA(B$3:B57) -> CRM006 | D57: Cliente | E57: Organization | F57: Organization_Name | G57: Razón social | H57: Longitud de 100 caracteres | I57: Básica | J57: NO | K57: Validez | L57: 1 | M57: 0.98 | N57: A demanda | O57: INSIS, VTIME, INSUNIX | P57: Gaudy Sanchez | Q57: SÍ
A58: CRM | C58: =+UPPER(MID(B58,1,3))&"00"&COUNTA(B$3:B58) -> 006 | D58: Cliente | E58: Organization | F58: Organization_Name | G58: Razón social | H58: Sin duplicidad (Valor único, debe ser único a nivel semántico). | I58: Básica | J58: SÍ | K58: Consistencia | L58: 1 | M58: 0.98 | N58: A demanda | O58: INSIS, VTIME, INSUNIX | P58: Gaudy Sanchez | Q58: SÍ
A59: CRM | C59: =+UPPER(MID(B59,1,3))&"00"&COUNTA(B$3:B59) -> 006 | D59: Cliente | E59: Organization | F59: Organization_Name | G59: Razón social | H59: No acepta carácteres especiales, excepto: Ampersand(&),Guion(-), Punto(.) , Comillas dobles("), Barra diagonal(/). | I59: Básica | J59: NO | K59: Validez | L59: 1 | M59: 0.98 | N59: A demanda | O59: INSIS, VTIME, INSUNIX | P59: Gaudy Sanchez | Q59: SÍ
A60: CRM | C60: =+UPPER(MID(B60,1,3))&"00"&COUNTA(B$3:B60) -> 006 | D60: Cliente | E60: Organization | F60: Organization_Name | G60: Razón social | H60: Debe contener un tipo societario válido (S.A., S.A.C., S.R.L., E.I.R.L., etc.). | I60: Básica | J60: NO | K60: Validez | L60: 1 | M60: 0.98 | N60: A demanda | O60: INSIS, VTIME, INSUNIX | P60: Gaudy Sanchez | Q60: SÍ
A61: CRM | C61: =+UPPER(MID(B61,1,3))&"00"&COUNTA(B$3:B61) -> 006 | D61: Cliente | E61: Organization | F61: Organization_Name | G61: Razón social | H61: No se acepta saltos de línea. | I61: Básica | J61: SÍ | K61: Validez | L61: 1 | M61: 0.98 | N61: A demanda | O61: INSIS, VTIME, INSUNIX | P61: Gaudy Sanchez | Q61: SÍ
A62: CRM | C62: =+UPPER(MID(B62,1,3))&"00"&COUNTA(B$3:B62) -> 006 | D62: Cliente | E62: Organization | F62: Organization_Name | G62: Razón social | H62: No se acepta tabulaciones. | I62: Básica | J62: NO | K62: Validez | L62: 1 | M62: 0.98 | N62: A demanda | O62: INSIS, VTIME, INSUNIX | P62: Gaudy Sanchez | Q62: SÍ
A63: CRM | C63: =+UPPER(MID(B63,1,3))&"00"&COUNTA(B$3:B63) -> 006 | D63: Cliente | E63: Organization | F63: Organization_Name | G63: Razón social | H63: Debe coincidir con el nombre registrado ante SUNAT | I63: Experta | J63: NO | K63: Precisión | L63: 1 | M63: 0.98 | N63: A demanda | O63: INSIS, VTIME, INSUNIX | P63: Gaudy Sanchez | Q63: SÍ
A64: CRM | C64: =+UPPER(MID(B64,1,3))&"00"&COUNTA(B$3:B64) -> 006 | D64: Cliente | E64: Organization | F64: Organization_Name | G64: Razón social | H64: Solo aplica para persona jurídica. | I64: Básica | J64: SÍ | K64: Integridad | L64: 1 | M64: 0.98 | N64: A demanda | O64: INSIS, VTIME, INSUNIX | P64: Gaudy Sanchez | Q64: SÍ
A65: CRM | C65: =+UPPER(MID(B65,1,3))&"00"&COUNTA(B$3:B65) -> 006 | D65: Cliente | E65: Organization | F65: Organization_Name | G65: Razón social | H65: No se permiten valores vacíos o nulos. | I65: Básica | J65: SÍ | K65: Completitud | L65: 1 | M65: 0.98 | N65: A demanda | O65: INSIS, VTIME, INSUNIX | P65: Gaudy Sanchez | Q65: SÍ
A66: CRM | B66: CRM | C66: =+UPPER(MID(B66,1,3))&"00"&COUNTA(B$3:B66) -> CRM007 | D66: Tipo Persona | E66: Party | F66: Party _Type_Code | G66: Código Tipo Persona | H66: No debe modificarse una vez creado. | I66: Básica | J66: SÍ | K66: Integridad | L66: 1 | M66: 0.98 | N66: A demanda | O66: INSIS, VTIME | P66: Gaudy Sanchez | Q66: SÍ
A67: CRM | C67: =+UPPER(MID(B67,1,3))&"00"&COUNTA(B$3:B67) -> 007 | D67: Tipo Persona | E67: Party | F67: Party _Type_Code | G67: Código Tipo Persona | H67: No se permiten valores vacíos o nulos. | I67: Básica | J67: SÍ | K67: Completitud | L67: 1 | M67: 0.98 | N67: A demanda | O67: INSIS, VTIME | P67: Gaudy Sanchez | Q67: SÍ
A68: CRM | C68: =+UPPER(MID(B68,1,3))&"00"&COUNTA(B$3:B68) -> 007 | D68: Tipo Persona | E68: Party | F68: Party _Type_Code | G68: Código Tipo Persona | H68: Debe representar un valor categorizado según La Positiva. | I68: Básica | J68: SÍ | K68: Validez | L68: 1 | M68: 0.98 | N68: A demanda | O68: INSIS, VTIME | P68: Gaudy Sanchez | Q68: SÍ
A69: CRM | B69: CRM | C69: =+UPPER(MID(B69,1,3))&"00"&COUNTA(B$3:B69) -> CRM008 | D69: Tipo Persona | E69: Party _Type | F69: Party _Type_Name | G69: Tipo de persona | H69: Longitud de 40 caracteres | I69: Básica | J69: NO | K69: Validez | L69: 1 | M69: 0.98 | N69: A demanda | O69: INSIS, VTIME | P69: Gaudy Sanchez | Q69: SÍ
A70: CRM | C70: =+UPPER(MID(B70,1,3))&"00"&COUNTA(B$3:B70) -> 008 | D70: Tipo Persona | E70: Party _Type | F70: Party _Type_Name | G70: Tipo de persona | H70: Debe estar asignado a un código. | I70: Básica | J70: SÍ | K70: Integridad | L70: 1 | M70: 0.98 | N70: A demanda | O70: INSIS, VTIME | P70: Gaudy Sanchez | Q70: SÍ
A71: CRM | C71: =+UPPER(MID(B71,1,3))&"00"&COUNTA(B$3:B71) -> 008 | D71: Tipo Persona | E71: Party _Type | F71: Party _Type_Name | G71: Tipo de persona | H71: No se acepta números (0-9). | I71: Básica | J71: NO | K71: Validez | L71: 1 | M71: 0.98 | N71: A demanda | O71: INSIS, VTIME | P71: Gaudy Sanchez | Q71: SÍ
A72: CRM | C72: =+UPPER(MID(B72,1,3))&"00"&COUNTA(B$3:B72) -> 008 | D72: Tipo Persona | E72: Party _Type | F72: Party _Type_Name | G72: Tipo de persona | H72: No acepta carácteres especiales. | I72: Básica | J72: NO | K72: Validez | L72: 1 | M72: 0.98 | N72: A demanda | O72: INSIS, VTIME | P72: Gaudy Sanchez | Q72: SÍ
A73: CRM | C73: =+UPPER(MID(B73,1,3))&"00"&COUNTA(B$3:B73) -> 008 | D73: Tipo Persona | E73: Party _Type | F73: Party _Type_Name | G73: Tipo de persona | H73: No se acepta saltos de línea. | I73: Básica | J73: SÍ | K73: Validez | L73: 1 | M73: 0.98 | N73: A demanda | O73: INSIS, VTIME | P73: Gaudy Sanchez | Q73: SÍ
A74: CRM | C74: =+UPPER(MID(B74,1,3))&"00"&COUNTA(B$3:B74) -> 008 | D74: Tipo Persona | E74: Party _Type | F74: Party _Type_Name | G74: Tipo de persona | H74: No se acepta tabulaciones. | I74: Básica | J74: NO | K74: Validez | L74: 1 | M74: 0.98 | N74: A demanda | O74: INSIS, VTIME | P74: Gaudy Sanchez | Q74: SÍ
A75: CRM | C75: =+UPPER(MID(B75,1,3))&"00"&COUNTA(B$3:B75) -> 008 | D75: Tipo Persona | E75: Party _Type | F75: Party _Type_Name | G75: Tipo de persona | H75: Valores permitidos: - Persona Natural - Persona Jurídica | I75: Básica | J75: SÍ | K75: Validez | L75: 1 | M75: 0.98 | N75: A demanda | O75: INSIS, VTIME | P75: Gaudy Sanchez | Q75: SÍ
A76: CRM | C76: =+UPPER(MID(B76,1,3))&"00"&COUNTA(B$3:B76) -> 008 | D76: Tipo Persona | E76: Party _Type | F76: Party _Type_Name | G76: Tipo de persona | H76: No se permiten valores vacíos o nulos. | I76: Básica | J76: SÍ | K76: Completitud | L76: 1 | M76: 0.98 | N76: A demanda | O76: INSIS, VTIME | P76: Gaudy Sanchez | Q76: SÍ
A77: CRM | B77: CRM | C77: =+UPPER(MID(B77,1,3))&"00"&COUNTA(B$3:B77) -> CRM009 | D77: Documento de Identidad | E77: Party | F77: identification_Type_Code | G77: Código Tipo Documento | H77: No debe modificarse una vez creado. | I77: Básica | J77: SÍ | K77: Integridad | L77: 1 | M77: 0.98 | N77: A demanda | O77: INSIS, VTIME | P77: Gaudy Sanchez | Q77: SÍ
A78: CRM | C78: =+UPPER(MID(B78,1,3))&"00"&COUNTA(B$3:B78) -> 009 | D78: Documento de Identidad | E78: Party | F78: identification_Type_Code | G78: Código Tipo Documento | H78: No se permiten valores vacíos o nulos. | I78: Básica | J78: SÍ | K78: Completitud | L78: 1 | M78: 0.98 | N78: A demanda | O78: INSIS, VTIME | P78: Gaudy Sanchez | Q78: SÍ
A79: CRM | C79: =+UPPER(MID(B79,1,3))&"00"&COUNTA(B$3:B79) -> 009 | D79: Documento de Identidad | E79: Party | F79: identification_Type_Code | G79: Código Tipo Documento | H79: Debe representar un valor categorizado según La Positiva. | I79: Básica | J79: SÍ | K79: Validez | L79: 1 | M79: 0.98 | N79: A demanda | O79: INSIS, VTIME | P79: Gaudy Sanchez | Q79: SÍ
A80: CRM | B80: CRM | C80: =+UPPER(MID(B80,1,3))&"00"&COUNTA(B$3:B80) -> CRM0010 | D80: Documento de Identidad | E80: Party_Identification | F80: identification_Type_Name | G80: Tipo Documento | H80: Longitud de 40 caracteres | I80: Básica | J80: NO | K80: Validez | L80: 1 | M80: 0.98 | N80: A demanda | O80: INSIS, VTIME | P80: Gaudy Sanchez | Q80: SÍ
A81: CRM | C81: =+UPPER(MID(B81,1,3))&"00"&COUNTA(B$3:B81) -> 0010 | D81: Documento de Identidad | E81: Party_Identification | F81: identification_Type_Name | G81: Tipo Documento | H81: Debe estar asignado a un código. | I81: Básica | J81: SÍ | K81: Integridad | L81: 1 | M81: 0.98 | N81: A demanda | O81: INSIS, VTIME | P81: Gaudy Sanchez | Q81: SÍ
A82: CRM | C82: =+UPPER(MID(B82,1,3))&"00"&COUNTA(B$3:B82) -> 0010 | D82: Documento de Identidad | E82: Party_Identification | F82: identification_Type_Name | G82: Tipo Documento | H82: No se acepta números (0-9). | I82: Básica | J82: NO | K82: Validez | L82: 1 | M82: 0.98 | N82: A demanda | O82: INSIS, VTIME | P82: Gaudy Sanchez | Q82: SÍ
A83: CRM | C83: =+UPPER(MID(B83,1,3))&"00"&COUNTA(B$3:B83) -> 0010 | D83: Documento de Identidad | E83: Party_Identification | F83: identification_Type_Name | G83: Tipo Documento | H83: No acepta carácteres especiales. | I83: Básica | J83: NO | K83: Validez | L83: 1 | M83: 0.98 | N83: A demanda | O83: INSIS, VTIME | P83: Gaudy Sanchez | Q83: SÍ
A84: CRM | C84: =+UPPER(MID(B84,1,3))&"00"&COUNTA(B$3:B84) -> 0010 | D84: Documento de Identidad | E84: Party_Identification | F84: identification_Type_Name | G84: Tipo Documento | H84: No se acepta saltos de línea. | I84: Básica | J84: SÍ | K84: Validez | L84: 1 | M84: 0.98 | N84: A demanda | O84: INSIS, VTIME | P84: Gaudy Sanchez | Q84: SÍ
A85: CRM | C85: =+UPPER(MID(B85,1,3))&"00"&COUNTA(B$3:B85) -> 0010 | D85: Documento de Identidad | E85: Party_Identification | F85: identification_Type_Name | G85: Tipo Documento | H85: No se acepta tabulaciones. | I85: Básica | J85: NO | K85: Validez | L85: 1 | M85: 0.98 | N85: A demanda | O85: INSIS, VTIME | P85: Gaudy Sanchez | Q85: SÍ
A86: CRM | C86: =+UPPER(MID(B86,1,3))&"00"&COUNTA(B$3:B86) -> 0010 | D86: Documento de Identidad | E86: Party_Identification | F86: identification_Type_Name | G86: Tipo Documento | H86: Valores permitidos: - DNI - RUC - Carnet de Extranjería - Pasaporte | I86: Básica | J86: SÍ | K86: Validez | L86: 1 | M86: 0.98 | N86: A demanda | O86: INSIS, VTIME | P86: Gaudy Sanchez | Q86: SÍ
A87: CRM | C87: =+UPPER(MID(B87,1,3))&"00"&COUNTA(B$3:B87) -> 0010 | D87: Documento de Identidad | E87: Party_Identification | F87: identification_Type_Name | G87: Tipo Documento | H87: No se permiten valores vacíos o nulos. | I87: Básica | J87: SÍ | K87: Completitud | L87: 1 | M87: 0.98 | N87: A demanda | O87: INSIS, VTIME | P87: Gaudy Sanchez | Q87: SÍ
A88: CRM | B88: CRM | C88: =+UPPER(MID(B88,1,3))&"0"&COUNTA(B$3:B88) -> CRM011 | D88: Documento de Identidad | E88: Party | F88: identification_Number | G88: Número Documento | H88: Longitudes permitidas por documento: - DNI: Exactamente 8 caracteres - RUC: Exactamente 11 caracteres. (Empezar con 10 o 20) - CE: Exactamente 9 caracteres - Pasaporte: 10 caracteres (alfanumérico) | I88: Básica | J88: NO | K88: Validez | L88: 1 | M88: 0.98 | N88: A demanda | O88: INSIS, VTIME, INSUNIX | P88: Gaudy Sanchez | Q88: SÍ
A89: CRM | C89: =+UPPER(MID(B89,1,3))&"0"&COUNTA(B$3:B89) -> 011 | D89: Documento de Identidad | E89: Party | F89: identification_Number | G89: Número Documento | H89: Sin duplicidad para un mismo tipo de documento. | I89: Básica | J89: NO | K89: Consistencia | L89: 1 | M89: 0.98 | N89: A demanda | O89: INSIS, VTIME, INSUNIX | P89: Gaudy Sanchez | Q89: SÍ
A90: CRM | C90: =+UPPER(MID(B90,1,3))&"0"&COUNTA(B$3:B90) -> 011 | D90: Documento de Identidad | E90: Party | F90: identification_Number | G90: Número Documento | H90: No acepta carácteres especiales. | I90: Básica | J90: NO | K90: Validez | L90: 1 | M90: 0.98 | N90: A demanda | O90: INSIS, VTIME, INSUNIX | P90: Gaudy Sanchez | Q90: SÍ
A91: CRM | C91: =+UPPER(MID(B91,1,3))&"0"&COUNTA(B$3:B91) -> 011 | D91: Documento de Identidad | E91: Party | F91: identification_Number | G91: Número Documento | H91: No se acepta saltos de línea. | I91: Básica | J91: SÍ | K91: Validez | L91: 1 | M91: 0.98 | N91: A demanda | O91: INSIS, VTIME, INSUNIX | P91: Gaudy Sanchez | Q91: SÍ
A92: CRM | C92: =+UPPER(MID(B92,1,3))&"0"&COUNTA(B$3:B92) -> 011 | D92: Documento de Identidad | E92: Party | F92: identification_Number | G92: Número Documento | H92: No se acepta tabulaciones. | I92: Básica | J92: NO | K92: Validez | L92: 1 | M92: 0.98 | N92: A demanda | O92: INSIS, VTIME, INSUNIX | P92: Gaudy Sanchez | Q92: SÍ
A93: CRM | C93: =+UPPER(MID(B93,1,3))&"0"&COUNTA(B$3:B93) -> 011 | D93: Documento de Identidad | E93: Party | F93: identification_Number | G93: Número Documento | H93: Deben validarse con entidad emisora correspondiente: - DNI: RENIEC - RUC: SUNAT - CE: Superintendencia Nacional de Migraciones - Pasaporte: Superintendencia Nacional de Migraciones | I93: Experta | J93: NO | K93: Precisión | L93: 1 | M93: 0.98 | N93: A demanda | O93: INSIS, VTIME, INSUNIX | P93: Gaudy Sanchez | Q93: SÍ
A94: CRM | C94: =+UPPER(MID(B94,1,3))&"0"&COUNTA(B$3:B94) -> 011 | D94: Documento de Identidad | E94: Party | F94: identification_Number | G94: Número Documento | H94: No se permiten valores vacíos o nulos. | I94: Básica | J94: SÍ | K94: Completitud | L94: 1 | M94: 0.98 | N94: A demanda | O94: INSIS, VTIME, INSUNIX | P94: Gaudy Sanchez | Q94: SÍ
A95: CRM | B95: CRM | C95: =+UPPER(MID(B95,1,3))&"0"&COUNTA(B$3:B95) -> CRM012 | D95: Grupo Económico | E95: Grouping | F95: Grouping_Identifier | G95: Código Grupo económico | H95: Debe ser entero positivo. | I95: Básica | J95: SÍ | K95: Validez | L95: 1 | M95: 0.98 | N95: A demanda | O95: INSIS | P95: Gaudy Sanchez | Q95: SÍ
A96: CRM | C96: =+UPPER(MID(B96,1,3))&"0"&COUNTA(B$3:B96) -> 012 | D96: Grupo Económico | E96: Grouping | F96: Grouping_Identifier | G96: Código Grupo económico | H96: No debe modificarse una vez creado. | I96: Básica | J96: SÍ | K96: Integridad | L96: 1 | M96: 0.98 | N96: A demanda | O96: INSIS | P96: Gaudy Sanchez | Q96: SÍ
A97: CRM | C97: =+UPPER(MID(B97,1,3))&"0"&COUNTA(B$3:B97) -> 012 | D97: Grupo Económico | E97: Grouping | F97: Grouping_Identifier | G97: Código Grupo económico | H97: Solo aplica para persona jurídica. | I97: Básica | J97: NO | K97: Integridad | L97: 1 | M97: 0.98 | N97: A demanda | O97: INSIS | P97: Gaudy Sanchez | Q97: SÍ
A98: CRM | C98: =+UPPER(MID(B98,1,3))&"0"&COUNTA(B$3:B98) -> 012 | D98: Grupo Económico | E98: Grouping | F98: Grouping_Identifier | G98: Código Grupo económico | H98: No se permiten valores vacíos o nulos. | I98: Básica | J98: SÍ | K98: Completitud | L98: 1 | M98: 0.98 | N98: A demanda | O98: INSIS | P98: Gaudy Sanchez | Q98: SÍ
A99: CRM | C99: =+UPPER(MID(B99,1,3))&"00"&COUNTA(B$3:B99) -> 0012 | D99: Grupo Económico | E99: Grouping | F99: Grouping_Identifier | G99: Código Grupo económico | H99: Debe representar un valor categorizado según La Positiva. | I99: Básica | J99: SÍ | K99: Validez | L99: 1 | M99: 0.98 | N99: A demanda | O99: INSIS | P99: Gaudy Sanchez | Q99: SÍ
A100: CRM | B100: CRM | C100: =+UPPER(MID(B100,1,3))&"0"&COUNTA(B$3:B100) -> CRM013 | D100: Grupo Económico | E100: Grouping | F100: Grouping_Name | G100: Grupo económico | H100: Longitud: 100 caracteres. | I100: Básica | J100: NO | K100: Validez | L100: 1 | M100: 0.98 | N100: A demanda | O100: INSIS | P100: Gaudy Sanchez | Q100: SÍ
...

Sheet 3.Trazabilidad
A1: Iniciativa | B1: Caso de Uso | C1: Código de Entidad del Dato | D1: Tabla del Entidad de Dato (OMG) | E1: Campo del Entidad de Dato (OMG) | F1: Nombre de entidad del dato | G1: Llave | H1: Aplicativo(s) | I1: Fuente oficial | J1: Compañia | K1: Esquema | L1: Tabla en fuente oficial | M1: Campo en Fuente Oficial | N1: Personal | O1: Sensble | P1: Fuentes y campos necesarias para el cálculo o generación del dato | Q1: Ruta u Origen del Repositorio (Servidor) | R1: Data Entry (SI/NO) | S1: Periodicidad de Actualización | T1: Profundidad de datos | U1: Formato del Dato | V1: Longitud | W1: ¿Es llave primaria? | X1: Data Owner | Y1: Data Custodian | Z1: Validado por Data Custodian | AA1: Fecha de Actualización en el Diccionario Técnico | AB1: Actualización realizada en el Diccionario Técnico | AC1: Motivo de Actualización en el Diccionario Técnico | AD1: Responsable de la actualización en el Diccionario Técnico
A2: Iniciativa | B2: Caso de uso que corresponde | C2: Identificador único secuencial, asignado al Entidad de Dato por CDO | D2: Nombre de la entidad que se visualiza en la documentación de OMG | E2: Campo de la entidad que se visualiza en la documentación de OMG | F2: Nombre único con el cual el Negocio identifica al Entidad de Dato | H2: Nombre del aplicativo en el que se consulta/visualiza el dato | I2: Nombre del repositorio aprobado por el Dominio en donde se encuentra albergado este Dato | J2: Nompre de la compañía oficial de donde viene la tabla en fuente oficial. | K2: Agrupa las tablas dentro de la base de datos. | L2: Nombre de la tabla del aplicativo en el que se visualiza el Dato | M2: Nombre de campo desde donde se extrae el Concepto de Negocio por parte de la unidad de negocio | N2: Es dato personal si me permite identificar directamente a una persona natural. | O2: Tipificación de datos que requieren un tratamiento especial por su sinsibilidad. Ej: diagnóstico médico, N°tarjeta, sueldo del colaborador/cliente. | P2: Nombres de las fuentes y/o campos asociados a los datos calculados | Q2: Ruta física del repositorio, si es una dirección IP, Hostname en la que se encuentra | R2: Indicar SI, si el Dato es ingresado manualmente Indicar NO, si el Dato es obtenido por un proceso automático | S2: Indica la frecuencia requerida de actualización de la información, es decir la antigüedad máxima admitida del dato (e.g. si es suficiente con disponer de los datos del día anterior se indicaría D+1) | T2: Disponibilidad actual de datos históricos expresado en una unidad de tiempo (meses/fecha) | U2: Formato de dato de la Columna | V2: Número de caracteres o dígitos admitidos | W2: Indicador de si un campo es clave primaria de una tabla | X2: Nombre de la persona responsable de la gestión del dato. | Y2: Responsable de Tecnología | Z2: Una vez revisado por el Data Custodian colocar SÍ en señal de conformidad con la definición | AA2: Fecha en la que el dato fue actualizado | AB2: Descripción de la actualización realizada | AC2: Motivo de la actualización realizada | AD2: Nombre del colaborador que actualizó el dato
A3: CRM | B3: CRM | C3: =+UPPER(MID(B3,1,3))&"00"&COUNTA(B$3:B3) -> CRM001 | D3: Customer | E3: Party_Identifier | F3: Id Cliente | G3: =CONCATENATE(H3,".",J3,".",K3,".",L3,".",M3) -> INSIS.LPV.INSIS_PEOPLE_V10.P_CLIENTS.CLIENT_ID | H3: INSIS | I3: INSIS | J3: LPV | K3: INSIS_PEOPLE_V10 | L3: P_CLIENTS | M3: CLIENT_ID | N3: NO | O3: NO | P3: No aplica | Q3: 10.10.36.48 | R3: NO | S3: A demanda | T3: 2018 | U3: NUMERICO | V3: 10 | W3: SI | X3: Gaudy Sanchez | Y3: Javier Canchari | Z3: SÍ | AD3: Gobierno de Datos
A4: CRM | C4: =+UPPER(MID(B4,1,3))&"00"&COUNTA(B$3:B4) -> 001 | D4: Customer | E4: Party_Identifier | F4: Id Cliente | G4: =CONCATENATE(H4,".",J4,".",K4,".",L4,".",M4) -> VTIME.LPV.INSUDB.CLIENT.SCLIENT | H4: VTIME | I4: INSUDB | J4: LPV | K4: INSUDB | L4: CLIENT | M4: SCLIENT | N4: NO | O4: NO | P4: No aplica | Q4: PRD: 50.0.0.74 | R4: NO | S4: A demanda | T4: 2008 | U4: CHAR | V4: 14 | W4: SI | X4: Gaudy Sanchez | Y4: Fernando Fuentes | Z4: Si | AD4: Gobierno de Datos
A5: CRM | C5: =+UPPER(MID(B5,1,3))&"00"&COUNTA(B$3:B5) -> 001 | D5: Customer | E5: Party_Identifier | F5: Id Cliente | G5: =CONCATENATE(H5,".",J5,".",K5,".",L5,".",M5) -> VTIME.LPG.INSUDB.CLIENT.SCLIENT | H5: VTIME | I5: INSUDB | J5: LPG | K5: INSUDB | L5: CLIENT | M5: SCLIENT | N5: NO | O5: NO | P5: No aplica | Q5: 50.0.0.74 / oraprod | R5: NO | S5: A demanda | T5: 2008 | U5: CHAR | V5: 14 | W5: SI | X5: Gaudy Sanchez | Y5: Ellen Romero | Z5: Si | AD5: Gobierno de Datos
A6: CRM | C6: =+UPPER(MID(B6,1,3))&"00"&COUNTA(B$3:B6) -> 001 | D6: Customer | E6: Party_Identifier | F6: Id Cliente | G6: =CONCATENATE(H6,".",J6,".",K6,".",L6,".",M6) -> INSUNIX.LPV.INFORMIX.CLIENT.CODE | H6: INSUNIX | I6: INSUNIX | J6: LPV | K6: INFORMIX | L6: CLIENT | M6: CODE | N6: NO | O6: NO | P6: No aplica | Q6: 10.20.64.100 | R6: NO | S6: A demanda | T6: 1994 | U6: CHAR | V6: 11 | W6: SI | X6: Gaudy Sanchez | Y6: Javier Canchari | Z6: NO | AD6: Gobierno de Datos
A7: CRM | C7: =+UPPER(MID(B7,1,3))&"00"&COUNTA(B$3:B7) -> 001 | D7: Customer | E7: Party_Identifier | F7: Id Cliente | G7: =CONCATENATE(H7,".",J7,".",K7,".",L7,".",M7) -> INSUNIX.LPG.INFORMIX.CLIENT.CODE | H7: INSUNIX | I7: INSUNIX | J7: LPG | K7: INFORMIX | L7: CLIENT | M7: CODE | N7: NO | O7: NO | P7: No aplica | Q7: 10.20.162.27 | R7: NO | S7: A demanda | T7: 1994 | U7: CHAR | V7: 11 | W7: SI | X7: Gaudy Sanchez | Y7: Heli Rojas | Z7: Si | AD7: Gobierno de Datos
A8: CRM | C8: =+UPPER(MID(B8,1,3))&"00"&COUNTA(B$3:B8) -> 001 | D8: Customer | E8: Party_Identifier | F8: Id Cliente | G8: =CONCATENATE(H8,".",J8,".",K8,".",L8,".",M8) -> INSUNIX.LPE.INFORMIX.CLIENT.CODE | H8: INSUNIX | I8: INSUNIX | J8: LPE | K8: INFORMIX | L8: CLIENT | M8: CODE | P8: No aplica | Q8: 10.20.96.102 puerto: 1526 | R8: NO | S8: A demanda | T8: 1994 | U8: CHAR | V8: 11 | W8: SI | X8: Gaudy Sanchez | Y8: Cristian Torres | Z8: NO | AD8: Gobierno de Datos
A9: CRM | B9: CRM | C9: =+UPPER(MID(B9,1,3))&"00"&COUNTA(B$3:B9) -> CRM002 | D9: Person | E9: First_Name/Middle_Name | F9: Primer Nombre | G9: =CONCATENATE(H9,".",J9,".",K9,".",L9,".",M9) -> INSIS.LPV.INSIS_PEOPLE_V10.P_PEOPLE.GNAME | H9: INSIS | I9: INSIS | J9: LPV | K9: INSIS_PEOPLE_V10 | L9: P_PEOPLE | M9: GNAME | N9: SÍ | O9: NO | P9: No aplica | Q9: 10.10.36.48 | R9: NO | S9: A demanda | T9: 2018 | U9: VARCHAR2 | V9: 100 | W9: NO | X9: Gaudy Sanchez | Y9: Javier Canchari | Z9: SÍ | AD9: Gobierno de Datos
A10: CRM | C10: =+UPPER(MID(B10,1,3))&"00"&COUNTA(B$3:B10) -> 002 | D10: Person | E10: First_Name/Middle_Name | F10: Primer Nombre | G10: =CONCATENATE(H10,".",J10,".",K10,".",L10,".",M10) -> VTIME.LPV.INSUDB.CLIENT.SFIRSTNAME | H10: VTIME | I10: INSUDB | J10: LPV | K10: INSUDB | L10: CLIENT | M10: SFIRSTNAME | N10: SÍ | O10: NO | P10: No aplica | Q10: PRD: 50.0.0.74 | R10: NO | S10: A demanda | T10: 2008 | U10: VARCHAR2 | V10: 45 | W10: NO | X10: Gaudy Sanchez | Y10: Fernando Fuentes | Z10: Si | AD10: Gobierno de Datos
A11: CRM | C11: =+UPPER(MID(B11,1,3))&"00"&COUNTA(B$3:B11) -> 002 | D11: Person | E11: First_Name/Middle_Name | F11: Primer Nombre | G11: =CONCATENATE(H11,".",J11,".",K11,".",L11,".",M11) -> VTIME.LPG.INSUDB.CLIENT.SFIRSTNAME | H11: VTIME | I11: INSUDB | J11: LPG | K11: INSUDB | L11: CLIENT | M11: SFIRSTNAME | N11: SÍ | O11: NO | P11: No aplica | Q11: 50.0.0.74 / oraprod | R11: NO | S11: A demanda | T11: 2008 | U11: VARCHAR2 | V11: 45 | W11: NO | X11: Gaudy Sanchez | Y11: Ellen Romero | Z11: Si | AD11: Gobierno de Datos
A12: CRM | C12: =+UPPER(MID(B12,1,3))&"00"&COUNTA(B$3:B12) -> 002 | D12: Customer | E12: Party_Identifier | F12: Primer Nombre | G12: =CONCATENATE(H12,".",J12,".",K12,".",L12,".",M12) -> INSUNIX.LPV.INFORMIX.CLIENT.CLIENAME | H12: INSUNIX | I12: INSUNIX | J12: LPV | K12: INFORMIX | L12: CLIENT | M12: CLIENAME | N12: SÍ | O12: NO | P12: No aplica | Q12: 10.20.64.100 | R12: NO | S12: A demanda | T12: 1994 | U12: CHAR | V12: 40 | W12: NO | X12: Gaudy Sanchez | Y12: Javier Canchari | Z12: NO | AD12: Gobierno de Datos
A13: CRM | C13: =+UPPER(MID(B13,1,3))&"00"&COUNTA(B$3:B13) -> 002 | D13: Person | E13: First_Name/Middle_Name | F13: Primer Nombre | G13: =CONCATENATE(H13,".",J13,".",K13,".",L13,".",M13) -> INSUNIX.LPG.INFORMIX.CLIENT.CLIENAME | H13: INSUNIX | I13: INSUNIX | J13: LPG | K13: INFORMIX | L13: CLIENT | M13: CLIENAME | N13: SÍ | O13: NO | P13: No aplica | Q13: 10.20.162.27 | R13: NO | S13: A demanda | T13: 1994 | U13: CHAR | V13: 40 | W13: NO | X13: Gaudy Sanchez | Y13: Heli Rojas | Z13: Si | AD13: Gobierno de Datos
A14: CRM | C14: =+UPPER(MID(B14,1,3))&"00"&COUNTA(B$3:B14) -> 002 | D14: Customer | E14: Party_Identifier | F14: Primer Nombre | G14: =CONCATENATE(H14,".",J14,".",K14,".",L14,".",M14) -> INSUNIX.LPE.INFORMIX.CLIENT.CLIENAME | H14: INSUNIX | I14: INSUNIX | J14: LPE | K14: INFORMIX | L14: CLIENT | M14: CLIENAME | P14: No aplica | Q14: 10.20.96.102 puerto: 1526 | R14: NO | S14: A demanda | T14: 1994 | U14: CHAR | V14: 40 | W14: NO | X14: Gaudy Sanchez | Y14: Cristian Torres | Z14: NO | AD14: Gobierno de Datos
A15: CRM | B15: CRM | C15: =+UPPER(MID(B15,1,3))&"00"&COUNTA(B$3:B15) -> CRM003 | D15: Person | E15: First_Name/Middle_Name | F15: Segundo Nombre | G15: =CONCATENATE(H15,".",J15,".",K15,".",L15,".",M15) -> INSIS.LPV.INSIS_PEOPLE_V10.P_PEOPLE.GNAME | H15: INSIS | I15: INSIS | J15: LPV | K15: INSIS_PEOPLE_V10 | L15: P_PEOPLE | M15: GNAME | N15: SÍ | O15: NO | P15: No aplica | Q15: 10.10.36.48 | R15: NO | S15: A demanda | T15: 2018 | U15: VARCHAR2 | V15: 100 | W15: NO | X15: Gaudy Sanchez | Y15: Javier Canchari | Z15: SÍ | AD15: Gobierno de Datos
A16: CRM | C16: =+UPPER(MID(B16,1,3))&"00"&COUNTA(B$3:B16) -> 003 | D16: Person | E16: First_Name/Middle_Name | F16: Segundo Nombre | G16: =CONCATENATE(H16,".",J16,".",K16,".",L16,".",M16) -> VTIME.LPV.INSUDB.CLIENT.SFIRSTNAME | H16: VTIME | I16: INSUDB | J16: LPV | K16: INSUDB | L16: CLIENT | M16: SFIRSTNAME | N16: SÍ | O16: NO | P16: No aplica | Q16: PRD: 50.0.0.74 | R16: NO | S16: A demanda | T16: 2008 | U16: VARCHAR2 | V16: 45 | W16: NO | X16: Gaudy Sanchez | Y16: Fernando Fuentes | Z16: Si | AD16: Gobierno de Datos
A17: CRM | C17: =+UPPER(MID(B17,1,3))&"00"&COUNTA(B$3:B17) -> 003 | D17: Person | E17: First_Name/Middle_Name | F17: Segundo Nombre | G17: =CONCATENATE(H17,".",J17,".",K17,".",L17,".",M17) -> VTIME.LPG.INSUDB.CLIENT.SFIRSTNAME | H17: VTIME | I17: INSUDB | J17: LPG | K17: INSUDB | L17: CLIENT | M17: SFIRSTNAME | N17: SÍ | O17: NO | P17: No aplica | Q17: 50.0.0.74 / oraprod | R17: NO | S17: A demanda | T17: 2008 | U17: VARCHAR2 | V17: 45 | W17: NO | X17: Gaudy Sanchez | Y17: Ellen Romero | Z17: Si | AD17: Gobierno de Datos
A18: CRM | C18: =+UPPER(MID(B18,1,3))&"00"&COUNTA(B$3:B18) -> 003 | D18: Customer | E18: Party_Identifier | F18: Segundo Nombre | G18: =CONCATENATE(H18,".",J18,".",K18,".",L18,".",M18) -> INSUNIX.LPV.INFORMIX.CLIENT.CLIENAME | H18: INSUNIX | I18: INSUNIX | J18: LPV | K18: INFORMIX | L18: CLIENT | M18: CLIENAME | N18: SÍ | O18: NO | P18: No aplica | Q18: 10.20.64.100 | R18: NO | S18: A demanda | T18: 1994 | U18: CHAR | V18: 40 | W18: NO | X18: Gaudy Sanchez | Y18: Javier Canchari | Z18: NO | AD18: Gobierno de Datos
A19: CRM | C19: =+UPPER(MID(B19,1,3))&"00"&COUNTA(B$3:B19) -> 003 | D19: Person | E19: First_Name/Middle_Name | F19: Segundo Nombre | G19: =CONCATENATE(H19,".",J19,".",K19,".",L19,".",M19) -> INSUNIX.LPG.INFORMIX.CLIENT.CLIENAME | H19: INSUNIX | I19: INSUNIX | J19: LPG | K19: INFORMIX | L19: CLIENT | M19: CLIENAME | N19: SÍ | O19: NO | P19: No aplica | Q19: 10.20.162.27 | R19: NO | S19: A demanda | T19: 1994 | U19: CHAR | V19: 40 | W19: NO | X19: Gaudy Sanchez | Y19: Heli Rojas | Z19: Si | AD19: Gobierno de Datos
A20: CRM | C20: =+UPPER(MID(B20,1,3))&"00"&COUNTA(B$3:B20) -> 003 | D20: Customer | E20: Party_Identifier | F20: Segundo Nombre | G20: =CONCATENATE(H20,".",J20,".",K20,".",L20,".",M20) -> INSUNIX.LPE.INFORMIX.CLIENT.CLIENAME | H20: INSUNIX | I20: INSUNIX | J20: LPE | K20: INFORMIX | L20: CLIENT | M20: CLIENAME | P20: No aplica | Q20: 10.20.96.102 puerto: 1526 | R20: NO | S20: A demanda | T20: 1994 | U20: CHAR | V20: 40 | W20: NO | X20: Gaudy Sanchez | Y20: Cristian Torres | Z20: NO | AD20: Gobierno de Datos
A21: CRM | B21: CRM | C21: =+UPPER(MID(B21,1,3))&"00"&COUNTA(B$3:B21) -> CRM004 | D21: Person | E21: Last_Name | F21: Apellido Paterno | G21: =CONCATENATE(H21,".",J21,".",K21,".",L21,".",M21) -> INSIS.LPV.INSIS_PEOPLE_V10.P_PEOPLE.SNAME | H21: INSIS | I21: INSIS | J21: LPV | K21: INSIS_PEOPLE_V10 | L21: P_PEOPLE | M21: SNAME | N21: SÍ | O21: NO | P21: No aplica | Q21: 10.10.36.48 | R21: NO | S21: A demanda | T21: 2018 | U21: VARCHAR2 | V21: 100 | W21: NO | X21: Gaudy Sanchez | Y21: Javier Canchari | Z21: SÍ | AD21: Gobierno de Datos
A22: CRM | C22: =+UPPER(MID(B22,1,3))&"00"&COUNTA(B$3:B22) -> 004 | D22: Person | E22: Last_Name | F22: Apellido Paterno | G22: =CONCATENATE(H22,".",J22,".",K22,".",L22,".",M22) -> VTIME.LPV.INSUDB.CLIENT.SLASTNAME | H22: VTIME | I22: INSUDB | J22: LPV | K22: INSUDB | L22: CLIENT | M22: SLASTNAME | N22: SÍ | O22: NO | P22: No aplica | Q22: PRD: 50.0.0.74 | R22: NO | S22: A demanda | T22: 2008 | U22: VARCHAR2 | V22: 45 | W22: NO | X22: Gaudy Sanchez | Y22: Fernando Fuentes | Z22: Si | AD22: Gobierno de Datos
A23: CRM | C23: =+UPPER(MID(B23,1,3))&"00"&COUNTA(B$3:B23) -> 004 | D23: Person | E23: Last_Name | F23: Apellido Paterno | G23: =CONCATENATE(H23,".",J23,".",K23,".",L23,".",M23) -> VTIME.LPG.INSUDB.CLIENT.SLASTNAME | H23: VTIME | I23: INSUDB | J23: LPG | K23: INSUDB | L23: CLIENT | M23: SLASTNAME | N23: SÍ | O23: NO | P23: No aplica | Q23: 50.0.0.74 / oraprod | R23: NO | S23: A demanda | T23: 2008 | U23: VARCHAR2 | V23: 45 | W23: NO | X23: Gaudy Sanchez | Y23: Ellen Romero | Z23: Si | AD23: Gobierno de Datos
A24: CRM | C24: =+UPPER(MID(B24,1,3))&"00"&COUNTA(B$3:B24) -> 004 | D24: Customer | E24: Party_Identifier | F24: Apellido Paterno | G24: =CONCATENATE(H24,".",J24,".",K24,".",L24,".",M24) -> INSUNIX.LPV.INFORMIX.CLIENT.CLIENAME | H24: INSUNIX | I24: INSUNIX | J24: LPV | K24: INFORMIX | L24: CLIENT | M24: CLIENAME | N24: SÍ | O24: NO | P24: No aplica | Q24: 10.20.64.100 | R24: NO | S24: A demanda | T24: 1994 | U24: CHAR | V24: 40 | W24: NO | X24: Gaudy Sanchez | Y24: Javier Canchari | Z24: NO | AD24: Gobierno de Datos
A25: CRM | C25: =+UPPER(MID(B25,1,3))&"00"&COUNTA(B$3:B25) -> 004 | D25: Person | E25: Last_Name | F25: Apellido Paterno | G25: =CONCATENATE(H25,".",J25,".",K25,".",L25,".",M25) -> INSUNIX.LPG.INFORMIX.CLIENT.CLIENAME | H25: INSUNIX | I25: INSUNIX | J25: LPG | K25: INFORMIX | L25: CLIENT | M25: CLIENAME | N25: SÍ | O25: NO | P25: No aplica | Q25: 10.20.162.27 | R25: NO | S25: A demanda | T25: 1994 | U25: CHAR | V25: 40 | W25: NO | X25: Gaudy Sanchez | Y25: Heli Rojas | Z25: Si | AD25: Gobierno de Datos
A26: CRM | C26: =+UPPER(MID(B26,1,3))&"00"&COUNTA(B$3:B26) -> 004 | D26: Customer | E26: Party_Identifier | F26: Apellido Paterno | G26: =CONCATENATE(H26,".",J26,".",K26,".",L26,".",M26) -> INSUNIX.LPE.INFORMIX.CLIENT.CLIENAME | H26: INSUNIX | I26: INSUNIX | J26: LPE | K26: INFORMIX | L26: CLIENT | M26: CLIENAME | P26: No aplica | Q26: 10.20.96.102 puerto: 1526 | R26: NO | S26: A demanda | T26: 1994 | U26: CHAR | V26: 40 | W26: NO | X26: Gaudy Sanchez | Y26: Cristian Torres | Z26: NO | AD26: Gobierno de Datos
A27: CRM | B27: CRM | C27: =+UPPER(MID(B27,1,3))&"00"&COUNTA(B$3:B27) -> CRM005 | D27: Person | E27: Last_Name | F27: Apellido Materno | G27: =CONCATENATE(H27,".",J27,".",K27,".",L27,".",M27) -> INSIS.LPV.INSIS_PEOPLE_V10.P_PEOPLE.FNAME | H27: INSIS | I27: INSIS | J27: LPV | K27: INSIS_PEOPLE_V10 | L27: P_PEOPLE | M27: FNAME | N27: SÍ | O27: NO | P27: No aplica | Q27: 10.10.36.48 | R27: NO | S27: A demanda | T27: 2018 | U27: VARCHAR2 | V27: 100 | W27: NO | X27: Gaudy Sanchez | Y27: Javier Canchari | Z27: SÍ | AD27: Gobierno de Datos
A28: CRM | C28: =+UPPER(MID(B28,1,3))&"00"&COUNTA(B$3:B28) -> 005 | D28: Person | E28: Last_Name | F28: Apellido Materno | G28: =CONCATENATE(H28,".",J28,".",K28,".",L28,".",M28) -> VTIME.LPV.INSUDB.CLIENT.SLASTNAME2 | H28: VTIME | I28: INSUDB | J28: LPV | K28: INSUDB | L28: CLIENT | M28: SLASTNAME2 | N28: SÍ | O28: NO | P28: No aplica | Q28: PRD: 50.0.0.74 | R28: NO | S28: A demanda | T28: 2008 | U28: VARCHAR2 | V28: 45 | W28: NO | X28: Gaudy Sanchez | Y28: Fernando Fuentes | Z28: Si | AD28: Gobierno de Datos
A29: CRM | C29: =+UPPER(MID(B29,1,3))&"00"&COUNTA(B$3:B29) -> 005 | D29: Person | E29: Last_Name | F29: Apellido Materno | G29: =CONCATENATE(H29,".",J29,".",K29,".",L29,".",M29) -> VTIME.LPG.INSUDB.CLIENT.SLASTNAME2 | H29: VTIME | I29: INSUDB | J29: LPG | K29: INSUDB | L29: CLIENT | M29: SLASTNAME2 | N29: SÍ | O29: NO | P29: No aplica | Q29: 50.0.0.74 / oraprod | R29: NO | S29: A demanda | T29: 2008 | U29: VARCHAR2 | V29: 45 | W29: NO | X29: Gaudy Sanchez | Y29: Ellen Romero | Z29: Si | AD29: Gobierno de Datos
A30: CRM | C30: =+UPPER(MID(B30,1,3))&"00"&COUNTA(B$3:B30) -> 005 | D30: Person | E30: Last_Name | F30: Apellido Materno | G30: =CONCATENATE(H30,".",J30,".",K30,".",L30,".",M30) -> INSUNIX.LPV.INFORMIX.CLIENT.CLIENAME | H30: INSUNIX | I30: INSUNIX | J30: LPV | K30: INFORMIX | L30: CLIENT | M30: CLIENAME | N30: SÍ | O30: NO | P30: No aplica | Q30: 10.20.64.100 | R30: NO | S30: A demanda | T30: 1994 | U30: CHAR | V30: 40 | W30: NO | X30: Gaudy Sanchez | Y30: Javier Canchari | Z30: NO | AD30: Gobierno de Datos
A31: CRM | C31: =+UPPER(MID(B31,1,3))&"00"&COUNTA(B$3:B31) -> 005 | D31: Person | E31: Last_Name | F31: Apellido Materno | G31: =CONCATENATE(H31,".",J31,".",K31,".",L31,".",M31) -> INSUNIX.LPG.INFORMIX.CLIENT.CLIENAME | H31: INSUNIX | I31: INSUNIX | J31: LPG | K31: INFORMIX | L31: CLIENT | M31: CLIENAME | N31: SÍ | O31: NO | P31: No aplica | Q31: 10.20.162.27 | R31: NO | S31: A demanda | T31: 1994 | U31: CHAR | V31: 40 | W31: NO | X31: Gaudy Sanchez | Y31: Heli Rojas | Z31: Si | AD31: Gobierno de Datos
A32: CRM | C32: =+UPPER(MID(B32,1,3))&"00"&COUNTA(B$3:B32) -> 005 | D32: Customer | E32: Party_Identifier | F32: Apellido Materno | G32: =CONCATENATE(H32,".",J32,".",K32,".",L32,".",M32) -> INSUNIX.LPE.INFORMIX.CLIENT.CLIENAME | H32: INSUNIX | I32: INSUNIX | J32: LPE | K32: INFORMIX | L32: CLIENT | M32: CLIENAME | P32: No aplica | Q32: 10.20.96.102 puerto: 1526 | R32: NO | S32: A demanda | T32: 1994 | U32: CHAR | V32: 40 | W32: NO | X32: Gaudy Sanchez | Y32: Cristian Torres | Z32: NO | AD32: Gobierno de Datos
A33: CRM | B33: CRM | C33: =+UPPER(MID(B33,1,3))&"00"&COUNTA(B$3:B33) -> CRM006 | D33: Organization | E33: Organization_Name | F33: Razón social | G33: =CONCATENATE(H33,".",J33,".",K33,".",L33,".",M33) -> INSIS.LPV.INSIS_PEOPLE_V10.P_PEOPLE.NAME | H33: INSIS | I33: INSIS | J33: LPV | K33: INSIS_PEOPLE_V10 | L33: P_PEOPLE | M33: NAME | N33: SÍ | O33: NO | P33: No aplica | Q33: 10.10.36.48 | R33: NO | S33: A demanda | T33: 2018 | U33: VARCHAR2 | V33: 400 | W33: NO | X33: Gaudy Sanchez | Y33: Javier Canchari | Z33: SÍ | AD33: Gobierno de Datos
A34: CRM | C34: =+UPPER(MID(B34,1,3))&"00"&COUNTA(B$3:B34) -> 006 | D34: Organization | E34: Organization_Name | F34: Razón social | G34: =CONCATENATE(H34,".",J34,".",K34,".",L34,".",M34) -> VTIME.LPV.INSUDB.CLIENT.SLEGALNAME | H34: VTIME | I34: INSUDB | J34: LPV | K34: INSUDB | L34: CLIENT | M34: SLEGALNAME | N34: NO | O34: NO | P34: No aplica | Q34: PRD: 50.0.0.74 | R34: NO | S34: A demanda | T34: 2008 | U34: VARCHAR2 | V34: 120 | W34: NO | X34: Gaudy Sanchez | Y34: Fernando Fuentes | Z34: Si | AD34: Gobierno de Datos
A35: CRM | C35: =+UPPER(MID(B35,1,3))&"00"&COUNTA(B$3:B35) -> 006 | D35: Organization | E35: Organization_Name | F35: Razón social | G35: =CONCATENATE(H35,".",J35,".",K35,".",L35,".",M35) -> VTIME.LPG.INSUDB.CLIENT.SLEGALNAME | H35: VTIME | I35: INSUDB | J35: LPG | K35: INSUDB | L35: CLIENT | M35: SLEGALNAME | N35: NO | O35: NO | P35: No aplica | Q35: 50.0.0.74 / oraprod | R35: NO | S35: A demanda | T35: 2008 | U35: VARCHAR2 | V35: 120 | W35: NO | X35: Gaudy Sanchez | Y35: Ellen Romero | Z35: Si | AD35: Gobierno de Datos
A36: CRM | C36: =+UPPER(MID(B36,1,3))&"00"&COUNTA(B$3:B36) -> 006 | D36: Organization | E36: Party_Identifier | F36: Razón social | G36: =CONCATENATE(H36,".",J36,".",K36,".",L36,".",M36) -> INSUNIX.LPV.INFORMIX.CLIENT.CLIENAME | H36: INSUNIX | I36: INSUNIX | J36: LPV | K36: INFORMIX | L36: CLIENT | M36: CLIENAME | N36: NO | O36: NO | P36: No aplica | Q36: 10.20.64.100 | R36: NO | S36: A demanda | T36: 1994 | U36: CHAR | V36: 40 | W36: NO | X36: Gaudy Sanchez | Y36: Javier Canchari | Z36: NO | AD36: Gobierno de Datos
A37: CRM | C37: =+UPPER(MID(B37,1,3))&"00"&COUNTA(B$3:B37) -> 006 | D37: Organization | E37: Organization_Name | F37: Razón social | G37: =CONCATENATE(H37,".",J37,".",K37,".",L37,".",M37) -> INSUNIX.LPG.INFORMIX.CLIENT.CLIENAME | H37: INSUNIX | I37: INSUNIX | J37: LPG | K37: INFORMIX | L37: CLIENT | M37: CLIENAME | N37: NO | O37: NO | P37: No aplica | Q37: 10.20.162.27 | R37: NO | S37: A demanda | T37: 1994 | U37: CHAR | V37: 40 | W37: NO | X37: Gaudy Sanchez | Y37: Heli Rojas | Z37: Si | AD37: Gobierno de Datos
A38: CRM | C38: =+UPPER(MID(B38,1,3))&"00"&COUNTA(B$3:B38) -> 006 | D38: Customer | E38: Party_Identifier | F38: Razón social | G38: =CONCATENATE(H38,".",J38,".",K38,".",L38,".",M38) -> INSUNIX.LPE.INFORMIX.CLIENT.CLIENAME | H38: INSUNIX | I38: INSUNIX | J38: LPE | K38: INFORMIX | L38: CLIENT | M38: CLIENAME | P38: No aplica | Q38: 10.20.96.102 puerto: 1526 | R38: NO | S38: A demanda | T38: 1994 | U38: CHAR | V38: 40 | W38: NO | X38: Gaudy Sanchez | Y38: Cristian Torres | Z38: NO | AD38: Gobierno de Datos
A39: CRM | B39: CRM | C39: =+UPPER(MID(B39,1,3))&"00"&COUNTA(B$3:B39) -> CRM007 | D39: Party | E39: Party _Type_Code | F39: Código Tipo Persona | G39: =CONCATENATE(H39,".",J39,".",K39,".",L39,".",M39) -> INSIS.LPV.INSIS_PEOPLE_V10.P_PEOPLE.MAN_COMP | H39: INSIS | I39: INSIS | J39: LPV | K39: INSIS_PEOPLE_V10 | L39: P_PEOPLE | M39: MAN_COMP | N39: NO | O39: NO | P39: No aplica | Q39: 10.10.36.48 | R39: NO | S39: A demanda | T39: 2018 | U39: NUMERICO | V39: 2 | W39: NO | X39: Gaudy Sanchez | Y39: Javier Canchari | Z39: SÍ | AD39: Gobierno de Datos
A40: CRM | C40: =+UPPER(MID(B40,1,3))&"00"&COUNTA(B$3:B40) -> 007 | D40: Party | E40: Party _Type_Code | F40: Código Tipo Persona | G40: =CONCATENATE(H40,".",J40,".",K40,".",L40,".",M40) -> VTIME.LPV.INSUDB.CLIENT.NPERSON_TYP | H40: VTIME | I40: INSUDB | J40: LPV | K40: INSUDB | L40: CLIENT | M40: NPERSON_TYP | N40: NO | O40: NO | P40: No aplica | Q40: PRD: 50.0.0.74 | R40: NO | S40: A demanda | T40: 2008 | U40: NUMBER | V40: 5 | W40: NO | X40: Gaudy Sanchez | Y40: Fernando Fuentes | Z40: Si | AD40: Gobierno de Datos
A41: CRM | C41: =+UPPER(MID(B41,1,3))&"00"&COUNTA(B$3:B41) -> 007 | D41: Party | E41: Party _Type_Code | F41: Código Tipo Persona | G41: =CONCATENATE(H41,".",J41,".",K41,".",L41,".",M41) -> VTIME.LPG.INSUDB.CLIENT.NPERSON_TYP | H41: VTIME | I41: INSUDB | J41: LPG | K41: INSUDB | L41: CLIENT | M41: NPERSON_TYP | N41: NO | O41: NO | P41: No aplica | Q41: 50.0.0.74 / oraprod | R41: NO | S41: A demanda | T41: 2008 | U41: NUMBER | V41: 5 | W41: NO | X41: Gaudy Sanchez | Y41: Ellen Romero | Z41: Si | AD41: Gobierno de Datos
A42: CRM | C42: =+UPPER(MID(B42,1,3))&"00"&COUNTA(B$3:B42) -> 007 | D42: Party | E42: Party _Type_Code | F42: Código Tipo Persona | G42: =CONCATENATE(H42,".",J42,".",K42,".",L42,".",M42) -> INSUNIX.LPV.INSUNIX.TABLE712.CODIGINT CODIGEXT | H42: INSUNIX | I42: INSUNIX | J42: LPV | K42: INSUNIX | L42: TABLE712 | M42: CODIGINT CODIGEXT | P42: CODIGINT=1 (Persona Natural), CODIGINT=2 (Persona Juridica) CODIGEXT=N (Persona Natural), CODIGEXT=E (Persona Juridica) | Q42: 10.20.64.100 | R42: - | S42: - | T42: - | U42: INTEGER CHAR | V42: - 6 | W42: NO | X42: Gaudy Sanchez | Y42: Javier Canchari | Z42: NO | AD42: Gobierno de Datos
A43: CRM | C43: =+UPPER(MID(B43,1,3))&"00"&COUNTA(B$3:B43) -> 007 | D43: Party | E43: Party _Type_Code | F43: Código Tipo Persona | G43: =CONCATENATE(H43,".",J43,".",K43,".",L43,".",M43) -> INSUNIX.LPG.-.-.- | H43: INSUNIX | I43: INSUNIX | J43: LPG | K43: - | L43: - | M43: - | P43: - | Q43: - | R43: - | S43: - | T43: - | U43: - | V43: - | W43: - | X43: Gaudy Sanchez | Y43: Heli Rojas | Z43: Si | AD43: Gobierno de Datos
A44: CRM | C44: =+UPPER(MID(B44,1,3))&"00"&COUNTA(B$3:B44) -> 007 | D44: Customer | E44: Party_Identifier | F44: Código Tipo Persona | G44: =CONCATENATE(H44,".",J44,".",K44,".",L44,".",M44) -> INSUNIX.LPE.-.-.- | H44: INSUNIX | I44: INSUNIX | J44: LPE | K44: - | L44: - | M44: - | P44: No aplica | Q44: 10.20.96.102 puerto: 1526 | R44: NO | S44: A demanda | T44: 1994 | U44: - | V44: - | W44: - | X44: Gaudy Sanchez | Y44: Cristian Torres | Z44: NO | AD44: Gobierno de Datos
A45: CRM | B45: CRM | C45: =+UPPER(MID(B45,1,3))&"00"&COUNTA(B$3:B45) -> CRM008 | D45: Party _Type | E45: Party _Type_Name | F45: Tipo de persona | G45: =CONCATENATE(H45,".",J45,".",K45,".",L45,".",M45) -> INSIS.LPV.INSIS_PEOPLE_V10.HST_PEOPLE_MAN_COMP.NAME | H45: INSIS | I45: INSIS | J45: LPV | K45: INSIS_PEOPLE_V10 | L45: HST_PEOPLE_MAN_COMP | M45: NAME | N45: NO | O45: NO | P45: No aplica | Q45: 10.10.36.48 | R45: NO | S45: A demanda | T45: 2018 | U45: VARCHAR2 | V45: 40 | W45: NO | X45: Gaudy Sanchez | Y45: Javier Canchari | Z45: SÍ | AD45: Gobierno de Datos
A46: CRM | C46: =+UPPER(MID(B46,1,3))&"00"&COUNTA(B$3:B46) -> 008 | D46: Party _Type | E46: Party _Type_Name | F46: Tipo de persona | G46: =CONCATENATE(H46,".",J46,".",K46,".",L46,".",M46) -> VTIME.LPV.INSUDB.TABLE5006.SDESCRIPT | H46: VTIME | I46: INSUDB | J46: LPV | K46: INSUDB | L46: TABLE5006 | M46: SDESCRIPT | N46: NO | O46: NO | P46: No aplica | Q46: PRD: 50.0.0.74 | R46: NO | S46: A demanda | T46: 2008 | U46: CHAR | V46: 30 | W46: NO | X46: Gaudy Sanchez | Y46: Fernando Fuentes | Z46: Si | AD46: Gobierno de Datos
A47: CRM | C47: =+UPPER(MID(B47,1,3))&"00"&COUNTA(B$3:B47) -> 008 | D47: Party _Type | E47: Party _Type_Name | F47: Tipo de persona | G47: =CONCATENATE(H47,".",J47,".",K47,".",L47,".",M47) -> VTIME.LPG.INSUDB.TABLE5006.SDESCRIPT | H47: VTIME | I47: INSUDB | J47: LPG | K47: INSUDB | L47: TABLE5006 | M47: SDESCRIPT | N47: NO | O47: NO | P47: No aplica | Q47: 50.0.0.74 / oraprod | R47: NO | S47: A demanda | T47: 2008 | U47: CHAR | V47: 30 | W47: NO | X47: Gaudy Sanchez | Y47: Ellen Romero | Z47: Si | AD47: Gobierno de Datos
A48: CRM | C48: =+UPPER(MID(B48,1,3))&"00"&COUNTA(B$3:B48) -> 008 | D48: Party _Type | E48: Party _Type_Name | F48: Tipo de persona | G48: =CONCATENATE(H48,".",J48,".",K48,".",L48,".",M48) -> INSUNIX.LPV.INSUNIX.TABLE712.DESCRIPT | H48: INSUNIX | I48: INSUNIX | J48: LPV | K48: INSUNIX | L48: TABLE712 | M48: DESCRIPT | P48: CODIGINT=1 (Persona Natural), CODIGINT=2 (Persona Juridica) CODIGEXT=N (Persona Natural), CODIGEXT=E (Persona Juridica) | Q48: 10.20.64.100 | R48: - | S48: - | T48: - | U48: CHAR | V48: 30 | W48: NO | X48: Gaudy Sanchez | Y48: Javier Canchari | Z48: NO | AD48: Gobierno de Datos
A49: CRM | C49: =+UPPER(MID(B49,1,3))&"00"&COUNTA(B$3:B49) -> 008 | D49: Party _Type | E49: Party _Type_Name | F49: Tipo de persona | G49: =CONCATENATE(H49,".",J49,".",K49,".",L49,".",M49) -> INSUNIX.LPG.-.-.- | H49: INSUNIX | I49: INSUNIX | J49: LPG | K49: - | L49: - | M49: - | P49: - | Q49: - | R49: - | S49: - | T49: - | U49: - | V49: - | W49: - | X49: Gaudy Sanchez | Y49: Heli Rojas | Z49: Si | AD49: Gobierno de Datos
A50: CRM | C50: =+UPPER(MID(B50,1,3))&"00"&COUNTA(B$3:B50) -> 008 | D50: Customer | E50: Party_Identifier | F50: Tipo de persona | G50: =CONCATENATE(H50,".",J50,".",K50,".",L50,".",M50) -> INSUNIX.LPE.-.-.- | H50: INSUNIX | I50: INSUNIX | J50: LPE | K50: - | L50: - | M50: - | P50: No aplica | Q50: 10.20.96.102 puerto: 1526 | R50: NO | S50: A demanda | T50: 1994 | U50: - | V50: - | W50: - | X50: Gaudy Sanchez | Y50: Cristian Torres | Z50: NO | AD50: Gobierno de Datos
A51: CRM | B51: CRM | C51: =+UPPER(MID(B51,1,3))&"00"&COUNTA(B$3:B51) -> CRM009 | D51: Legal_Jurisdiction_Party_Identity | E51: Legal_Classification_Code | F51: Código Tipo Documento | G51: =CONCATENATE(H51,".",J51,".",K51,".",L51,".",M51) -> INSIS.LPV.INSIS_PEOPLE_V10.P_PEOPLE.ATTR1 | H51: INSIS | I51: INSIS | J51: LPV | K51: INSIS_PEOPLE_V10 | L51: P_PEOPLE | M51: ATTR1 | N51: NO | O51: NO | P51: No aplica | Q51: 10.10.36.48 | R51: NO | S51: A demanda | T51: 2018 | U51: VARCHAR2 | V51: 50 | W51: NO | X51: Gaudy Sanchez | Y51: Javier Canchari | Z51: SÍ | AD51: Gobierno de Datos
A52: CRM | C52: =+UPPER(MID(B52,1,3))&"00"&COUNTA(B$3:B52) -> 009 | D52: Legal_Jurisdiction_Party_Identity | E52: Legal_Classification_Code | F52: Código Tipo Documento | G52: =CONCATENATE(H52,".",J52,".",K52,".",L52,".",M52) -> VTIME.LPV.INSUDB.CLIDOCUMENTS.NTYPCLIENTDOC | H52: VTIME | I52: INSUDB | J52: LPV | K52: INSUDB | L52: CLIDOCUMENTS | M52: NTYPCLIENTDOC | N52: NO | O52: NO | P52: No aplica | Q52: PRD: 50.0.0.74 | R52: NO | S52: A demanda | T52: 2008 | U52: NUMBER | V52: 2 | W52: NO | X52: Gaudy Sanchez | Y52: Fernando Fuentes | Z52: Si | AD52: Gobierno de Datos
A53: CRM | C53: =+UPPER(MID(B53,1,3))&"00"&COUNTA(B$3:B53) -> 009 | D53: Legal_Jurisdiction_Party_Identity | E53: Legal_Classification_Code | F53: Código Tipo Documento | G53: =CONCATENATE(H53,".",J53,".",K53,".",L53,".",M53) -> VTIME.LPG.INSUDB.CLIDOCUMENTS.NTYPCLIENTDOC | H53: VTIME | I53: INSUDB | J53: LPG | K53: INSUDB | L53: CLIDOCUMENTS | M53: NTYPCLIENTDOC | N53: NO | O53: NO | P53: No aplica | Q53: 50.0.0.74 / oraprod | R53: NO | S53: A demanda | T53: 2008 | U53: NUMBER | V53: 2 | W53: NO | X53: Gaudy Sanchez | Y53: Ellen Romero | Z53: Si | AD53: Gobierno de Datos
A54: CRM | C54: =+UPPER(MID(B54,1,3))&"00"&COUNTA(B$3:B54) -> 009 | D54: Legal_Jurisdiction_Party_Identity | E54: Legal_Classification_Code | F54: Código Tipo Documento | G54: =CONCATENATE(H54,".",J54,".",K54,".",L54,".",M54) -> INSUNIX.LPV.-.-.- | H54: INSUNIX | I54: INSUNIX | J54: LPV | K54: - | L54: - | M54: - | P54: - | Q54: - | R54: - | S54: - | T54: - | U54: - | V54: - | W54: - | X54: Gaudy Sanchez | Y54: Javier Canchari | Z54: NO | AD54: Gobierno de Datos
A55: CRM | C55: =+UPPER(MID(B55,1,3))&"00"&COUNTA(B$3:B55) -> 009 | D55: Legal_Jurisdiction_Party_Identity | E55: Legal_Classification_Code | F55: Código Tipo Documento | G55: =CONCATENATE(H55,".",J55,".",K55,".",L55,".",M55) -> INSUNIX.LPG.-.-.- | H55: INSUNIX | I55: INSUNIX | J55: LPG | K55: - | L55: - | M55: - | P55: - | Q55: - | R55: - | S55: - | T55: - | U55: - | V55: - | W55: - | X55: Gaudy Sanchez | Y55: Heli Rojas | Z55: Si | AD55: Gobierno de Datos
A56: CRM | C56: =+UPPER(MID(B56,1,3))&"00"&COUNTA(B$3:B56) -> 009 | D56: Customer | E56: Party_Identifier | F56: Código Tipo Documento | G56: =CONCATENATE(H56,".",J56,".",K56,".",L56,".",M56) -> INSUNIX.LPE.-.-.- | H56: INSUNIX | I56: INSUNIX | J56: LPE | K56: - | L56: - | M56: - | P56: No aplica | Q56: 10.20.96.102 puerto: 1526 | R56: NO | S56: A demanda | T56: 1994 | U56: - | V56: - | W56: - | X56: Gaudy Sanchez | Y56: Cristian Torres | Z56: NO | AD56: Gobierno de Datos
A57: CRM | B57: CRM | C57: =+UPPER(MID(B57,1,3))&"0"&COUNTA(B$3:B57) -> CRM010 | D57: Legal_Classification | E57: Legal_Classification_Name | F57: Tipo Documento | G57: =CONCATENATE(H57,".",J57,".",K57,".",L57,".",M57) -> INSIS.LPV.INSIS_CUST.CFGLPV_DOCUMENT_TYPE.NAME | H57: INSIS | I57: INSIS | J57: LPV | K57: INSIS_CUST | L57: CFGLPV_DOCUMENT_TYPE | M57: NAME | N57: NO | O57: NO | P57: No aplica | Q57: 10.10.36.48 | R57: NO | S57: A demanda | T57: 2018 | U57: VARCHAR2 | V57: 200 | W57: NO | X57: Gaudy Sanchez | Y57: Javier Canchari | Z57: SÍ | AD57: Gobierno de Datos
A58: CRM | C58: =+UPPER(MID(B58,1,3))&"0"&COUNTA(B$3:B58) -> 010 | D58: Legal_Classification | E58: Legal_Classification_Name | F58: Tipo Documento | G58: =CONCATENATE(H58,".",J58,".",K58,".",L58,".",M58) -> VTIME.LPV.INSUDB.FORMATVALUES.SDESCRIPT | H58: VTIME | I58: INSUDB | J58: LPV | K58: INSUDB | L58: FORMATVALUES | M58: SDESCRIPT | N58: NO | O58: NO | P58: No aplica | Q58: PRD: 50.0.0.74 | R58: NO | S58: A demanda | T58: 2008 | U58: CHAR | V58: 30 | W58: NO | X58: Gaudy Sanchez | Y58: Fernando Fuentes | Z58: Si | AD58: Gobierno de Datos
A59: CRM | C59: =+UPPER(MID(B59,1,3))&"0"&COUNTA(B$3:B59) -> 010 | D59: Legal_Classification | E59: Legal_Classification_Name | F59: Tipo Documento | G59: =CONCATENATE(H59,".",J59,".",K59,".",L59,".",M59) -> VTIME.LPG.INSUDB.FORMATVALUES.SDESCRIPT | H59: VTIME | I59: INSUDB | J59: LPG | K59: INSUDB | L59: FORMATVALUES | M59: SDESCRIPT | N59: NO | O59: NO | P59: No aplica | Q59: 50.0.0.74 / oraprod | R59: NO | S59: A demanda | T59: 2008 | U59: CHAR | V59: 30 | W59: NO | X59: Gaudy Sanchez | Y59: Ellen Romero | Z59: Si | AD59: Gobierno de Datos
A60: CRM | C60: =+UPPER(MID(B60,1,3))&"0"&COUNTA(B$3:B60) -> 010 | D60: Legal_Classification | E60: Legal_Classification_Name | F60: Tipo Documento | G60: =CONCATENATE(H60,".",J60,".",K60,".",L60,".",M60) -> INSUNIX.LPV.-.-.- | H60: INSUNIX | I60: INSUNIX | J60: LPV | K60: - | L60: - | M60: - | P60: - | Q60: - | R60: - | S60: - | T60: - | U60: - | V60: - | W60: - | X60: Gaudy Sanchez | Y60: Javier Canchari | Z60: NO | AD60: Gobierno de Datos
A61: CRM | C61: =+UPPER(MID(B61,1,3))&"0"&COUNTA(B$3:B61) -> 010 | D61: Legal_Classification | E61: Legal_Classification_Name | F61: Tipo Documento | G61: =CONCATENATE(H61,".",J61,".",K61,".",L61,".",M61) -> INSUNIX.LPG.-.-.- | H61: INSUNIX | I61: INSUNIX | J61: LPG | K61: - | L61: - | M61: - | P61: - | Q61: - | R61: - | S61: - | T61: - | U61: - | V61: - | W61: - | X61: Gaudy Sanchez | Y61: Heli Rojas | Z61: Si | AD61: Gobierno de Datos
A62: CRM | C62: =+UPPER(MID(B62,1,3))&"00"&COUNTA(B$3:B62) -> 0010 | D62: Customer | E62: Party_Identifier | F62: Tipo Documento | G62: =CONCATENATE(H62,".",J62,".",K62,".",L62,".",M62) -> INSUNIX.LPE.-.-.- | H62: INSUNIX | I62: INSUNIX | J62: LPE | K62: - | L62: - | M62: - | P62: No aplica | Q62: 10.20.96.102 puerto: 1526 | R62: NO | S62: A demanda | T62: 1994 | U62: - | V62: - | W62: - | X62: Gaudy Sanchez | Y62: Cristian Torres | Z62: NO | AD62: Gobierno de Datos
A63: CRM | B63: CRM | C63: =+UPPER(MID(B63,1,3))&"0"&COUNTA(B$3:B63) -> CRM011 | D63: Legal_Jurisdiction_Party_Identity | E63: Legal Jurisdiction Party Identifier | F63: Número Documento | G63: =CONCATENATE(H63,".",J63,".",K63,".",L63,".",M63) -> INSIS.LPV.INSIS_PEOPLE_V10.P_PEOPLE.EGN | H63: INSIS | I63: INSIS | J63: LPV | K63: INSIS_PEOPLE_V10 | L63: P_PEOPLE | M63: EGN | N63: SÍ | O63: NO | P63: No aplica | Q63: 10.10.36.48 | R63: NO | S63: A demanda | T63: 2018 | U63: VARCHAR2 | V63: 50 | W63: NO | X63: Gaudy Sanchez | Y63: Javier Canchari | Z63: SÍ | AD63: Gobierno de Datos
A64: CRM | C64: =+UPPER(MID(B64,1,3))&"0"&COUNTA(B$3:B64) -> 011 | D64: Legal_Jurisdiction_Party_Identity | E64: Legal Jurisdiction Party Identifier | F64: Número Documento | G64: =CONCATENATE(H64,".",J64,".",K64,".",L64,".",M64) -> VTIME.LPV.INSUDB.CLIDOCUMENTS.SCLINUMDOCU | H64: VTIME | I64: INSUDB | J64: LPV | K64: INSUDB | L64: CLIDOCUMENTS | M64: SCLINUMDOCU | N64: SÍ | O64: NO | P64: No aplica | Q64: PRD: 50.0.0.74 | R64: NO | S64: A demanda | T64: 2008 | U64: CHAR | V64: 12 | W64: SI | X64: Gaudy Sanchez | Y64: Fernando Fuentes | Z64: Si | AD64: Gobierno de Datos
A65: CRM | C65: =+UPPER(MID(B65,1,3))&"0"&COUNTA(B$3:B65) -> 011 | D65: Legal_Jurisdiction_Party_Identity | E65: Legal Jurisdiction Party Identifier | F65: Número Documento | G65: =CONCATENATE(H65,".",J65,".",K65,".",L65,".",M65) -> VTIME.LPG.INSUDB.CLIDOCUMENTS.SCLINUMDOCU | H65: VTIME | I65: INSUDB | J65: LPG | K65: INSUDB | L65: CLIDOCUMENTS | M65: SCLINUMDOCU | N65: SÍ | O65: NO | P65: No aplica | Q65: 50.0.0.74 / oraprod | R65: NO | S65: A demanda | T65: 2008 | U65: CHAR | V65: 12 | W65: NO | X65: Gaudy Sanchez | Y65: Ellen Romero | Z65: Si | AD65: Gobierno de Datos
A66: CRM | C66: =+UPPER(MID(B66,1,3))&"0"&COUNTA(B$3:B66) -> 011 | D66: Legal_Jurisdiction_Party_Identity | E66: Legal Jurisdiction Party Identifier | F66: Número Documento | G66: =CONCATENATE(H66,".",J66,".",K66,".",L66,".",M66) -> INSUNIX.LPV.INFORMIX.CLIENT.ELEC_BOOK | H66: INSUNIX | I66: INSUNIX | J66: LPV | K66: INFORMIX | L66: CLIENT | M66: ELEC_BOOK | P66: No aplica | Q66: 10.20.64.100 | R66: NO | S66: A demanda | T66: 1994 | U66: CHAR | V66: 12 | W66: NO | X66: Gaudy Sanchez | Y66: Javier Canchari | Z66: NO | AD66: Gobierno de Datos
A67: CRM | C67: =+UPPER(MID(B67,1,3))&"0"&COUNTA(B$3:B67) -> 011 | D67: Legal_Jurisdiction_Party_Identity | E67: Legal Jurisdiction Party Identifier | F67: Número Documento | G67: =CONCATENATE(H67,".",J67,".",K67,".",L67,".",M67) -> INSUNIX.LPV.INFORMIX.CLIENT.RUC | H67: INSUNIX | I67: INSUNIX | J67: LPV | K67: INFORMIX | L67: CLIENT | M67: RUC | P67: No aplica | Q67: 10.20.64.100 | R67: NO | S67: A demanda | T67: 1994 | U67: CHAR | V67: 12 | W67: NO | X67: Gaudy Sanchez | Y67: Javier Canchari | Z67: NO | AD67: Gobierno de Datos
A68: CRM | C68: =+UPPER(MID(B68,1,3))&"0"&COUNTA(B$3:B68) -> 011 | D68: Legal_Jurisdiction_Party_Identity | E68: Legal Jurisdiction Party Identifier | F68: Número Documento | G68: =CONCATENATE(H68,".",J68,".",K68,".",L68,".",M68) -> INSUNIX.LPG.INFORMIX.CLIENT.ELEC_BOOK | H68: INSUNIX | I68: INSUNIX | J68: LPG | K68: INFORMIX | L68: CLIENT | M68: ELEC_BOOK | N68: SÍ | O68: NO | P68: No aplica | Q68: 10.20.162.27 | R68: NO | S68: A demanda | T68: 1994 | U68: CHAR | V68: 12 | W68: NO | X68: Gaudy Sanchez | Y68: Heli Rojas | Z68: Si | AD68: Gobierno de Datos
A69: CRM | C69: =+UPPER(MID(B69,1,3))&"0"&COUNTA(B$3:B69) -> 011 | D69: Legal_Jurisdiction_Party_Identity | E69: Legal Jurisdiction Party Identifier | F69: Número Documento | G69: =CONCATENATE(H69,".",J69,".",K69,".",L69,".",M69) -> INSUNIX.LPG.INFORMIX.CLIENT.RUC | H69: INSUNIX | I69: INSUNIX | J69: LPG | K69: INFORMIX | L69: CLIENT | M69: RUC | N69: SÍ | O69: NO | P69: No aplica | Q69: 10.20.162.27 | R69: NO | S69: A demanda | T69: 1994 | U69: CHAR | V69: 12 | W69: NO | X69: Gaudy Sanchez | Y69: Heli Rojas | Z69: Si | AD69: Gobierno de Datos
A70: CRM | C70: =+UPPER(MID(B70,1,3))&"0"&COUNTA(B$3:B70) -> 011 | D70: Customer | E70: Party_Identifier | F70: Número Documento | G70: =CONCATENATE(H70,".",J70,".",K70,".",L70,".",M70) -> INSUNIX.LPE.INFORMIX.CLIENT.ELEC_BOOK | H70: INSUNIX | I70: INSUNIX | J70: LPE | K70: INFORMIX | L70: CLIENT | M70: ELEC_BOOK | P70: No aplica | Q70: 10.20.96.102 puerto: 1526 | R70: NO | S70: A demanda | T70: 1994 | U70: CHAR | V70: 12 | W70: NO | X70: Gaudy Sanchez | Y70: Cristian Torres | Z70: NO | AD70: Gobierno de Datos
A71: CRM | C71: =+UPPER(MID(B71,1,3))&"0"&COUNTA(B$3:B71) -> 011 | D71: Customer | E71: Party_Identifier | F71: Número Documento | G71: =CONCATENATE(H71,".",J71,".",K71,".",L71,".",M71) -> INSUNIX.LPE.INFORMIX.CLIENT.RUC | H71: INSUNIX | I71: INSUNIX | J71: LPE | K71: INFORMIX | L71: CLIENT | M71: RUC | P71: No aplica | Q71: 10.20.96.102 puerto: 1526 | R71: NO | S71: A demanda | T71: 1994 | U71: CHAR | V71: 12 | W71: NO | X71: Gaudy Sanchez | Y71: Cristian Torres | Z71: NO | AD71: Gobierno de Datos
A72: CRM | C72: =+UPPER(MID(B72,1,3))&"0"&COUNTA(B$3:B72) -> 011 | D72: Legal_Jurisdiction_Party_Identity | E72: Legal Jurisdiction Party Identifier | F72: RUC de Persona Natural | G72: =CONCATENATE(H72,".",J72,".",K72,".",L72,".",M72) -> INSIS.LPV.INSIS_SYS_V10.DOC_DOCUMENTS.DOC_NUM | H72: INSIS | I72: INSIS | J72: LPV | K72: INSIS_SYS_V10 | L72: DOC_DOCUMENTS | M72: DOC_NUM | N72: SÍ | O72: NO | P72: Condición: DOC_ID = 404 | Q72: 10.10.36.48 | R72: NO | S72: A demanda | T72: 2018 | U72: VARCHAR2 | V72: 50 | W72: NO | X72: Gaudy Sanchez | Y72: Javier Canchari | Z72: SÍ | AD72: Gobierno de Datos
A73: CRM | C73: =+UPPER(MID(B73,1,3))&"0"&COUNTA(B$3:B73) -> 011 | D73: Legal_Jurisdiction_Party_Identity | E73: Legal Jurisdiction Party Identifier | F73: RUC de Persona Natural | G73: =CONCATENATE(H73,".",J73,".",K73,".",L73,".",M73) -> VTIME.LPV.INSUDB.CLIDOCUMENTS.SCLINUMDOCU | H73: VTIME | I73: INSUDB | J73: LPV | K73: INSUDB | L73: CLIDOCUMENTS | M73: SCLINUMDOCU | N73: SÍ | O73: NO | P73: No aplica | Q73: PRD: 50.0.0.74 | R73: NO | S73: A demanda | T73: 2008 | U73: CHAR | V73: 12 | W73: NO | X73: Gaudy Sanchez | Y73: Fernando Fuentes | Z73: Si | AD73: Gobierno de Datos
A74: CRM | C74: =+UPPER(MID(B74,1,3))&"0"&COUNTA(B$3:B74) -> 011 | D74: Legal_Jurisdiction_Party_Identity | E74: Legal Jurisdiction Party Identifier | F74: RUC de Persona Natural | G74: =CONCATENATE(H74,".",J74,".",K74,".",L74,".",M74) -> VTIME.LPG.INSUDB.CLIDOCUMENTS.SCLINUMDOCU | H74: VTIME | I74: INSUDB | J74: LPG | K74: INSUDB | L74: CLIDOCUMENTS | M74: SCLINUMDOCU | N74: SÍ | O74: NO | P74: No aplica | Q74: 50.0.0.74 / oraprod | R74: NO | S74: A demanda | T74: 2008 | U74: CHAR | V74: 12 | W74: NO | X74: Gaudy Sanchez | Y74: Ellen Romero | Z74: Si | AD74: Gobierno de Datos
A75: CRM | C75: =+UPPER(MID(B75,1,3))&"0"&COUNTA(B$3:B75) -> 011 | D75: Legal_Jurisdiction_Party_Identity | E75: Legal Jurisdiction Party Identifier | F75: RUC de Persona Natural | G75: =CONCATENATE(H75,".",J75,".",K75,".",L75,".",M75) -> INSUNIX.LPV.-.-.- | H75: INSUNIX | I75: INSUNIX | J75: LPV | K75: - | L75: - | M75: - | P75: - | Q75: - | R75: - | S75: - | T75: - | U75: - | V75: - | W75: - | X75: Gaudy Sanchez | Y75: Javier Canchari | Z75: NO | AD75: Gobierno de Datos
A76: CRM | C76: =+UPPER(MID(B76,1,3))&"0"&COUNTA(B$3:B76) -> 011 | D76: Legal_Jurisdiction_Party_Identity | E76: Legal Jurisdiction Party Identifier | F76: RUC de Persona Natural | G76: =CONCATENATE(H76,".",J76,".",K76,".",L76,".",M76) -> INSUNIX.LPG.-.-.- | H76: INSUNIX | I76: INSUNIX | J76: LPG | K76: - | L76: - | M76: - | P76: - | Q76: - | R76: - | S76: - | T76: - | U76: - | V76: - | W76: - | X76: Gaudy Sanchez | Y76: Heli Rojas | Z76: Si | AD76: Gobierno de Datos
A77: CRM | C77: =+UPPER(MID(B77,1,3))&"0"&COUNTA(B$3:B77) -> 011 | D77: Customer | E77: Party_Identifier | F77: RUC de Persona Natural | G77: =CONCATENATE(H77,".",J77,".",K77,".",L77,".",M77) -> INSUNIX.LPE.-.-.- | H77: INSUNIX | I77: INSUNIX | J77: LPE | K77: - | L77: - | M77: - | P77: No aplica | Q77: 10.20.96.102 puerto: 1526 | R77: NO | S77: A demanda | T77: 1994 | U77: - | V77: - | W77: - | X77: Gaudy Sanchez | Y77: Cristian Torres | Z77: NO | AD77: Gobierno de Datos
A78: CRM | B78: CRM | C78: =+UPPER(MID(B78,1,3))&"0"&COUNTA(B$3:B78) -> CRM012 | D78: Grouping | E78: Grouping_Identifier | F78: Código Grupo económico | G78: =CONCATENATE(H78,".",J78,".",K78,".",L78,".",M78) -> INSIS.LPV.INSIS_PEOPLE_V10.P_PEOPLE_GROUPS.GROUP_CODE | H78: INSIS | I78: INSIS | J78: LPV | K78: INSIS_PEOPLE_V10 | L78: P_PEOPLE_GROUPS | M78: GROUP_CODE | N78: NO | O78: NO | P78: No aplica | Q78: 10.10.36.48 | R78: NO | S78: A demanda | T78: 2018 | U78: VARCHAR2 | V78: 20 | W78: NO | X78: Gaudy Sanchez | Y78: Javier Canchari | Z78: SÍ | AD78: Gobierno de Datos
A79: CRM | C79: =+UPPER(MID(B79,1,3))&"0"&COUNTA(B$3:B79) -> 012 | D79: Grouping | E79: Grouping_Identifier | F79: Código Grupo económico | G79: =CONCATENATE(H79,".",J79,".",K79,".",L79,".",M79) -> VTIME.LPV.-.-.- | H79: VTIME | I79: INSUDB | J79: LPV | K79: - | L79: - | M79: - | P79: - | Q79: PRD: 50.0.0.74 | R79: NO | S79: A demanda | T79: 2008 | U79: - | V79: - | W79: - | X79: Gaudy Sanchez | Y79: Fernando Fuentes | Z79: Si | AD79: Gobierno de Datos
A80: CRM | C80: =+UPPER(MID(B80,1,3))&"0"&COUNTA(B$3:B80) -> 012 | D80: Grouping | E80: Grouping_Identifier | F80: Código Grupo económico | G80: =CONCATENATE(H80,".",J80,".",K80,".",L80,".",M80) -> VTIME.LPG.-.-.- | H80: VTIME | I80: INSUNIX | J80: LPG | K80: - | L80: - | M80: - | P80: - | Q80: - | R80: - | S80: - | T80: - | U80: - | V80: - | W80: - | X80: Gaudy Sanchez | Y80: Ellen Romero | Z80: Si | AD80: Gobierno de Datos
A81: CRM | C81: =+UPPER(MID(B81,1,3))&"0"&COUNTA(B$3:B81) -> 012 | D81: Customer | E81: Party_Identifier | F81: Código Grupo económico | G81: =CONCATENATE(H81,".",J81,".",K81,".",L81,".",M81) -> INSUNIX.LPV.-.-.- | H81: INSUNIX | I81: INSUNIX | J81: LPV | K81: - | L81: - | M81: - | P81: - | Q81: - | R81: - | S81: - | T81: - | U81: - | V81: - | W81: - | X81: Gaudy Sanchez | Y81: Javier Canchari | Z81: NO | AD81: Gobierno de Datos
A82: CRM | C82: =+UPPER(MID(B82,1,3))&"0"&COUNTA(B$3:B82) -> 012 | D82: Grouping | E82: Grouping_Identifier | F82: Código Grupo económico | G82: =CONCATENATE(H82,".",J82,".",K82,".",L82,".",M82) -> INSUNIX.LPG.-.-.- | H82: INSUNIX | I82: INSUNIX | J82: LPG | K82: - | L82: - | M82: - | P82: - | Q82: - | R82: - | S82: - | T82: - | U82: - | V82: - | W82: - | X82: Gaudy Sanchez | Y82: Heli Rojas | Z82: Si | AD82: Gobierno de Datos
A83: CRM | C83: =+UPPER(MID(B83,1,3))&"0"&COUNTA(B$3:B83) -> 012 | D83: Customer | E83: Party_Identifier | F83: Código Grupo económico | G83: =CONCATENATE(H83,".",J83,".",K83,".",L83,".",M83) -> INSUNIX.LPE.-.-.- | H83: INSUNIX | I83: INSUNIX | J83: LPE | K83: - | L83: - | M83: - | P83: No aplica | Q83: 10.20.96.102 puerto: 1526 | R83: NO | S83: A demanda | T83: 1994 | U83: - | V83: - | W83: - | X83: Gaudy Sanchez | Y83: Cristian Torres | Z83: NO | AD83: Gobierno de Datos
A84: CRM | B84: CRM | C84: =+UPPER(MID(B84,1,3))&"0"&COUNTA(B$3:B84) -> CRM013 | D84: Grouping | E84: Grouping_Name | F84: Grupo económico | G84: =CONCATENATE(H84,".",J84,".",K84,".",L84,".",M84) -> INSIS.LPV.INSIS_PEOPLE_V10.HT_PEOPLE_GROUPS.NAME | H84: INSIS | I84: INSIS | J84: LPV | K84: INSIS_PEOPLE_V10 | L84: HT_PEOPLE_GROUPS | M84: NAME | N84: SÍ | O84: NO | P84: condicion: GROUP_TYPE = 'SEGMENT' | Q84: 10.10.36.48 | R84: NO | S84: A demanda | T84: 2018 | U84: VARCHAR2 | V84: 250 | W84: NO | X84: Gaudy Sanchez | Y84: Javier Canchari | Z84: SÍ | AD84: Gobierno de Datos
A85: CRM | C85: =+UPPER(MID(B85,1,3))&"0"&COUNTA(B$3:B85) -> 013 | D85: Grouping | E85: Grouping_Name | F85: Grupo económico | G85: =CONCATENATE(H85,".",J85,".",K85,".",L85,".",M85) -> VTIME.LPV.-.-.- | H85: VTIME | I85: INSUDB | J85: LPV | K85: - | L85: - | M85: - | P85: - | Q85: PRD: 50.0.0.74 | R85: NO | S85: A demanda | T85: 2008 | U85: - | V85: - | W85: - | X85: Gaudy Sanchez | Y85: Fernando Fuentes | Z85: Si | AD85: Gobierno de Datos
A86: CRM | C86: =+UPPER(MID(B86,1,3))&"0"&COUNTA(B$3:B86) -> 013 | D86: Grouping | E86: Grouping_Name | F86: Grupo económico | G86: =CONCATENATE(H86,".",J86,".",K86,".",L86,".",M86) -> VTIME.LPG.-.-.- | H86: VTIME | I86: INSUNIX | J86: LPG | K86: - | L86: - | M86: - | P86: - | Q86: - | R86: - | S86: - | T86: - | U86: - | V86: - | W86: - | X86: Gaudy Sanchez | Y86: Ellen Romero | Z86: Si | AD86: Gobierno de Datos
A87: CRM | C87: =+UPPER(MID(B87,1,3))&"0"&COUNTA(B$3:B87) -> 013 | D87: Grouping | E87: Party_Identifier | F87: Grupo económico | G87: =CONCATENATE(H87,".",J87,".",K87,".",L87,".",M87) -> INSUNIX.LPV.-.-.- | H87: INSUNIX | I87: INSUNIX | J87: LPV | K87: - | L87: - | M87: - | P87: - | Q87: - | R87: - | S87: - | T87: - | U87: - | V87: - | W87: - | X87: Gaudy Sanchez | Y87: Javier Canchari | Z87: NO | AD87: Gobierno de Datos
A88: CRM | C88: =+UPPER(MID(B88,1,3))&"0"&COUNTA(B$3:B88) -> 013 | D88: Grouping | E88: Grouping_Name | F88: Grupo económico | G88: =CONCATENATE(H88,".",J88,".",K88,".",L88,".",M88) -> INSUNIX.LPG.-.-.- | H88: INSUNIX | I88: INSUNIX | J88: LPG | K88: - | L88: - | M88: - | P88: - | Q88: - | R88: - | S88: - | T88: - | U88: - | V88: - | W88: - | X88: Gaudy Sanchez | Y88: Heli Rojas | Z88: Si | AD88: Gobierno de Datos
A89: CRM | C89: =+UPPER(MID(B89,1,3))&"0"&COUNTA(B$3:B89) -> 013 | D89: Customer | E89: Party_Identifier | F89: Grupo económico | G89: =CONCATENATE(H89,".",J89,".",K89,".",L89,".",M89) -> INSUNIX.LPE.-.-.- | H89: INSUNIX | I89: INSUNIX | J89: LPE | K89: - | L89: - | M89: - | P89: No aplica | Q89: 10.20.96.102 puerto: 1526 | R89: NO | S89: A demanda | T89: 1994 | U89: - | V89: - | W89: - | X89: Gaudy Sanchez | Y89: Cristian Torres | Z89: NO | AD89: Gobierno de Datos
A90: CRM | B90: CRM | C90: =+UPPER(MID(B90,1,3))&"0"&COUNTA(B$3:B90) -> CRM014 | D90: Person | E90: Gender_Code | F90: Código Género | G90: =CONCATENATE(H90,".",J90,".",K90,".",L90,".",M90) -> INSIS.LPV.INSIS_PEOPLE_V10.P_PEOPLE.SEX | H90: INSIS | I90: INSIS | J90: LPV | K90: INSIS_PEOPLE_V10 | L90: P_PEOPLE | M90: SEX | N90: NO | O90: NO | P90: No aplica | Q90: 10.10.36.48 | R90: NO | S90: A demanda | T90: 2018 | U90: NUMBER | V90: 1 | W90: NO | X90: Gaudy Sanchez | Y90: Javier Canchari | Z90: SÍ | AD90: Gobierno de Datos
A91: CRM | C91: =+UPPER(MID(B91,1,3))&"0"&COUNTA(B$3:B91) -> 014 | D91: Person | E91: Gender_Code | F91: Código Género | G91: =CONCATENATE(H91,".",J91,".",K91,".",L91,".",M91) -> VTIME.LPV.INSUDB.CLIENT.SSEXCLIEN | H91: VTIME | I91: INSUDB | J91: LPV | K91: INSUDB | L91: CLIENT | M91: SSEXCLIEN | N91: NO | O91: NO | P91: No aplica | Q91: PRD: 50.0.0.74 | R91: NO | S91: A demanda | T91: 2008 | U91: CHAR | V91: 1 | W91: NO | X91: Gaudy Sanchez | Y91: Fernando Fuentes | Z91: Si | AD91: Gobierno de Datos
A92: CRM | C92: =+UPPER(MID(B92,1,3))&"0"&COUNTA(B$3:B92) -> 014 | D92: Person | E92: Gender_Code | F92: Código Género | G92: =CONCATENATE(H92,".",J92,".",K92,".",L92,".",M92) -> VTIME.LPG.INSUDB.CLIENT.SSEXCLIEN | H92: VTIME | I92: INSUDB | J92: LPG | K92: INSUDB | L92: CLIENT | M92: SSEXCLIEN | N92: NO | O92: NO | P92: No aplica | Q92: 50.0.0.74 / oraprod | R92: NO | S92: A demanda | T92: 2008 | U92: CHAR | V92: 1 | W92: NO | X92: Gaudy Sanchez | Y92: Ellen Romero | Z92: Si | AD92: Gobierno de Datos
A93: CRM | C93: =+UPPER(MID(B93,1,3))&"0"&COUNTA(B$3:B93) -> 014 | D93: Person | E93: Gender_Code | F93: Código Género | G93: =CONCATENATE(H93,".",J93,".",K93,".",L93,".",M93) -> INSUNIX.LPV.INFORMIX.CLIENT.SEXCLIEN | H93: INSUNIX | I93: INSUNIX | J93: LPV | K93: INFORMIX | L93: CLIENT | M93: SEXCLIEN | N93: NO | O93: NO | P93: No aplica | Q93: 10.20.64.100 | R93: NO | S93: A demanda | T93: 1994 | U93: CHAR | V93: 1 | W93: NO | X93: Gaudy Sanchez | Y93: Javier Canchari | Z93: NO | AD93: Gobierno de Datos
A94: CRM | C94: =+UPPER(MID(B94,1,3))&"0"&COUNTA(B$3:B94) -> 014 | D94: Person | E94: Gender_Code | F94: Código Género | G94: =CONCATENATE(H94,".",J94,".",K94,".",L94,".",M94) -> INSUNIX.LPG.INFORMIX.CLIENT.SEXCLIEN | H94: INSUNIX | I94: INSUNIX | J94: LPG | K94: INFORMIX | L94: CLIENT | M94: SEXCLIEN | N94: NO | O94: NO | P94: No aplica | Q94: 10.20.162.27 | R94: NO | S94: A demanda | T94: 1994 | U94: CHAR | V94: 1 | W94: NO | X94: Gaudy Sanchez | Y94: Heli Rojas | Z94: Si | AD94: Gobierno de Datos
A95: CRM | C95: =+UPPER(MID(B95,1,3))&"0"&COUNTA(B$3:B95) -> 014 | D95: Customer | E95: Party_Identifier | F95: Código Género | G95: =CONCATENATE(H95,".",J95,".",K95,".",L95,".",M95) -> INSUNIX.LPE.INFORMIX.CLIENT.SEXCLIEN | H95: INSUNIX | I95: INSUNIX | J95: LPE | K95: INFORMIX | L95: CLIENT | M95: SEXCLIEN | P95: No aplica | Q95: 10.20.96.102 puerto: 1526 | R95: NO | S95: A demanda | T95: 1994 | U95: CHAR | V95: 1 | W95: NO | X95: Gaudy Sanchez | Y95: Cristian Torres | Z95: NO | AD95: Gobierno de Datos
A96: CRM | B96: CRM | C96: =+UPPER(MID(B96,1,3))&"0"&COUNTA(B$3:B96) -> CRM015 | D96: Gender | E96: Gender_Name | F96: Género | G96: =CONCATENATE(H96,".",J96,".",K96,".",L96,".",M96) -> INSIS.LPV.INSIS_PEOPLE_V10.HST_PEOPLE_SEX.NAME | H96: INSIS | I96: INSIS | J96: LPV | K96: INSIS_PEOPLE_V10 | L96: HST_PEOPLE_SEX | M96: NAME | N96: SÍ | O96: NO | P96: No aplica | Q96: 10.10.36.48 | R96: NO | S96: A demanda | T96: 2018 | U96: VARCHAR2 | V96: 40 | W96: NO | X96: Gaudy Sanchez | Y96: Javier Canchari | Z96: SÍ | AD96: Gobierno de Datos
A97: CRM | C97: =+UPPER(MID(B97,1,3))&"0"&COUNTA(B$3:B97) -> 015 | D97: Gender | E97: Gender_Name | F97: Género | G97: =CONCATENATE(H97,".",J97,".",K97,".",L97,".",M97) -> VTIME.LPV.INSUDB.TABLE18.SDESCRIPT | H97: VTIME | I97: INSUDB | J97: LPV | K97: INSUDB | L97: TABLE18 | M97: SDESCRIPT | N97: SÍ | O97: NO | P97: No aplica | Q97: PRD: 50.0.0.74 | R97: NO | S97: A demanda | T97: 2008 | U97: CHAR | V97: 30 | W97: NO | X97: Gaudy Sanchez | Y97: Fernando Fuentes | Z97: Si | AD97: Gobierno de Datos
A98: CRM | C98: =+UPPER(MID(B98,1,3))&"0"&COUNTA(B$3:B98) -> 015 | D98: Gender | E98: Gender_Name | F98: Género | G98: =CONCATENATE(H98,".",J98,".",K98,".",L98,".",M98) -> VTIME.LPG.INSUDB.TABLE18.SDESCRIPT | H98: VTIME | I98: INSUDB | J98: LPG | K98: INSUDB | L98: TABLE18 | M98: SDESCRIPT | N98: SÍ | O98: NO | P98: No aplica | Q98: 50.0.0.74 / oraprod | R98: NO | S98: A demanda | T98: 2008 | U98: CHAR | V98: 30 | W98: NO | X98: Gaudy Sanchez | Y98: Ellen Romero | Z98: Si | AD98: Gobierno de Datos
A99: CRM | C99: =+UPPER(MID(B99,1,3))&"0"&COUNTA(B$3:B99) -> 015 | D99: Gender | E99: Gender_Name | F99: Género | G99: =CONCATENATE(H99,".",J99,".",K99,".",L99,".",M99) -> INSUNIX.LPV.INSUNIX.TABLE18.DESCRIPT | H99: INSUNIX | I99: INSUNIX | J99: LPV | K99: INSUNIX | L99: TABLE18 | M99: DESCRIPT | N99: SÍ | O99: NO | P99: No aplica | Q99: 10.20.64.100 | R99: NO | S99: A demanda | T99: 1994 | U99: CHAR | V99: 30 | W99: NO | X99: Gaudy Sanchez | Y99: Javier Canchari | Z99: NO | AD99: Gobierno de Datos
A100: CRM | C100: =+UPPER(MID(B100,1,3))&"0"&COUNTA(B$3:B100) -> 015 | D100: Gender | E100: Gender_Name | F100: Género | G100: =CONCATENATE(H100,".",J100,".",K100,".",L100,".",M100) -> INSUNIX.LPG.INSUNIX.TABLE18.DESCRIPT | H100: INSUNIX | I100: INSUNIX | J100: LPG | K100: INSUNIX | L100: TABLE18 | M100: DESCRIPT | N100: SÍ | O100: NO | P100: No aplica | Q100: 10.20.162.27 | R100: NO | S100: A demanda | T100: 1994 | U100: CHAR | V100: 30 | W100: NO | X100: Gaudy Sanchez | Y100: Heli Rojas | Z100: Si | AD100: Gobierno de Datos
...

Sheet LAKEHOUSE
A1: CORE | B1: CIA | C1: ESQUEMA | D1: TABLA
A2: INSUNIX | B2: LPE | C2: diediaz0 | D2: table10b | E2: =CONCATENATE(A2,".",B2,".",C2,".",D2) -> INSUNIX.LPE.diediaz0.table10b
A3: INSUNIX | B3: LPE | C3: diediaz0 | D3: table10b | E3: =CONCATENATE(A3,".",B3,".",C3,".",D3) -> INSUNIX.LPE.diediaz0.table10b
A4: INSUNIX | B4: LPE | C4: diediaz0 | D4: table10b | E4: =CONCATENATE(A4,".",B4,".",C4,".",D4) -> INSUNIX.LPE.diediaz0.table10b
A5: INSUNIX | B5: LPE | C5: diediaz0 | D5: table10b | E5: =CONCATENATE(A5,".",B5,".",C5,".",D5) -> INSUNIX.LPE.diediaz0.table10b
A6: INSUNIX | B6: LPE | C6: diediaz0 | D6: table10b | E6: =CONCATENATE(A6,".",B6,".",C6,".",D6) -> INSUNIX.LPE.diediaz0.table10b
A7: INSUNIX | B7: LPE | C7: informix | D7: cession_rea | E7: =CONCATENATE(A7,".",B7,".",C7,".",D7) -> INSUNIX.LPE.informix.cession_rea
A8: INSUNIX | B8: LPE | C8: informix | D8: cession_rea | E8: =CONCATENATE(A8,".",B8,".",C8,".",D8) -> INSUNIX.LPE.informix.cession_rea
A9: INSUNIX | B9: LPE | C9: informix | D9: cession_rea | E9: =CONCATENATE(A9,".",B9,".",C9,".",D9) -> INSUNIX.LPE.informix.cession_rea
A10: INSUNIX | B10: LPE | C10: informix | D10: cession_rea | E10: =CONCATENATE(A10,".",B10,".",C10,".",D10) -> INSUNIX.LPE.informix.cession_rea
A11: INSUNIX | B11: LPE | C11: informix | D11: cession_rea | E11: =CONCATENATE(A11,".",B11,".",C11,".",D11) -> INSUNIX.LPE.informix.cession_rea
A12: INSUNIX | B12: LPE | C12: informix | D12: cession_rea | E12: =CONCATENATE(A12,".",B12,".",C12,".",D12) -> INSUNIX.LPE.informix.cession_rea
A13: INSUNIX | B13: LPE | C13: informix | D13: cession_rea | E13: =CONCATENATE(A13,".",B13,".",C13,".",D13) -> INSUNIX.LPE.informix.cession_rea
... A13372: INSIS | B13372: LPV | C13372: INSIS_GEN_BLC_V10 | D13372: BLC_ACTIONS | E13372: =CONCATENATE(A13372,".",B13372,".",C13372,".",D13372) -> INSIS.LPV.INSIS_GEN_BLC_V10.BLC_ACTIONS

Sheet REPORTE (Tbl Campo)
B2: Aplicativo | C2: Compañía | D2: Esquema | E2: Tablas del Diccionario | G2: Catálogo/No Catálogo | H2: Personal | I2: Sensible | J2: Llave | K2: Tabla encontradas en Lakehouse | M2: Aplicativo(s) | N2: Fuente oficial | O2: Compañia | P2: Esquema | Q2: Tabla en fuente oficial | R2: Campo en Fuente Oficial | S2: LLAVE | T2: Personal | U2: Sensible | V2: Cuenta de Campo en Fuente Oficial | W2: Campos encontradas en Lakehouse | AF2: X
B3: INSIS | C3: LPV | D3: INSIS_PEOPLE_V10 | E3: P_CLIENTS | F3: ="SELECT * FROM "&D3&"."&E3 -> SELECT * FROM INSIS_PEOPLE_V10.P_CLIENTS | G3: NO CATÁLOGO | J3: =CONCATENATE(B3,".",C3,".",D3,".",E3) -> INSIS.LPV.INSIS_PEOPLE_V10.P_CLIENTS | K3: {=IF(AND(COUNTIF(LAKEHOUSE!$E$2:$E$14000,$J$3:$J$310)>0),"X","-")} -> - | M3: INSIS | N3: INSIS | O3: LPV | P3: INSIS_PEOPLE_V10 | Q3: P_CLIENTS | R3: CLIENT_ID | S3: =CONCATENATE(M3,".",O3,".",P3,".",Q3,".",R3) -> INSIS.LPV.INSIS_PEOPLE_V10.P_CLIENTS.CLIENT_ID | T3: {=IFERROR(INDEX('3.Trazabilidad'!N:N, MATCH(S3, '3.Trazabilidad'!G:G, 0)), "-")} -> NO | U3: {=IFERROR(INDEX('3.Trazabilidad'!O:O, MATCH(S3, '3.Trazabilidad'!G:G, 0)), "-")} -> NO | V3: 1 | W3: {=IF(AND(COUNTIF('LAKEHOUSE (Tbl Campos)'!$F$2:$F$14000,$S$3:$S$910)>0),"X","-")} -> -
B4: INSIS | C4: LPV | D4: INSIS_PEOPLE_V10 | E4: P_PEOPLE | F4: ="SELECT * FROM "&D4&"."&E4 -> SELECT * FROM INSIS_PEOPLE_V10.P_PEOPLE | G4: NO CATÁLOGO | J4: =CONCATENATE(B4,".",C4,".",D4,".",E4) -> INSIS.LPV.INSIS_PEOPLE_V10.P_PEOPLE | K4: {=IF(AND(COUNTIF(LAKEHOUSE!$E$2:$E$14000,$J$3:$J$310)>0),"X","-")} -> - | M4: INSIS | N4: INSIS | O4: LPV | P4: INSIS_PEOPLE_V10 | Q4: P_PEOPLE | R4: GNAME | S4: =CONCATENATE(M4,".",O4,".",P4,".",Q4,".",R4) -> INSIS.LPV.INSIS_PEOPLE_V10.P_PEOPLE.GNAME | T4: {=IFERROR(INDEX('3.Trazabilidad'!N:N, MATCH(S4, '3.Trazabilidad'!G:G, 0)), "-")} -> SÍ | U4: {=IFERROR(INDEX('3.Trazabilidad'!O:O, MATCH(S4, '3.Trazabilidad'!G:G, 0)), "-")} -> NO | V4: 1 | W4: {=IF(AND(COUNTIF('LAKEHOUSE (Tbl Campos)'!$F$2:$F$14000,$S$3:$S$910)>0),"X","-")} -> - | Y4: RESUMEN | Z4: INSIS | AA4: INSUNIX | AB4: VTIME | AC4: TOTAL
B5: INSIS | C5: LPV | D5: INSIS_PEOPLE_V10 | E5: HST_PEOPLE_MAN_COMP | F5: ="SELECT * FROM "&D5&"."&E5 -> SELECT * FROM INSIS_PEOPLE_V10.HST_PEOPLE_MAN_COMP | G5: CATÁLOGO | J5: =CONCATENATE(B5,".",C5,".",D5,".",E5) -> INSIS.LPV.INSIS_PEOPLE_V10.HST_PEOPLE_MAN_COMP | K5: {=IF(AND(COUNTIF(LAKEHOUSE!$E$2:$E$14000,$J$3:$J$310)>0),"X","-")} -> - | M5: INSIS | N5: INSIS | O5: LPV | P5: INSIS_PEOPLE_V10 | Q5: P_PEOPLE | R5: SNAME | S5: =CONCATENATE(M5,".",O5,".",P5,".",Q5,".",R5) -> INSIS.LPV.INSIS_PEOPLE_V10.P_PEOPLE.SNAME | T5: {=IFERROR(INDEX('3.Trazabilidad'!N:N, MATCH(S5, '3.Trazabilidad'!G:G, 0)), "-")} -> SÍ | U5: {=IFERROR(INDEX('3.Trazabilidad'!O:O, MATCH(S5, '3.Trazabilidad'!G:G, 0)), "-")} -> NO | V5: 1 | W5: {=IF(AND(COUNTIF('LAKEHOUSE (Tbl Campos)'!$F$2:$F$14000,$S$3:$S$910)>0),"X","-")} -> - | Y5: # Tablas del diccionario (Críticas) | Z5: =COUNTIFS($B$2:$B$973,"INSIS",$E$2:$E$973,"<>") -> 33 | AA5: =COUNTIFS($B$2:$B$973,"INSUNIX",$E$2:$E$973,"<>") -> 18 | AB5: =COUNTIFS($B$2:$B$973,"VTIME",$E$2:$E$973,"<>") -> 21 | AC5: =SUM(Z5:AB5) -> 72
B6: INSIS | C6: LPV | D6: INSIS_CUST | E6: CFGLPV_DOCUMENT_TYPE | F6: ="SELECT * FROM "&D6&"."&E6 -> SELECT * FROM INSIS_CUST.CFGLPV_DOCUMENT_TYPE | G6: CATÁLOGO | J6: =CONCATENATE(B6,".",C6,".",D6,".",E6) -> INSIS.LPV.INSIS_CUST.CFGLPV_DOCUMENT_TYPE | K6: {=IF(AND(COUNTIF(LAKEHOUSE!$E$2:$E$14000,$J$3:$J$310)>0),"X","-")} -> - | M6: INSIS | N6: INSIS | O6: LPV | P6: INSIS_PEOPLE_V10 | Q6: P_PEOPLE | R6: FNAME | S6: =CONCATENATE(M6,".",O6,".",P6,".",Q6,".",R6) -> INSIS.LPV.INSIS_PEOPLE_V10.P_PEOPLE.FNAME | T6: {=IFERROR(INDEX('3.Trazabilidad'!N:N, MATCH(S6, '3.Trazabilidad'!G:G, 0)), "-")} -> SÍ | U6: {=IFERROR(INDEX('3.Trazabilidad'!O:O, MATCH(S6, '3.Trazabilidad'!G:G, 0)), "-")} -> NO | V6: 1 | W6: {=IF(AND(COUNTIF('LAKEHOUSE (Tbl Campos)'!$F$2:$F$14000,$S$3:$S$910)>0),"X","-")} -> - | Y6: # Tablas del Diccionario ingestadas en Lakehouse | Z6: =COUNTIFS($B$2:$B$82,"INSIS",$K$2:$K$82,"X") -> 0 | AA6: =COUNTIFS($B$2:$B$82,"INSUNIX",$K$2:$K$82,"X") -> 0 | AB6: =COUNTIFS($B$2:$B$79,"VTIME",$K$2:$K$79,"X") -> 0 | AC6: =SUM(Z6:AB6) -> 0
B7: INSIS | C7: LPV | D7: INSIS_SYS_V10 | E7: DOC_DOCUMENTS | F7: ="SELECT * FROM "&D7&"."&E7 -> SELECT * FROM INSIS_SYS_V10.DOC_DOCUMENTS | G7: NO CATÁLOGO | J7: =CONCATENATE(B7,".",C7,".",D7,".",E7) -> INSIS.LPV.INSIS_SYS_V10.DOC_DOCUMENTS | K7: {=IF(AND(COUNTIF(LAKEHOUSE!$E$2:$E$14000,$J$3:$J$310)>0),"X","-")} -> - | M7: INSIS | N7: INSIS | O7: LPV | P7: INSIS_PEOPLE_V10 | Q7: P_PEOPLE | R7: NAME | S7: =CONCATENATE(M7,".",O7,".",P7,".",Q7,".",R7) -> INSIS.LPV.INSIS_PEOPLE_V10.P_PEOPLE.NAME | T7: {=IFERROR(INDEX('3.Trazabilidad'!N:N, MATCH(S7, '3.Trazabilidad'!G:G, 0)), "-")} -> SÍ | U7: {=IFERROR(INDEX('3.Trazabilidad'!O:O, MATCH(S7, '3.Trazabilidad'!G:G, 0)), "-")} -> NO | V7: 1 | W7: {=IF(AND(COUNTIF('LAKEHOUSE (Tbl Campos)'!$F$2:$F$14000,$S$3:$S$910)>0),"X","-")} -> - | Y7: # Tablas del Diccionario no ingestadas en Lakehouse | Z7: =COUNTIFS($B$2:$B$82,"INSIS",$K$2:$K$82,"-") -> 33 | AA7: =COUNTIFS($B$2:$B$82,"INSUNIX",$K$2:$K$82,"-") -> 18 | AB7: =COUNTIFS($B$2:$B$79,"VTIME",$K$2:$K$79,"-") -> 21 | AC7: =SUM(Z7:AB7) -> 72
B8: INSIS | C8: LPV | D8: INSIS_PEOPLE_V10 | E8: P_PEOPLE_GROUPS | F8: ="SELECT * FROM "&D8&"."&E8 -> SELECT * FROM INSIS_PEOPLE_V10.P_PEOPLE_GROUPS | G8: NO CATÁLOGO | J8: =CONCATENATE(B8,".",C8,".",D8,".",E8) -> INSIS.LPV.INSIS_PEOPLE_V10.P_PEOPLE_GROUPS | K8: {=IF(AND(COUNTIF(LAKEHOUSE!$E$2:$E$14000,$J$3:$J$310)>0),"X","-")} -> - | M8: INSIS | N8: INSIS | O8: LPV | P8: INSIS_PEOPLE_V10 | Q8: P_PEOPLE | R8: MAN_COMP | S8: =CONCATENATE(M8,".",O8,".",P8,".",Q8,".",R8) -> INSIS.LPV.INSIS_PEOPLE_V10.P_PEOPLE.MAN_COMP | T8: {=IFERROR(INDEX('3.Trazabilidad'!N:N, MATCH(S8, '3.Trazabilidad'!G:G, 0)), "-")} -> NO | U8: {=IFERROR(INDEX('3.Trazabilidad'!O:O, MATCH(S8, '3.Trazabilidad'!G:G, 0)), "-")} -> NO | V8: 1 | W8: {=IF(AND(COUNTIF('LAKEHOUSE (Tbl Campos)'!$F$2:$F$14000,$S$3:$S$910)>0),"X","-")} -> - | Y8: # Tablas mapeadas en Lakehouse | Z8: 17 | AC8: =SUM(Z8:AB8) -> 17
B9: INSIS | C9: LPV | D9: INSIS_PEOPLE_V10 | E9: HT_PEOPLE_GROUPS | F9: ="SELECT * FROM "&D9&"."&E9 -> SELECT * FROM INSIS_PEOPLE_V10.HT_PEOPLE_GROUPS | G9: CATÁLOGO | J9: =CONCATENATE(B9,".",C9,".",D9,".",E9) -> INSIS.LPV.INSIS_PEOPLE_V10.HT_PEOPLE_GROUPS | K9: {=IF(AND(COUNTIF(LAKEHOUSE!$E$2:$E$14000,$J$3:$J$310)>0),"X","-")} -> - | M9: INSIS | N9: INSIS | O9: LPV | P9: INSIS_PEOPLE_V10 | Q9: HST_PEOPLE_MAN_COMP | R9: NAME | S9: =CONCATENATE(M9,".",O9,".",P9,".",Q9,".",R9) -> INSIS.LPV.INSIS_PEOPLE_V10.HST_PEOPLE_MAN_COMP.NAME | T9: {=IFERROR(INDEX('3.Trazabilidad'!N:N, MATCH(S9, '3.Trazabilidad'!G:G, 0)), "-")} -> NO | U9: {=IFERROR(INDEX('3.Trazabilidad'!O:O, MATCH(S9, '3.Trazabilidad'!G:G, 0)), "-")} -> NO | V9: 1 | W9: {=IF(AND(COUNTIF('LAKEHOUSE (Tbl Campos)'!$F$2:$F$14000,$S$3:$S$910)>0),"X","-")} -> -
B10: INSIS | C10: LPV | D10: INSIS_PEOPLE_V10 | E10: HST_PEOPLE_SEX | F10: ="SELECT * FROM "&D10&"."&E10 -> SELECT * FROM INSIS_PEOPLE_V10.HST_PEOPLE_SEX | G10: CATÁLOGO | J10: =CONCATENATE(B10,".",C10,".",D10,".",E10) -> INSIS.LPV.INSIS_PEOPLE_V10.HST_PEOPLE_SEX | K10: {=IF(AND(COUNTIF(LAKEHOUSE!$E$2:$E$14000,$J$3:$J$310)>0),"X","-")} -> - | M10: INSIS | N10: INSIS | O10: LPV | P10: INSIS_PEOPLE_V10 | Q10: P_PEOPLE | R10: ATTR1 | S10: =CONCATENATE(M10,".",O10,".",P10,".",Q10,".",R10) -> INSIS.LPV.INSIS_PEOPLE_V10.P_PEOPLE.ATTR1 | T10: {=IFERROR(INDEX('3.Trazabilidad'!N:N, MATCH(S10, '3.Trazabilidad'!G:G, 0)), "-")} -> NO | U10: {=IFERROR(INDEX('3.Trazabilidad'!O:O, MATCH(S10, '3.Trazabilidad'!G:G, 0)), "-")} -> NO | V10: 1 | W10: {=IF(AND(COUNTIF('LAKEHOUSE (Tbl Campos)'!$F$2:$F$14000,$S$3:$S$910)>0),"X","-")} -> -
B11: INSIS | C11: LPV | D11: INSIS_PEOPLE_V10 | E11: HT_PEOPLE_COMPANY_TYPES | F11: ="SELECT * FROM "&D11&"."&E11 -> SELECT * FROM INSIS_PEOPLE_V10.HT_PEOPLE_COMPANY_TYPES | G11: CATÁLOGO | J11: =CONCATENATE(B11,".",C11,".",D11,".",E11) -> INSIS.LPV.INSIS_PEOPLE_V10.HT_PEOPLE_COMPANY_TYPES | K11: {=IF(AND(COUNTIF(LAKEHOUSE!$E$2:$E$14000,$J$3:$J$310)>0),"X","-")} -> - | M11: INSIS | N11: INSIS | O11: LPV | P11: INSIS_CUST | Q11: CFGLPV_DOCUMENT_TYPE | R11: NAME | S11: =CONCATENATE(M11,".",O11,".",P11,".",Q11,".",R11) -> INSIS.LPV.INSIS_CUST.CFGLPV_DOCUMENT_TYPE.NAME | T11: {=IFERROR(INDEX('3.Trazabilidad'!N:N, MATCH(S11, '3.Trazabilidad'!G:G, 0)), "-")} -> NO | U11: {=IFERROR(INDEX('3.Trazabilidad'!O:O, MATCH(S11, '3.Trazabilidad'!G:G, 0)), "-")} -> NO | V11: 1 | W11: {=IF(AND(COUNTIF('LAKEHOUSE (Tbl Campos)'!$F$2:$F$14000,$S$3:$S$910)>0),"X","-")} -> -
B12: INSIS | C12: LPV | D12: INSIS_PEOPLE_V10 | E12: HT_PEOPLE_OCCUP_CODE | F12: ="SELECT * FROM "&D12&"."&E12 -> SELECT * FROM INSIS_PEOPLE_V10.HT_PEOPLE_OCCUP_CODE | G12: CATÁLOGO | J12: =CONCATENATE(B12,".",C12,".",D12,".",E12) -> INSIS.LPV.INSIS_PEOPLE_V10.HT_PEOPLE_OCCUP_CODE | K12: {=IF(AND(COUNTIF(LAKEHOUSE!$E$2:$E$14000,$J$3:$J$310)>0),"X","-")} -> - | M12: INSIS | N12: INSIS | O12: LPV | P12: INSIS_PEOPLE_V10 | Q12: P_PEOPLE | R12: EGN | S12: =CONCATENATE(M12,".",O12,".",P12,".",Q12,".",R12) -> INSIS.LPV.INSIS_PEOPLE_V10.P_PEOPLE.EGN | T12: {=IFERROR(INDEX('3.Trazabilidad'!N:N, MATCH(S12, '3.Trazabilidad'!G:G, 0)), "-")} -> SÍ | U12: {=IFERROR(INDEX('3.Trazabilidad'!O:O, MATCH(S12, '3.Trazabilidad'!G:G, 0)), "-")} -> NO | V12: 1 | W12: {=IF(AND(COUNTIF('LAKEHOUSE (Tbl Campos)'!$F$2:$F$14000,$S$3:$S$910)>0),"X","-")} -> -
B13: INSIS | C13: LPV | D13: INSIS_PEOPLE_V10 | E13: HT_CUSTOMER_CORP_STAT | F13: ="SELECT * FROM "&D13&"."&E13 -> SELECT * FROM INSIS_PEOPLE_V10.HT_CUSTOMER_CORP_STAT | G13: CATÁLOGO | J13: =CONCATENATE(B13,".",C13,".",D13,".",E13) -> INSIS.LPV.INSIS_PEOPLE_V10.HT_CUSTOMER_CORP_STAT | K13: {=IF(AND(COUNTIF(LAKEHOUSE!$E$2:$E$14000,$J$3:$J$310)>0),"X","-")} -> - | M13: INSIS | N13: INSIS | O13: LPV | P13: INSIS_SYS_V10 | Q13: DOC_DOCUMENTS | R13: DOC_NUM | S13: =CONCATENATE(M13,".",O13,".",P13,".",Q13,".",R13) -> INSIS.LPV.INSIS_SYS_V10.DOC_DOCUMENTS.DOC_NUM | T13: {=IFERROR(INDEX('3.Trazabilidad'!N:N, MATCH(S13, '3.Trazabilidad'!G:G, 0)), "-")} -> SÍ | U13: {=IFERROR(INDEX('3.Trazabilidad'!O:O, MATCH(S13, '3.Trazabilidad'!G:G, 0)), "-")} -> NO | V13: 1 | W13: {=IF(AND(COUNTIF('LAKEHOUSE (Tbl Campos)'!$F$2:$F$14000,$S$3:$S$910)>0),"X","-")} -> -
B14: INSIS | C14: LPV | D14: INSIS_PEOPLE_V10 | E14: HT_CUSTOMER_INTERNAL_STATUS | F14: ="SELECT * FROM "&D14&"."&E14 -> SELECT * FROM INSIS_PEOPLE_V10.HT_CUSTOMER_INTERNAL_STATUS | G14: CATÁLOGO | J14: =CONCATENATE(B14,".",C14,".",D14,".",E14) -> INSIS.LPV.INSIS_PEOPLE_V10.HT_CUSTOMER_INTERNAL_STATUS | K14: {=IF(AND(COUNTIF(LAKEHOUSE!$E$2:$E$14000,$J$3:$J$310)>0),"X","-")} -> - | M14: INSIS | N14: INSIS | O14: LPV | P14: INSIS_PEOPLE_V10 | Q14: P_PEOPLE_GROUPS | R14: GROUP_CODE | S14: =CONCATENATE(M14,".",O14,".",P14,".",Q14,".",R14) -> INSIS.LPV.INSIS_PEOPLE_V10.P_PEOPLE_GROUPS.GROUP_CODE | T14: {=IFERROR(INDEX('3.Trazabilidad'!N:N, MATCH(S14, '3.Trazabilidad'!G:G, 0)), "-")} -> NO | U14: {=IFERROR(INDEX('3.Trazabilidad'!O:O, MATCH(S14, '3.Trazabilidad'!G:G, 0)), "-")} -> NO | V14: 1 | W14: {=IF(AND(COUNTIF('LAKEHOUSE (Tbl Campos)'!$F$2:$F$14000,$S$3:$S$910)>0),"X","-")} -> - | Y14: Leyenda
B15: INSIS | C15: LPV | D15: INSIS_PEOPLE_V10 | E15: P_CONTACTS | F15: ="SELECT * FROM "&D15&"."&E15 -> SELECT * FROM INSIS_PEOPLE_V10.P_CONTACTS | G15: NO CATÁLOGO | J15: =CONCATENATE(B15,".",C15,".",D15,".",E15) -> INSIS.LPV.INSIS_PEOPLE_V10.P_CONTACTS | K15: {=IF(AND(COUNTIF(LAKEHOUSE!$E$2:$E$14000,$J$3:$J$310)>0),"X","-")} -> - | M15: INSIS | N15: INSIS | O15: LPV | P15: INSIS_PEOPLE_V10 | Q15: HT_PEOPLE_GROUPS | R15: NAME | S15: =CONCATENATE(M15,".",O15,".",P15,".",Q15,".",R15) -> INSIS.LPV.INSIS_PEOPLE_V10.HT_PEOPLE_GROUPS.NAME | T15: {=IFERROR(INDEX('3.Trazabilidad'!N:N, MATCH(S15, '3.Trazabilidad'!G:G, 0)), "-")} -> SÍ | U15: {=IFERROR(INDEX('3.Trazabilidad'!O:O, MATCH(S15, '3.Trazabilidad'!G:G, 0)), "-")} -> NO | V15: 1 | W15: {=IF(AND(COUNTIF('LAKEHOUSE (Tbl Campos)'!$F$2:$F$14000,$S$3:$S$910)>0),"X","-")} -> - | Y15: X: Tablas encontradas
B16: INSIS | C16: LPV | D16: INSIS_PEOPLE_V10 | E16: P_ADDRESS | F16: ="SELECT * FROM "&D16&"."&E16 -> SELECT * FROM INSIS_PEOPLE_V10.P_ADDRESS | G16: NO CATÁLOGO | J16: =CONCATENATE(B16,".",C16,".",D16,".",E16) -> INSIS.LPV.INSIS_PEOPLE_V10.P_ADDRESS | K16: {=IF(AND(COUNTIF(LAKEHOUSE!$E$2:$E$14000,$J$3:$J$310)>0),"X","-")} -> - | M16: INSIS | N16: INSIS | O16: LPV | P16: INSIS_PEOPLE_V10 | Q16: P_PEOPLE | R16: SEX | S16: =CONCATENATE(M16,".",O16,".",P16,".",Q16,".",R16) -> INSIS.LPV.INSIS_PEOPLE_V10.P_PEOPLE.SEX | T16: {=IFERROR(INDEX('3.Trazabilidad'!N:N, MATCH(S16, '3.Trazabilidad'!G:G, 0)), "-")} -> NO | U16: {=IFERROR(INDEX('3.Trazabilidad'!O:O, MATCH(S16, '3.Trazabilidad'!G:G, 0)), "-")} -> NO | V16: 1 | W16: {=IF(AND(COUNTIF('LAKEHOUSE (Tbl Campos)'!$F$2:$F$14000,$S$3:$S$910)>0),"X","-")} -> - | Y16: -: Tablas no encontradas
B17: INSIS | C17: LPV | D17: INSIS_PEOPLE_V10 | E17: HT_ADDRESS_TYPE | F17: ="SELECT * FROM "&D17&"."&E17 -> SELECT * FROM INSIS_PEOPLE_V10.HT_ADDRESS_TYPE | G17: CATÁLOGO | J17: =CONCATENATE(B17,".",C17,".",D17,".",E17) -> INSIS.LPV.INSIS_PEOPLE_V10.HT_ADDRESS_TYPE | K17: {=IF(AND(COUNTIF(LAKEHOUSE!$E$2:$E$14000,$J$3:$J$310)>0),"X","-")} -> - | M17: INSIS | N17: INSIS | O17: LPV | P17: INSIS_PEOPLE_V10 | Q17: HST_PEOPLE_SEX | R17: NAME | S17: =CONCATENATE(M17,".",O17,".",P17,".",Q17,".",R17) -> INSIS.LPV.INSIS_PEOPLE_V10.HST_PEOPLE_SEX.NAME | T17: {=IFERROR(INDEX('3.Trazabilidad'!N:N, MATCH(S17, '3.Trazabilidad'!G:G, 0)), "-")} -> SÍ | U17: {=IFERROR(INDEX('3.Trazabilidad'!O:O, MATCH(S17, '3.Trazabilidad'!G:G, 0)), "-")} -> NO | V17: 1 | W17: {=IF(AND(COUNTIF('LAKEHOUSE (Tbl Campos)'!$F$2:$F$14000,$S$3:$S$910)>0),"X","-")} -> -
B18: INSIS | C18: LPV | D18: INSIS_PEOPLE_V10 | E18: P_AGENTS | F18: ="SELECT * FROM "&D18&"."&E18 -> SELECT * FROM INSIS_PEOPLE_V10.P_AGENTS | G18: NO CATÁLOGO | J18: =CONCATENATE(B18,".",C18,".",D18,".",E18) -> INSIS.LPV.INSIS_PEOPLE_V10.P_AGENTS | K18: {=IF(AND(COUNTIF(LAKEHOUSE!$E$2:$E$14000,$J$3:$J$310)>0),"X","-")} -> - | M18: INSIS | N18: INSIS | O18: LPV | P18: INSIS_PEOPLE_V10 | Q18: P_PEOPLE | R18: BIRTH_DATE | S18: =CONCATENATE(M18,".",O18,".",P18,".",Q18,".",R18) -> INSIS.LPV.INSIS_PEOPLE_V10.P_PEOPLE.BIRTH_DATE | T18: {=IFERROR(INDEX('3.Trazabilidad'!N:N, MATCH(S18, '3.Trazabilidad'!G:G, 0)), "-")} -> SÍ | U18: {=IFERROR(INDEX('3.Trazabilidad'!O:O, MATCH(S18, '3.Trazabilidad'!G:G, 0)), "-")} -> NO | V18: 1 | W18: {=IF(AND(COUNTIF('LAKEHOUSE (Tbl Campos)'!$F$2:$F$14000,$S$3:$S$910)>0),"X","-")} -> -
B19: INSIS | C19: LPV | D19: INSIS_PEOPLE_V10 | E19: HT_AGENT_TYPE | F19: ="SELECT * FROM "&D19&"."&E19 -> SELECT * FROM INSIS_PEOPLE_V10.HT_AGENT_TYPE | G19: CATÁLOGO | J19: =CONCATENATE(B19,".",C19,".",D19,".",E19) -> INSIS.LPV.INSIS_PEOPLE_V10.HT_AGENT_TYPE | K19: {=IF(AND(COUNTIF(LAKEHOUSE!$E$2:$E$14000,$J$3:$J$310)>0),"X","-")} -> - | M19: INSIS | N19: INSIS | O19: LPV | P19: INSIS_PEOPLE_V10 | Q19: P_PEOPLE | R19: COMP_TYPE | S19: =CONCATENATE(M19,".",O19,".",P19,".",Q19,".",R19) -> INSIS.LPV.INSIS_PEOPLE_V10.P_PEOPLE.COMP_TYPE | T19: {=IFERROR(INDEX('3.Trazabilidad'!N:N, MATCH(S19, '3.Trazabilidad'!G:G, 0)), "-")} -> NO | U19: {=IFERROR(INDEX('3.Trazabilidad'!O:O, MATCH(S19, '3.Trazabilidad'!G:G, 0)), "-")} -> NO | V19: 1 | W19: {=IF(AND(COUNTIF('LAKEHOUSE (Tbl Campos)'!$F$2:$F$14000,$S$3:$S$910)>0),"X","-")} -> -
B20: INSIS | C20: LPV | D20: INSIS_PEOPLE_V10 | E20: P_PEOPLE_RELATION | F20: ="SELECT * FROM "&D20&"."&E20 -> SELECT * FROM INSIS_PEOPLE_V10.P_PEOPLE_RELATION | G20: NO CATÁLOGO | J20: =CONCATENATE(B20,".",C20,".",D20,".",E20) -> INSIS.LPV.INSIS_PEOPLE_V10.P_PEOPLE_RELATION | K20: {=IF(AND(COUNTIF(LAKEHOUSE!$E$2:$E$14000,$J$3:$J$310)>0),"X","-")} -> - | M20: INSIS | N20: INSIS | O20: LPV | P20: INSIS_PEOPLE_V10 | Q20: HT_PEOPLE_COMPANY_TYPES | R20: NAME | S20: =CONCATENATE(M20,".",O20,".",P20,".",Q20,".",R20) -> INSIS.LPV.INSIS_PEOPLE_V10.HT_PEOPLE_COMPANY_TYPES.NAME | T20: {=IFERROR(INDEX('3.Trazabilidad'!N:N, MATCH(S20, '3.Trazabilidad'!G:G, 0)), "-")} -> NO | U20: {=IFERROR(INDEX('3.Trazabilidad'!O:O, MATCH(S20, '3.Trazabilidad'!G:G, 0)), "-")} -> NO | V20: 1 | W20: {=IF(AND(COUNTIF('LAKEHOUSE (Tbl Campos)'!$F$2:$F$14000,$S$3:$S$910)>0),"X","-")} -> - | Y20: Resumen de Campos | Z20: INSIS | AA20: INSUNIX | AB20: VTIME | AC20: TOTAL
B21: INSIS | C21: LPV | D21: INSIS_GEN_V10 | E21: POLICY_PARTICIPANTS | F21: ="SELECT * FROM "&D21&"."&E21 -> SELECT * FROM INSIS_GEN_V10.POLICY_PARTICIPANTS | G21: NO CATÁLOGO | J21: =CONCATENATE(B21,".",C21,".",D21,".",E21) -> INSIS.LPV.INSIS_GEN_V10.POLICY_PARTICIPANTS | K21: {=IF(AND(COUNTIF(LAKEHOUSE!$E$2:$E$14000,$J$3:$J$310)>0),"X","-")} -> - | M21: INSIS | N21: INSIS | O21: LPV | P21: INSIS_PEOPLE_V10 | Q21: P_PEOPLE | R21: INDUSTRY_CODE | S21: =CONCATENATE(M21,".",O21,".",P21,".",Q21,".",R21) -> INSIS.LPV.INSIS_PEOPLE_V10.P_PEOPLE.INDUSTRY_CODE | T21: {=IFERROR(INDEX('3.Trazabilidad'!N:N, MATCH(S21, '3.Trazabilidad'!G:G, 0)), "-")} -> NO | U21: {=IFERROR(INDEX('3.Trazabilidad'!O:O, MATCH(S21, '3.Trazabilidad'!G:G, 0)), "-")} -> NO | V21: 1 | W21: {=IF(AND(COUNTIF('LAKEHOUSE (Tbl Campos)'!$F$2:$F$14000,$S$3:$S$910)>0),"X","-")} -> - | Y21: # Campos del diccionario (Críticas) | Z21: =COUNTIFS($M$3:$M$904,"INSIS",$R$3:$R$904,"<>") -> 59 | AA21: =COUNTIFS($M$2:$M$126,"INSUNIX",$R$2:$R$126,"<>") -> 33 | AB21: =COUNTIFS($M$2:$M$126,"VTIME",$R$2:$R$126,"<>") -> 32 | AC21: =SUM(Z21:AB21) -> 124
B22: INSIS | C22: LPV | D22: INSIS_SYS_V10 | E22: CFG_NOM_LANGUAGE_TABLE | F22: ="SELECT * FROM "&D22&"."&E22 -> SELECT * FROM INSIS_SYS_V10.CFG_NOM_LANGUAGE_TABLE | G22: CATÁLOGO | J22: =CONCATENATE(B22,".",C22,".",D22,".",E22) -> INSIS.LPV.INSIS_SYS_V10.CFG_NOM_LANGUAGE_TABLE | K22: {=IF(AND(COUNTIF(LAKEHOUSE!$E$2:$E$14000,$J$3:$J$310)>0),"X","-")} -> - | M22: INSIS | N22: INSIS | O22: LPV | P22: INSIS_PEOPLE_V10 | Q22: HT_PEOPLE_OCCUP_CODE | R22: NAME | S22: =CONCATENATE(M22,".",O22,".",P22,".",Q22,".",R22) -> INSIS.LPV.INSIS_PEOPLE_V10.HT_PEOPLE_OCCUP_CODE.NAME | T22: {=IFERROR(INDEX('3.Trazabilidad'!N:N, MATCH(S22, '3.Trazabilidad'!G:G, 0)), "-")} -> SÍ | U22: {=IFERROR(INDEX('3.Trazabilidad'!O:O, MATCH(S22, '3.Trazabilidad'!G:G, 0)), "-")} -> NO | V22: 1 | W22: {=IF(AND(COUNTIF('LAKEHOUSE (Tbl Campos)'!$F$2:$F$14000,$S$3:$S$910)>0),"X","-")} -> - | Y22: # Campos del Diccionario ingestadas en Lakehouse | Z22: =COUNTIFS($M$2:$M$126,"INSIS",$W$2:$W$126,"X") -> 0 | AA22: =COUNTIFS($M$2:$M$126,"INSUNIX",$W$2:$W$126,"X") -> 0 | AB22: =COUNTIFS($M$2:$M$126,"VTIME",$W$2:$W$126,"X") -> 0 | AC22: =SUM(Z22:AB22) -> 0
B23: INSIS | C23: LPV | D23: INSIS_GEN_V10 | E23: O_ACCINSURED | F23: ="SELECT * FROM "&D23&"."&E23 -> SELECT * FROM INSIS_GEN_V10.O_ACCINSURED | G23: NO CATÁLOGO | J23: =CONCATENATE(B23,".",C23,".",D23,".",E23) -> INSIS.LPV.INSIS_GEN_V10.O_ACCINSURED | K23: {=IF(AND(COUNTIF(LAKEHOUSE!$E$2:$E$14000,$J$3:$J$310)>0),"X","-")} -> - | M23: INSIS | N23: INSIS | O23: LPV | P23: INSIS_PEOPLE_V10 | Q23: P_CLIENTS | R23: CORPORATE_IC_STATUS | S23: =CONCATENATE(M23,".",O23,".",P23,".",Q23,".",R23) -> INSIS.LPV.INSIS_PEOPLE_V10.P_CLIENTS.CORPORATE_IC_STATUS | T23: {=IFERROR(INDEX('3.Trazabilidad'!N:N, MATCH(S23, '3.Trazabilidad'!G:G, 0)), "-")} -> NO | U23: {=IFERROR(INDEX('3.Trazabilidad'!O:O, MATCH(S23, '3.Trazabilidad'!G:G, 0)), "-")} -> NO | V23: 1 | W23: {=IF(AND(COUNTIF('LAKEHOUSE (Tbl Campos)'!$F$2:$F$14000,$S$3:$S$910)>0),"X","-")} -> - | Y23: # Campos del Diccionario no ingestadas en Lakehouse | Z23: =COUNTIFS($M$2:$M$126,"INSIS",$W$2:$W$126,"-") -> 59 | AA23: =COUNTIFS($M$2:$M$126,"INSUNIX",$W$2:$W$126,"-") -> 33 | AB23: =COUNTIFS($M$2:$M$126,"VTIME",$W$2:$W$126,"-") -> 32 | AC23: =SUM(Z23:AB23) -> 124
B24: INSIS | C24: LPV | D24: INSIS_PEOPLE_V10 | E24: HT_PEOPLE_RELATION | F24: ="SELECT * FROM "&D24&"."&E24 -> SELECT * FROM INSIS_PEOPLE_V10.HT_PEOPLE_RELATION | G24: CATÁLOGO | J24: =CONCATENATE(B24,".",C24,".",D24,".",E24) -> INSIS.LPV.INSIS_PEOPLE_V10.HT_PEOPLE_RELATION | K24: {=IF(AND(COUNTIF(LAKEHOUSE!$E$2:$E$14000,$J$3:$J$310)>0),"X","-")} -> - | M24: INSIS | N24: INSIS | O24: LPV | P24: INSIS_PEOPLE_V10 | Q24: HT_CUSTOMER_CORP_STAT | R24: NAME | S24: =CONCATENATE(M24,".",O24,".",P24,".",Q24,".",R24) -> INSIS.LPV.INSIS_PEOPLE_V10.HT_CUSTOMER_CORP_STAT.NAME | T24: {=IFERROR(INDEX('3.Trazabilidad'!N:N, MATCH(S24, '3.Trazabilidad'!G:G, 0)), "-")} -> NO | U24: {=IFERROR(INDEX('3.Trazabilidad'!O:O, MATCH(S24, '3.Trazabilidad'!G:G, 0)), "-")} -> NO | V24: 1 | W24: {=IF(AND(COUNTIF('LAKEHOUSE (Tbl Campos)'!$F$2:$F$14000,$S$3:$S$910)>0),"X","-")} -> -
B25: INSIS | C25: LPV | D25: INSIS_GEN_V10 | E25: CLAIM | F25: ="SELECT * FROM "&D25&"."&E25 -> SELECT * FROM INSIS_GEN_V10.CLAIM | G25: NO CATÁLOGO | J25: =CONCATENATE(B25,".",C25,".",D25,".",E25) -> INSIS.LPV.INSIS_GEN_V10.CLAIM | K25: {=IF(AND(COUNTIF(LAKEHOUSE!$E$2:$E$14000,$J$3:$J$310)>0),"X","-")} -> - | M25: INSIS | N25: INSIS | O25: LPV | P25: INSIS_PEOPLE_V10 | Q25: P_CLIENTS | R25: IC_STATUS | S25: =CONCATENATE(M25,".",O25,".",P25,".",Q25,".",R25) -> INSIS.LPV.INSIS_PEOPLE_V10.P_CLIENTS.IC_STATUS | T25: {=IFERROR(INDEX('3.Trazabilidad'!N:N, MATCH(S25, '3.Trazabilidad'!G:G, 0)), "-")} -> NO | U25: {=IFERROR(INDEX('3.Trazabilidad'!O:O, MATCH(S25, '3.Trazabilidad'!G:G, 0)), "-")} -> NO | V25: 1 | W25: {=IF(AND(COUNTIF('LAKEHOUSE (Tbl Campos)'!$F$2:$F$14000,$S$3:$S$910)>0),"X","-")} -> -
B26: INSIS | C26: LPV | D26: INSIS_GEN_V10 | E26: CLAIM_OBJECTS | F26: ="SELECT * FROM "&D26&"."&E26 -> SELECT * FROM INSIS_GEN_V10.CLAIM_OBJECTS | G26: NO CATÁLOGO | J26: =CONCATENATE(B26,".",C26,".",D26,".",E26) -> INSIS.LPV.INSIS_GEN_V10.CLAIM_OBJECTS | K26: {=IF(AND(COUNTIF(LAKEHOUSE!$E$2:$E$14000,$J$3:$J$310)>0),"X","-")} -> - | M26: INSIS | N26: INSIS | O26: LPV | P26: INSIS_PEOPLE_V10 | Q26: HT_CUSTOMER_INTERNAL_STATUS | R26: NAME | S26: =CONCATENATE(M26,".",O26,".",P26,".",Q26,".",R26) -> INSIS.LPV.INSIS_PEOPLE_V10.HT_CUSTOMER_INTERNAL_STATUS.NAME | T26: {=IFERROR(INDEX('3.Trazabilidad'!N:N, MATCH(S26, '3.Trazabilidad'!G:G, 0)), "-")} -> NO | U26: {=IFERROR(INDEX('3.Trazabilidad'!O:O, MATCH(S26, '3.Trazabilidad'!G:G, 0)), "-")} -> NO | V26: 3 | W26: {=IF(AND(COUNTIF('LAKEHOUSE (Tbl Campos)'!$F$2:$F$14000,$S$3:$S$910)>0),"X","-")} -> -
B27: INSIS | C27: LPV | D27: INSIS_SYS_V10 | E27: HT_COUNTRIES | F27: ="SELECT * FROM "&D27&"."&E27 -> SELECT * FROM INSIS_SYS_V10.HT_COUNTRIES | G27: CATÁLOGO | J27: =CONCATENATE(B27,".",C27,".",D27,".",E27) -> INSIS.LPV.INSIS_SYS_V10.HT_COUNTRIES | K27: {=IF(AND(COUNTIF(LAKEHOUSE!$E$2:$E$14000,$J$3:$J$310)>0),"X","-")} -> - | M27: INSIS | N27: INSIS | O27: LPV | P27: INSIS_PEOPLE_V10 | Q27: P_CONTACTS | R27: PRIMARY_FLAG | S27: =CONCATENATE(M27,".",O27,".",P27,".",Q27,".",R27) -> INSIS.LPV.INSIS_PEOPLE_V10.P_CONTACTS.PRIMARY_FLAG | T27: {=IFERROR(INDEX('3.Trazabilidad'!N:N, MATCH(S27, '3.Trazabilidad'!G:G, 0)), "-")} -> NO | U27: {=IFERROR(INDEX('3.Trazabilidad'!O:O, MATCH(S27, '3.Trazabilidad'!G:G, 0)), "-")} -> NO | W27: {=IF(AND(COUNTIF('LAKEHOUSE (Tbl Campos)'!$F$2:$F$14000,$S$3:$S$910)>0),"X","-")} -> -
B28: INSIS | C28: LPV | D28: INSIS_SYS_V10 | E28: HT_COUNTRY_STATE | F28: ="SELECT * FROM "&D28&"."&E28 -> SELECT * FROM INSIS_SYS_V10.HT_COUNTRY_STATE | G28: CATÁLOGO | J28: =CONCATENATE(B28,".",C28,".",D28,".",E28) -> INSIS.LPV.INSIS_SYS_V10.HT_COUNTRY_STATE | K28: {=IF(AND(COUNTIF(LAKEHOUSE!$E$2:$E$14000,$J$3:$J$310)>0),"X","-")} -> - | M28: INSIS | N28: INSIS | O28: LPV | P28: INSIS_PEOPLE_V10 | Q28: P_CONTACTS | R28: DETAILS | S28: =CONCATENATE(M28,".",O28,".",P28,".",Q28,".",R28) -> INSIS.LPV.INSIS_PEOPLE_V10.P_CONTACTS.DETAILS | T28: {=IFERROR(INDEX('3.Trazabilidad'!N:N, MATCH(S28, '3.Trazabilidad'!G:G, 0)), "-")} -> SÍ | U28: {=IFERROR(INDEX('3.Trazabilidad'!O:O, MATCH(S28, '3.Trazabilidad'!G:G, 0)), "-")} -> NO | W28: {=IF(AND(COUNTIF('LAKEHOUSE (Tbl Campos)'!$F$2:$F$14000,$S$3:$S$910)>0),"X","-")} -> -
B29: INSIS | C29: LPV | D29: INSIS_SYS_V10 | E29: HT_STATE_REGION | F29: ="SELECT * FROM "&D29&"."&E29 -> SELECT * FROM INSIS_SYS_V10.HT_STATE_REGION | G29: CATÁLOGO | J29: =CONCATENATE(B29,".",C29,".",D29,".",E29) -> INSIS.LPV.INSIS_SYS_V10.HT_STATE_REGION | K29: {=IF(AND(COUNTIF(LAKEHOUSE!$E$2:$E$14000,$J$3:$J$310)>0),"X","-")} -> - | M29: INSIS | N29: INSIS | O29: LPV | P29: INSIS_PEOPLE_V10 | Q29: P_ADDRESS | R29: PRIMARY_FLAG | S29: =CONCATENATE(M29,".",O29,".",P29,".",Q29,".",R29) -> INSIS.LPV.INSIS_PEOPLE_V10.P_ADDRESS.PRIMARY_FLAG | T29: {=IFERROR(INDEX('3.Trazabilidad'!N:N, MATCH(S29, '3.Trazabilidad'!G:G, 0)), "-")} -> NO | U29: {=IFERROR(INDEX('3.Trazabilidad'!O:O, MATCH(S29, '3.Trazabilidad'!G:G, 0)), "-")} -> NO | W29: {=IF(AND(COUNTIF('LAKEHOUSE (Tbl Campos)'!$F$2:$F$14000,$S$3:$S$910)>0),"X","-")} -> -
B30: INSIS | C30: LPV | D30: INSIS_SYS_V10 | E30: HT_REGION_CITY | F30: ="SELECT * FROM "&D30&"."&E30 -> SELECT * FROM INSIS_SYS_V10.HT_REGION_CITY | G30: CATÁLOGO | J30: =CONCATENATE(B30,".",C30,".",D30,".",E30) -> INSIS.LPV.INSIS_SYS_V10.HT_REGION_CITY | K30: {=IF(AND(COUNTIF(LAKEHOUSE!$E$2:$E$14000,$J$3:$J$310)>0),"X","-")} -> - | M30: INSIS | N30: INSIS | O30: LPV | P30: INSIS_PEOPLE_V10 | Q30: P_ADDRESS | R30: ADDRESS | S30: =CONCATENATE(M30,".",O30,".",P30,".",Q30,".",R30) -> INSIS.LPV.INSIS_PEOPLE_V10.P_ADDRESS.ADDRESS | T30: {=IFERROR(INDEX('3.Trazabilidad'!N:N, MATCH(S30, '3.Trazabilidad'!G:G, 0)), "-")} -> SÍ | U30: {=IFERROR(INDEX('3.Trazabilidad'!O:O, MATCH(S30, '3.Trazabilidad'!G:G, 0)), "-")} -> NO | W30: {=IF(AND(COUNTIF('LAKEHOUSE (Tbl Campos)'!$F$2:$F$14000,$S$3:$S$910)>0),"X","-")} -> -
B31: INSIS | C31: LPV | D31: INSIS_CUST | E31: CFGLPV_MARITAL_STATUS | F31: ="SELECT * FROM "&D31&"."&E31 -> SELECT * FROM INSIS_CUST.CFGLPV_MARITAL_STATUS | G31: CATÁLOGO | J31: =CONCATENATE(B31,".",C31,".",D31,".",E31) -> INSIS.LPV.INSIS_CUST.CFGLPV_MARITAL_STATUS | K31: {=IF(AND(COUNTIF(LAKEHOUSE!$E$2:$E$14000,$J$3:$J$310)>0),"X","-")} -> - | M31: INSIS | N31: INSIS | O31: LPV | P31: INSIS_PEOPLE_V10 | Q31: P_ADDRESS | R31: ADDRESS_TYPE | S31: =CONCATENATE(M31,".",O31,".",P31,".",Q31,".",R31) -> INSIS.LPV.INSIS_PEOPLE_V10.P_ADDRESS.ADDRESS_TYPE | T31: {=IFERROR(INDEX('3.Trazabilidad'!N:N, MATCH(S31, '3.Trazabilidad'!G:G, 0)), "-")} -> NO | U31: {=IFERROR(INDEX('3.Trazabilidad'!O:O, MATCH(S31, '3.Trazabilidad'!G:G, 0)), "-")} -> NO | W31: {=IF(AND(COUNTIF('LAKEHOUSE (Tbl Campos)'!$F$2:$F$14000,$S$3:$S$910)>0),"X","-")} -> -
B32: INSIS | C32: LPV | D32: INSIS_NTW_V10 | E32: P_PROVIDERS | F32: ="SELECT * FROM "&D32&"."&E32 -> SELECT * FROM INSIS_NTW_V10.P_PROVIDERS | G32: NO CATÁLOGO | J32: =CONCATENATE(B32,".",C32,".",D32,".",E32) -> INSIS.LPV.INSIS_NTW_V10.P_PROVIDERS | K32: {=IF(AND(COUNTIF(LAKEHOUSE!$E$2:$E$14000,$J$3:$J$310)>0),"X","-")} -> - | M32: INSIS | N32: INSIS | O32: LPV | P32: INSIS_PEOPLE_V10 | Q32: HT_ADDRESS_TYPE | R32: NAME | S32: =CONCATENATE(M32,".",O32,".",P32,".",Q32,".",R32) -> INSIS.LPV.INSIS_PEOPLE_V10.HT_ADDRESS_TYPE.NAME | T32: {=IFERROR(INDEX('3.Trazabilidad'!N:N, MATCH(S32, '3.Trazabilidad'!G:G, 0)), "-")} -> NO | U32: {=IFERROR(INDEX('3.Trazabilidad'!O:O, MATCH(S32, '3.Trazabilidad'!G:G, 0)), "-")} -> NO | W32: {=IF(AND(COUNTIF('LAKEHOUSE (Tbl Campos)'!$F$2:$F$14000,$S$3:$S$910)>0),"X","-")} -> -
B33: INSIS | C33: LPV | D33: INSIS_GEN_V10 | E33: POLICY | F33: ="SELECT * FROM "&D33&"."&E33 -> SELECT * FROM INSIS_GEN_V10.POLICY | G33: NO CATÁLOGO | J33: =CONCATENATE(B33,".",C33,".",D33,".",E33) -> INSIS.LPV.INSIS_GEN_V10.POLICY | K33: {=IF(AND(COUNTIF(LAKEHOUSE!$E$2:$E$14000,$J$3:$J$310)>0),"X","-")} -> - | M33: INSIS | N33: INSIS | O33: LPV | P33: INSIS_PEOPLE_V10 | Q33: P_AGENTS | R33: AGENT_TYPE | S33: =CONCATENATE(M33,".",O33,".",P33,".",Q33,".",R33) -> INSIS.LPV.INSIS_PEOPLE_V10.P_AGENTS.AGENT_TYPE | T33: {=IFERROR(INDEX('3.Trazabilidad'!N:N, MATCH(S33, '3.Trazabilidad'!G:G, 0)), "-")} -> NO | U33: {=IFERROR(INDEX('3.Trazabilidad'!O:O, MATCH(S33, '3.Trazabilidad'!G:G, 0)), "-")} -> NO | W33: {=IF(AND(COUNTIF('LAKEHOUSE (Tbl Campos)'!$F$2:$F$14000,$S$3:$S$910)>0),"X","-")} -> -
B34: INSIS | C34: LPV | D34: INSIS_CUST | E34: HST_CUST_SALES_UNIT | F34: ="SELECT * FROM "&D34&"."&E34 -> SELECT * FROM INSIS_CUST.HST_CUST_SALES_UNIT | G34: CATÁLOGO | J34: =CONCATENATE(B34,".",C34,".",D34,".",E34) -> INSIS.LPV.INSIS_CUST.HST_CUST_SALES_UNIT | K34: {=IF(AND(COUNTIF(LAKEHOUSE!$E$2:$E$14000,$J$3:$J$310)>0),"X","-")} -> - | M34: INSIS | N34: INSIS | O34: LPV | P34: INSIS_PEOPLE_V10 | Q34: HT_AGENT_TYPE | R34: NAME | S34: =CONCATENATE(M34,".",O34,".",P34,".",Q34,".",R34) -> INSIS.LPV.INSIS_PEOPLE_V10.HT_AGENT_TYPE.NAME | T34: {=IFERROR(INDEX('3.Trazabilidad'!N:N, MATCH(S34, '3.Trazabilidad'!G:G, 0)), "-")} -> NO | U34: {=IFERROR(INDEX('3.Trazabilidad'!O:O, MATCH(S34, '3.Trazabilidad'!G:G, 0)), "-")} -> NO | W34: {=IF(AND(COUNTIF('LAKEHOUSE (Tbl Campos)'!$F$2:$F$14000,$S$3:$S$910)>0),"X","-")} -> -
B35: INSIS | C35: LPV | D35: INSIS_CUST_LPV | E35: BL_GENERAL_COLLECTION_LPV_OFFICE | F35: ="SELECT * FROM "&D35&"."&E35 -> SELECT * FROM INSIS_CUST_LPV.BL_GENERAL_COLLECTION_LPV_OFFICE | G35: CATÁLOGO | J35: =CONCATENATE(B35,".",C35,".",D35,".",E35) -> INSIS.LPV.INSIS_CUST_LPV.BL_GENERAL_COLLECTION_LPV_OFFICE | K35: {=IF(AND(COUNTIF(LAKEHOUSE!$E$2:$E$14000,$J$3:$J$310)>0),"X","-")} -> - | M35: INSIS | N35: INSIS | O35: LPV | P35: INSIS_PEOPLE_V10 | Q35: P_AGENTS | R35: AGENT_NO | S35: =CONCATENATE(M35,".",O35,".",P35,".",Q35,".",R35) -> INSIS.LPV.INSIS_PEOPLE_V10.P_AGENTS.AGENT_NO | T35: {=IFERROR(INDEX('3.Trazabilidad'!N:N, MATCH(S35, '3.Trazabilidad'!G:G, 0)), "-")} -> NO | U35: {=IFERROR(INDEX('3.Trazabilidad'!O:O, MATCH(S35, '3.Trazabilidad'!G:G, 0)), "-")} -> NO | W35: {=IF(AND(COUNTIF('LAKEHOUSE (Tbl Campos)'!$F$2:$F$14000,$S$3:$S$910)>0),"X","-")} -> -
B36: INSUNIX | C36: LPG | D36: INFORMIX | E36: CLIENT | F36: ="SELECT * FROM "&D36&"."&E36 -> SELECT * FROM INFORMIX.CLIENT | G36: NO CATÁLOGO | J36: =CONCATENATE(B36,".",C36,".",D36,".",E36) -> INSUNIX.LPG.INFORMIX.CLIENT | K36: {=IF(AND(COUNTIF(LAKEHOUSE!$E$2:$E$13372,$J$3:$J$310)>0),"X","-")} -> - | M36: INSIS | N36: INSIS | O36: LPV | P36: INSIS_PEOPLE_V10 | Q36: P_PEOPLE_RELATION | R36: VALID_FROM | S36: =CONCATENATE(M36,".",O36,".",P36,".",Q36,".",R36) -> INSIS.LPV.INSIS_PEOPLE_V10.P_PEOPLE_RELATION.VALID_FROM | T36: {=IFERROR(INDEX('3.Trazabilidad'!N:N, MATCH(S36, '3.Trazabilidad'!G:G, 0)), "-")} -> NO | U36: {=IFERROR(INDEX('3.Trazabilidad'!O:O, MATCH(S36, '3.Trazabilidad'!G:G, 0)), "-")} -> NO | W36: {=IF(AND(COUNTIF('LAKEHOUSE (Tbl Campos)'!$F$2:$F$14000,$S$3:$S$910)>0),"X","-")} -> -
B37: INSUNIX | C37: LPG | D37: INSUNIX | E37: TABLE18 | F37: ="SELECT * FROM "&D37&"."&E37 -> SELECT * FROM INSUNIX.TABLE18 | G37: CATÁLOGO | J37: =CONCATENATE(B37,".",C37,".",D37,".",E37) -> INSUNIX.LPG.INSUNIX.TABLE18 | K37: {=IF(AND(COUNTIF(LAKEHOUSE!$E$2:$E$13372,$J$3:$J$310)>0),"X","-")} -> - | M37: INSIS | N37: INSIS | O37: LPV | P37: INSIS_PEOPLE_V10 | Q37: P_PEOPLE_RELATION | R37: VALID_TO | S37: =CONCATENATE(M37,".",O37,".",P37,".",Q37,".",R37) -> INSIS.LPV.INSIS_PEOPLE_V10.P_PEOPLE_RELATION.VALID_TO | T37: {=IFERROR(INDEX('3.Trazabilidad'!N:N, MATCH(S37, '3.Trazabilidad'!G:G, 0)), "-")} -> NO | U37: {=IFERROR(INDEX('3.Trazabilidad'!O:O, MATCH(S37, '3.Trazabilidad'!G:G, 0)), "-")} -> NO | V37: 1 | W37: {=IF(AND(COUNTIF('LAKEHOUSE (Tbl Campos)'!$F$2:$F$14000,$S$3:$S$910)>0),"X","-")} -> -
B38: INSUNIX | C38: LPG | D38: INSUNIX | E38: TABLE121 | F38: ="SELECT * FROM "&D38&"."&E38 -> SELECT * FROM INSUNIX.TABLE121 | G38: CATÁLOGO | J38: =CONCATENATE(B38,".",C38,".",D38,".",E38) -> INSUNIX.LPG.INSUNIX.TABLE121 | K38: {=IF(AND(COUNTIF(LAKEHOUSE!$E$2:$E$13372,$J$3:$J$310)>0),"X","-")} -> - | M38: INSIS | N38: INSIS | O38: LPV | P38: INSIS_GEN_V10 | Q38: POLICY_PARTICIPANTS | R38: PARTICIPANT_ROLE | S38: =CONCATENATE(M38,".",O38,".",P38,".",Q38,".",R38) -> INSIS.LPV.INSIS_GEN_V10.POLICY_PARTICIPANTS.PARTICIPANT_ROLE | T38: {=IFERROR(INDEX('3.Trazabilidad'!N:N, MATCH(S38, '3.Trazabilidad'!G:G, 0)), "-")} -> NO | U38: {=IFERROR(INDEX('3.Trazabilidad'!O:O, MATCH(S38, '3.Trazabilidad'!G:G, 0)), "-")} -> NO | V38: 1 | W38: {=IF(AND(COUNTIF('LAKEHOUSE (Tbl Campos)'!$F$2:$F$14000,$S$3:$S$910)>0),"X","-")} -> -
B39: INSUNIX | C39: LPG | D39: INSUNIX | E39: TABLE23 | F39: ="SELECT * FROM "&D39&"."&E39 -> SELECT * FROM INSUNIX.TABLE23 | G39: CATÁLOGO | J39: =CONCATENATE(B39,".",C39,".",D39,".",E39) -> INSUNIX.LPG.INSUNIX.TABLE23 | K39: {=IF(AND(COUNTIF(LAKEHOUSE!$E$2:$E$13372,$J$3:$J$310)>0),"X","-")} -> - | M39: INSIS | N39: INSIS | O39: LPV | P39: INSIS_SYS_V10 | Q39: CFG_NOM_LANGUAGE_TABLE | R39: NAME | S39: =CONCATENATE(M39,".",O39,".",P39,".",Q39,".",R39) -> INSIS.LPV.INSIS_SYS_V10.CFG_NOM_LANGUAGE_TABLE.NAME | T39: {=IFERROR(INDEX('3.Trazabilidad'!N:N, MATCH(S39, '3.Trazabilidad'!G:G, 0)), "-")} -> NO | U39: {=IFERROR(INDEX('3.Trazabilidad'!O:O, MATCH(S39, '3.Trazabilidad'!G:G, 0)), "-")} -> NO | V39: 1 | W39: {=IF(AND(COUNTIF('LAKEHOUSE (Tbl Campos)'!$F$2:$F$14000,$S$3:$S$910)>0),"X","-")} -> -
B40: INSUNIX | C40: LPG | D40: INFORMIX | E40: CLIEN_BLOCK_HIS | F40: ="SELECT * FROM "&D40&"."&E40 -> SELECT * FROM INFORMIX.CLIEN_BLOCK_HIS | G40: NO CATÁLOGO | J40: =CONCATENATE(B40,".",C40,".",D40,".",E40) -> INSUNIX.LPG.INFORMIX.CLIEN_BLOCK_HIS | K40: {=IF(AND(COUNTIF(LAKEHOUSE!$E$2:$E$13372,$J$3:$J$310)>0),"X","-")} -> - | M40: INSIS | N40: INSIS | O40: LPV | P40: INSIS_GEN_V10 | Q40: O_ACCINSURED | R40: MAN_ID | S40: =CONCATENATE(M40,".",O40,".",P40,".",Q40,".",R40) -> INSIS.LPV.INSIS_GEN_V10.O_ACCINSURED.MAN_ID | T40: {=IFERROR(INDEX('3.Trazabilidad'!N:N, MATCH(S40, '3.Trazabilidad'!G:G, 0)), "-")} -> NO | U40: {=IFERROR(INDEX('3.Trazabilidad'!O:O, MATCH(S40, '3.Trazabilidad'!G:G, 0)), "-")} -> NO | V40: 1 | W40: {=IF(AND(COUNTIF('LAKEHOUSE (Tbl Campos)'!$F$2:$F$14000,$S$3:$S$910)>0),"X","-")} -> -
B41: INSUNIX | C41: LPG | D41: INFORMIX | E41: TABLE120 | F41: ="SELECT * FROM "&D41&"."&E41 -> SELECT * FROM INFORMIX.TABLE120 | G41: CATÁLOGO | J41: =CONCATENATE(B41,".",C41,".",D41,".",E41) -> INSUNIX.LPG.INFORMIX.TABLE120 | K41: {=IF(AND(COUNTIF(LAKEHOUSE!$E$2:$E$13372,$J$3:$J$310)>0),"X","-")} -> - | M41: INSIS | N41: INSIS | O41: LPV | P41: INSIS_GEN_V10 | Q41: POLICY_PARTICIPANTS | R41: MAN_ID | S41: =CONCATENATE(M41,".",O41,".",P41,".",Q41,".",R41) -> INSIS.LPV.INSIS_GEN_V10.POLICY_PARTICIPANTS.MAN_ID | T41: {=IFERROR(INDEX('3.Trazabilidad'!N:N, MATCH(S41, '3.Trazabilidad'!G:G, 0)), "-")} -> NO | U41: {=IFERROR(INDEX('3.Trazabilidad'!O:O, MATCH(S41, '3.Trazabilidad'!G:G, 0)), "-")} -> NO | V41: 1 | W41: {=IF(AND(COUNTIF('LAKEHOUSE (Tbl Campos)'!$F$2:$F$14000,$S$3:$S$910)>0),"X","-")} -> -
B42: INSUNIX | C42: LPG | D42: INFORMIX | E42: ADDRESS | F42: ="SELECT * FROM "&D42&"."&E42 -> SELECT * FROM INFORMIX.ADDRESS | G42: NO CATÁLOGO | J42: =CONCATENATE(B42,".",C42,".",D42,".",E42) -> INSUNIX.LPG.INFORMIX.ADDRESS | K42: {=IF(AND(COUNTIF(LAKEHOUSE!$E$2:$E$13372,$J$3:$J$310)>0),"X","-")} -> - | M42: INSIS | N42: INSIS | O42: LPV | P42: INSIS_PEOPLE_V10 | Q42: P_PEOPLE_RELATION | R42: REL_ID | S42: =CONCATENATE(M42,".",O42,".",P42,".",Q42,".",R42) -> INSIS.LPV.INSIS_PEOPLE_V10.P_PEOPLE_RELATION.REL_ID | T42: {=IFERROR(INDEX('3.Trazabilidad'!N:N, MATCH(S42, '3.Trazabilidad'!G:G, 0)), "-")} -> NO | U42: {=IFERROR(INDEX('3.Trazabilidad'!O:O, MATCH(S42, '3.Trazabilidad'!G:G, 0)), "-")} -> NO | V42: 1 | W42: {=IF(AND(COUNTIF('LAKEHOUSE (Tbl Campos)'!$F$2:$F$14000,$S$3:$S$910)>0),"X","-")} -> -
B43: INSUNIX | C43: LPG | D43: INSUNIX | E43: TABLE61 | F43: ="SELECT * FROM "&D43&"."&E43 -> SELECT * FROM INSUNIX.TABLE61 | G43: CATÁLOGO | J43: =CONCATENATE(B43,".",C43,".",D43,".",E43) -> INSUNIX.LPG.INSUNIX.TABLE61 | K43: {=IF(AND(COUNTIF(LAKEHOUSE!$E$2:$E$13372,$J$3:$J$310)>0),"X","-")} -> - | M43: INSIS | N43: INSIS | O43: LPV | P43: INSIS_PEOPLE_V10 | Q43: HT_PEOPLE_RELATION | R43: REL_NAME | S43: =CONCATENATE(M43,".",O43,".",P43,".",Q43,".",R43) -> INSIS.LPV.INSIS_PEOPLE_V10.HT_PEOPLE_RELATION.REL_NAME | T43: {=IFERROR(INDEX('3.Trazabilidad'!N:N, MATCH(S43, '3.Trazabilidad'!G:G, 0)), "-")} -> NO | U43: {=IFERROR(INDEX('3.Trazabilidad'!O:O, MATCH(S43, '3.Trazabilidad'!G:G, 0)), "-")} -> NO | V43: 1 | W43: {=IF(AND(COUNTIF('LAKEHOUSE (Tbl Campos)'!$F$2:$F$14000,$S$3:$S$910)>0),"X","-")} -> -
B44: INSUNIX | C44: LPG | D44: INSUNIX | E44: INTERMEDIA | F44: ="SELECT * FROM "&D44&"."&E44 -> SELECT * FROM INSUNIX.INTERMEDIA | G44: NO CATÁLOGO | J44: =CONCATENATE(B44,".",C44,".",D44,".",E44) -> INSUNIX.LPG.INSUNIX.INTERMEDIA | K44: {=IF(AND(COUNTIF(LAKEHOUSE!$E$2:$E$13372,$J$3:$J$310)>0),"X","-")} -> - | M44: INSIS | N44: INSIS | O44: LPV | P44: INSIS_GEN_V10 | Q44: CLAIM | R44: DEATH_DATE | S44: =CONCATENATE(M44,".",O44,".",P44,".",Q44,".",R44) -> INSIS.LPV.INSIS_GEN_V10.CLAIM.DEATH_DATE | T44: {=IFERROR(INDEX('3.Trazabilidad'!N:N, MATCH(S44, '3.Trazabilidad'!G:G, 0)), "-")} -> SÍ | U44: {=IFERROR(INDEX('3.Trazabilidad'!O:O, MATCH(S44, '3.Trazabilidad'!G:G, 0)), "-")} -> NO | V44: 1 | W44: {=IF(AND(COUNTIF('LAKEHOUSE (Tbl Campos)'!$F$2:$F$14000,$S$3:$S$910)>0),"X","-")} -> -
B45: INSUNIX | C45: LPG | D45: INSUNIX | E45: INTERM_TYP | F45: ="SELECT * FROM "&D45&"."&E45 -> SELECT * FROM INSUNIX.INTERM_TYP | G45: NO CATÁLOGO | J45: =CONCATENATE(B45,".",C45,".",D45,".",E45) -> INSUNIX.LPG.INSUNIX.INTERM_TYP | K45: {=IF(AND(COUNTIF(LAKEHOUSE!$E$2:$E$13372,$J$3:$J$310)>0),"X","-")} -> - | M45: INSIS | N45: INSIS | O45: LPV | P45: INSIS_GEN_V10 | Q45: CLAIM_OBJECTS | R45: INJURED_OBJECT_ID | S45: =CONCATENATE(M45,".",O45,".",P45,".",Q45,".",R45) -> INSIS.LPV.INSIS_GEN_V10.CLAIM_OBJECTS.INJURED_OBJECT_ID | T45: {=IFERROR(INDEX('3.Trazabilidad'!N:N, MATCH(S45, '3.Trazabilidad'!G:G, 0)), "-")} -> NO | U45: {=IFERROR(INDEX('3.Trazabilidad'!O:O, MATCH(S45, '3.Trazabilidad'!G:G, 0)), "-")} -> NO | V45: 8 | W45: {=IF(AND(COUNTIF('LAKEHOUSE (Tbl Campos)'!$F$2:$F$14000,$S$3:$S$910)>0),"X","-")} -> -
B46: INSUNIX | C46: LPG | D46: INSUNIX | E46: CLIENT_INTER | F46: ="SELECT * FROM "&D46&"."&E46 -> SELECT * FROM INSUNIX.CLIENT_INTER | G46: NO CATÁLOGO | J46: =CONCATENATE(B46,".",C46,".",D46,".",E46) -> INSUNIX.LPG.INSUNIX.CLIENT_INTER | K46: {=IF(AND(COUNTIF(LAKEHOUSE!$E$2:$E$13372,$J$3:$J$310)>0),"X","-")} -> - | M46: INSIS | N46: INSIS | O46: LPV | P46: INSIS_GEN_V10 | Q46: POLICY | R46: ATTR3 | S46: =CONCATENATE(M46,".",O46,".",P46,".",Q46,".",R46) -> INSIS.LPV.INSIS_GEN_V10.POLICY.ATTR3 | T46: {=IFERROR(INDEX('3.Trazabilidad'!N:N, MATCH(S46, '3.Trazabilidad'!G:G, 0)), "-")} -> NO | U46: {=IFERROR(INDEX('3.Trazabilidad'!O:O, MATCH(S46, '3.Trazabilidad'!G:G, 0)), "-")} -> NO | V46: 1 | W46: {=IF(AND(COUNTIF('LAKEHOUSE (Tbl Campos)'!$F$2:$F$14000,$S$3:$S$910)>0),"X","-")} -> -
B47: INSUNIX | C47: LPG | D47: INFORMIX | E47: ROLES | F47: ="SELECT * FROM "&D47&"."&E47 -> SELECT * FROM INFORMIX.ROLES | G47: NO CATÁLOGO | J47: =CONCATENATE(B47,".",C47,".",D47,".",E47) -> INSUNIX.LPG.INFORMIX.ROLES | K47: {=IF(AND(COUNTIF(LAKEHOUSE!$E$2:$E$13372,$J$3:$J$310)>0),"X","-")} -> - | M47: INSIS | N47: INSIS | O47: LPV | P47: INSIS_CUST | Q47: HST_CUST_SALES_UNIT | R47: NAME | S47: =CONCATENATE(M47,".",O47,".",P47,".",Q47,".",R47) -> INSIS.LPV.INSIS_CUST.HST_CUST_SALES_UNIT.NAME | T47: {=IFERROR(INDEX('3.Trazabilidad'!N:N, MATCH(S47, '3.Trazabilidad'!G:G, 0)), "-")} -> NO | U47: {=IFERROR(INDEX('3.Trazabilidad'!O:O, MATCH(S47, '3.Trazabilidad'!G:G, 0)), "-")} -> NO | V47: 1 | W47: {=IF(AND(COUNTIF('LAKEHOUSE (Tbl Campos)'!$F$2:$F$14000,$S$3:$S$910)>0),"X","-")} -> -
B48: INSUNIX | C48: LPG | D48: INSUNIX | E48: TABLE12 | F48: ="SELECT * FROM "&D48&"."&E48 -> SELECT * FROM INSUNIX.TABLE12 | G48: CATÁLOGO | J48: =CONCATENATE(B48,".",C48,".",D48,".",E48) -> INSUNIX.LPG.INSUNIX.TABLE12 | K48: {=IF(AND(COUNTIF(LAKEHOUSE!$E$2:$E$13372,$J$3:$J$310)>0),"X","-")} -> - | M48: INSIS | N48: INSIS | O48: LPV | P48: INSIS_GEN_V10 | Q48: POLICY | R48: OFFICE_ID | S48: =CONCATENATE(M48,".",O48,".",P48,".",Q48,".",R48) -> INSIS.LPV.INSIS_GEN_V10.POLICY.OFFICE_ID | T48: {=IFERROR(INDEX('3.Trazabilidad'!N:N, MATCH(S48, '3.Trazabilidad'!G:G, 0)), "-")} -> NO | U48: {=IFERROR(INDEX('3.Trazabilidad'!O:O, MATCH(S48, '3.Trazabilidad'!G:G, 0)), "-")} -> NO | V48: 1 | W48: {=IF(AND(COUNTIF('LAKEHOUSE (Tbl Campos)'!$F$2:$F$14000,$S$3:$S$910)>0),"X","-")} -> -
... B61: VTIME | C61: LPG | D61: INSUDB | E61: CLIENT_BLOCKHIS | F61: ="SELECT * FROM "&D61&"."&E61 -> SELECT * FROM INSUDB.CLIENT_BLOCKHIS | G61: NO CATÁLOGO | J61: =CONCATENATE(B61,".",C61,".",D61,".",E61) -> VTIME.LPG.INSUDB.CLIENT_BLOCKHIS | K61: {=IF(AND(COUNTIF(LAKEHOUSE!$E$2:$E$13372,$J$3:$J$310)>0),"X","-")} -> - | M61: INSIS | N61: INSIS | O61: LPV | P61: INSIS_NTW_V10 | Q61: P_PROVIDERS | R61: ABBREVIATION | S61: =CONCATENATE(M61,".",O61,".",P61,".",Q61,".",R61) -> INSIS.LPV.INSIS_NTW_V10.P_PROVIDERS.ABBREVIATION | T61: {=IFERROR(INDEX('3.Trazabilidad'!N:N, MATCH(S61, '3.Trazabilidad'!G:G, 0)), "-")} -> SÍ | U61: {=IFERROR(INDEX('3.Trazabilidad'!O:O, MATCH(S61, '3.Trazabilidad'!G:G, 0)), "-")} -> NO | V61: 1 | W61: {=IF(AND(COUNTIF('LAKEHOUSE (Tbl Campos)'!$F$2:$F$14000,$S$3:$S$910)>0),"X","-")} -> -
B62: VTIME | C62: LPG | D62: INSUDB | E62: TAB_BLOCKCLI | F62: ="SELECT * FROM "&D62&"."&E62 -> SELECT * FROM INSUDB.TAB_BLOCKCLI | G62: CATÁLOGO | J62: =CONCATENATE(B62,".",C62,".",D62,".",E62) -> VTIME.LPG.INSUDB.TAB_BLOCKCLI | K62: {=IF(AND(COUNTIF(LAKEHOUSE!$E$2:$E$13372,$J$3:$J$310)>0),"X","-")} -> - | M62: INSUNIX | N62: INSUNIX | O62: LPG | P62: INFORMIX | Q62: ADDRESS | R62: E_MAIL | S62: =CONCATENATE(M62,".",O62,".",P62,".",Q62,".",R62) -> INSUNIX.LPG.INFORMIX.ADDRESS.E_MAIL | V62: 1 | W62: {=IF(AND(COUNTIF('LAKEHOUSE (Tbl Campos)'!$F$2:$F$14000,$S$3:$S$910)>0),"X","-")} -> -
B63: VTIME | C63: LPG | D63: INSUDB | E63: ADDRESS | F63: ="SELECT * FROM "&D63&"."&E63 -> SELECT * FROM INSUDB.ADDRESS | G63: NO CATÁLOGO | J63: =CONCATENATE(B63,".",C63,".",D63,".",E63) -> VTIME.LPG.INSUDB.ADDRESS | K63: {=IF(AND(COUNTIF(LAKEHOUSE!$E$2:$E$13372,$J$3:$J$310)>0),"X","-")} -> - | M63: INSUNIX | N63: INSUNIX | O63: LPG | P63: INFORMIX | Q63: ADDRESS | R63: PHONE | S63: =CONCATENATE(M63,".",O63,".",P63,".",Q63,".",R63) -> INSUNIX.LPG.INFORMIX.ADDRESS.PHONE | V63: 1 | W63: {=IF(AND(COUNTIF('LAKEHOUSE (Tbl Campos)'!$F$2:$F$14000,$S$3:$S$910)>0),"X","-")} -> -
B64: VTIME | C64: LPG | D64: INSUDB | E64: PHONES | F64: ="SELECT * FROM "&D64&"."&E64 -> SELECT * FROM INSUDB.PHONES | G64: NO CATÁLOGO | J64: =CONCATENATE(B64,".",C64,".",D64,".",E64) -> VTIME.LPG.INSUDB.PHONES | K64: {=IF(AND(COUNTIF(LAKEHOUSE!$E$2:$E$13372,$J$3:$J$310)>0),"X","-")} -> - | M64: INSUNIX | N64: INSUNIX | O64: LPG | P64: INFORMIX | Q64: ADDRESS | R64: RECTYPE | S64: =CONCATENATE(M64,".",O64,".",P64,".",Q64,".",R64) -> INSUNIX.LPG.INFORMIX.ADDRESS.RECTYPE | V64: 1 | W64: {=IF(AND(COUNTIF('LAKEHOUSE (Tbl Campos)'!$F$2:$F$14000,$S$3:$S$910)>0),"X","-")} -> -
B65: VTIME | C65: LPG | D65: INSUDB | E65: TABLE6000 | F65: ="SELECT * FROM "&D65&"."&E65 -> SELECT * FROM INSUDB.TABLE6000 | G65: CATÁLOGO | J65: =CONCATENATE(B65,".",C65,".",D65,".",E65) -> VTIME.LPG.INSUDB.TABLE6000 | K65: {=IF(AND(COUNTIF(LAKEHOUSE!$E$2:$E$13372,$J$3:$J$310)>0),"X","-")} -> - | M65: INSUNIX | N65: INSUNIX | O65: LPG | P65: INFORMIX | Q65: ADDRESS | R65: STREET | S65: =CONCATENATE(M65,".",O65,".",P65,".",Q65,".",R65) -> INSUNIX.LPG.INFORMIX.ADDRESS.STREET | V65: 1 | W65: {=IF(AND(COUNTIF('LAKEHOUSE (Tbl Campos)'!$F$2:$F$14000,$S$3:$S$910)>0),"X","-")} -> -
B66: VTIME | C66: LPG | D66: INSUDB | E66: INTERMEDIA | F66: ="SELECT * FROM "&D66&"."&E66 -> SELECT * FROM INSUDB.INTERMEDIA | G66: NO CATÁLOGO | J66: =CONCATENATE(B66,".",C66,".",D66,".",E66) -> VTIME.LPG.INSUDB.INTERMEDIA | K66: {=IF(AND(COUNTIF(LAKEHOUSE!$E$2:$E$13372,$J$3:$J$310)>0),"X","-")} -> - | M66: INSUNIX | N66: INSUNIX | O66: LPG | P66: INFORMIX | Q66: CLAIM_AUTO | R66: DRIV_ID | S66: =CONCATENATE(M66,".",O66,".",P66,".",Q66,".",R66) -> INSUNIX.LPG.INFORMIX.CLAIM_AUTO.DRIV_ID | V66: 9 | W66: {=IF(AND(COUNTIF('LAKEHOUSE (Tbl Campos)'!$F$2:$F$14000,$S$3:$S$910)>0),"X","-")} -> -
B67: VTIME | C67: LPG | D67: INSUDB | E67: INTERM_TYP | F67: ="SELECT * FROM "&D67&"."&E67 -> SELECT * FROM INSUDB.INTERM_TYP | G67: CATÁLOGO | J67: =CONCATENATE(B67,".",C67,".",D67,".",E67) -> VTIME.LPG.INSUDB.INTERM_TYP | K67: {=IF(AND(COUNTIF(LAKEHOUSE!$E$2:$E$13372,$J$3:$J$310)>0),"X","-")} -> - | M67: INSUNIX | N67: INSUNIX | O67: LPG | P67: INFORMIX | Q67: CLAIM_AUTO | R67: DRIVER | S67: =CONCATENATE(M67,".",O67,".",P67,".",Q67,".",R67) -> INSUNIX.LPG.INFORMIX.CLAIM_AUTO.DRIVER | V67: 1 | W67: {=IF(AND(COUNTIF('LAKEHOUSE (Tbl Campos)'!$F$2:$F$14000,$S$3:$S$910)>0),"X","-")} -> -
B68: VTIME | C68: LPG | D68: INSUDB | E68: CLIENTINTER | F68: ="SELECT * FROM "&D68&"."&E68 -> SELECT * FROM INSUDB.CLIENTINTER | G68: NO CATÁLOGO | J68: =CONCATENATE(B68,".",C68,".",D68,".",E68) -> VTIME.LPG.INSUDB.CLIENTINTER | K68: {=IF(AND(COUNTIF(LAKEHOUSE!$E$2:$E$13372,$J$3:$J$310)>0),"X","-")} -> - | M68: INSUNIX | N68: INSUNIX | O68: LPG | P68: INFORMIX | Q68: CLAIM_CASE | R68: DEATHDAT | S68: =CONCATENATE(M68,".",O68,".",P68,".",Q68,".",R68) -> INSUNIX.LPG.INFORMIX.CLAIM_CASE.DEATHDAT | V68: 1 | W68: {=IF(AND(COUNTIF('LAKEHOUSE (Tbl Campos)'!$F$2:$F$14000,$S$3:$S$910)>0),"X","-")} -> -
B69: VTIME | C69: LPG | D69: INSUDB | E69: ROLES | F69: ="SELECT * FROM "&D69&"."&E69 -> SELECT * FROM INSUDB.ROLES | G69: NO CATÁLOGO | J69: =CONCATENATE(B69,".",C69,".",D69,".",E69) -> VTIME.LPG.INSUDB.ROLES | K69: {=IF(AND(COUNTIF(LAKEHOUSE!$E$2:$E$13372,$J$3:$J$310)>0),"X","-")} -> - | M69: INSUNIX | N69: INSUNIX | O69: LPG | P69: INFORMIX | Q69: CLIEN_BLOCK_HIS | R69: COD_MOT | S69: =CONCATENATE(M69,".",O69,".",P69,".",Q69,".",R69) -> INSUNIX.LPG.INFORMIX.CLIEN_BLOCK_HIS.COD_MOT | V69: 1 | W69: {=IF(AND(COUNTIF('LAKEHOUSE (Tbl Campos)'!$F$2:$F$14000,$S$3:$S$910)>0),"X","-")} -> -
B70: VTIME | C70: LPG | D70: INSUDB | E70: TABLE12 | F70: ="SELECT * FROM "&D70&"."&E70 -> SELECT * FROM INSUDB.TABLE12 | G70: CATÁLOGO | J70: =CONCATENATE(B70,".",C70,".",D70,".",E70) -> VTIME.LPG.INSUDB.TABLE12 | K70: {=IF(AND(COUNTIF(LAKEHOUSE!$E$2:$E$13372,$J$3:$J$310)>0),"X","-")} -> - | M70: INSUNIX | N70: INSUNIX | O70: LPG | P70: INFORMIX | Q70: CLIENT | R70: BIRTHDATE | S70: =CONCATENATE(M70,".",O70,".",P70,".",Q70,".",R70) -> INSUNIX.LPG.INFORMIX.CLIENT.BIRTHDATE | V70: 1 | W70: {=IF(AND(COUNTIF('LAKEHOUSE (Tbl Campos)'!$F$2:$F$14000,$S$3:$S$910)>0),"X","-")} -> -
B71: VTIME | C71: LPG | D71: INSUDB | E71: BENEFICIAR | F71: ="SELECT * FROM "&D71&"."&E71 -> SELECT * FROM INSUDB.BENEFICIAR | G71: NO CATÁLOGO | J71: =CONCATENATE(B71,".",C71,".",D71,".",E71) -> VTIME.LPG.INSUDB.BENEFICIAR | K71: {=IF(AND(COUNTIF(LAKEHOUSE!$E$2:$E$13372,$J$3:$J$310)>0),"X","-")} -> - | M71: INSUNIX | N71: INSUNIX | O71: LPG | P71: INFORMIX | Q71: CLIENT | R71: BLOCKADE | S71: =CONCATENATE(M71,".",O71,".",P71,".",Q71,".",R71) -> INSUNIX.LPG.INFORMIX.CLIENT.BLOCKADE | V71: 1 | W71: {=IF(AND(COUNTIF('LAKEHOUSE (Tbl Campos)'!$F$2:$F$14000,$S$3:$S$910)>0),"X","-")} -> -
B72: VTIME | C72: LPG | D72: INSUDB | E72: TABLE55 | F72: ="SELECT * FROM "&D72&"."&E72 -> SELECT * FROM INSUDB.TABLE55 | G72: CATÁLOGO | J72: =CONCATENATE(B72,".",C72,".",D72,".",E72) -> VTIME.LPG.INSUDB.TABLE55 | K72: {=IF(AND(COUNTIF(LAKEHOUSE!$E$2:$E$13372,$J$3:$J$310)>0),"X","-")} -> - | M72: INSUNIX | N72: INSUNIX | O72: LPG | P72: INFORMIX | Q72: CLIENT | R72: CIIU | S72: =CONCATENATE(M72,".",O72,".",P72,".",Q72,".",R72) -> INSUNIX.LPG.INFORMIX.CLIENT.CIIU | V72: 4 | W72: {=IF(AND(COUNTIF('LAKEHOUSE (Tbl Campos)'!$F$2:$F$14000,$S$3:$S$910)>0),"X","-")} -> -
B73: VTIME | C73: LPG | D73: INSUDB | E73: CLAIMBENEF | F73: ="SELECT * FROM "&D73&"."&E73 -> SELECT * FROM INSUDB.CLAIMBENEF | G73: NO CATÁLOGO | J73: =CONCATENATE(B73,".",C73,".",D73,".",E73) -> VTIME.LPG.INSUDB.CLAIMBENEF | K73: {=IF(AND(COUNTIF(LAKEHOUSE!$E$2:$E$13372,$J$3:$J$310)>0),"X","-")} -> - | M73: INSUNIX | N73: INSUNIX | O73: LPG | P73: INFORMIX | Q73: CLIENT | R73: CLIENAME | S73: =CONCATENATE(M73,".",O73,".",P73,".",Q73,".",R73) -> INSUNIX.LPG.INFORMIX.CLIENT.CLIENAME | V73: 1 | W73: {=IF(AND(COUNTIF('LAKEHOUSE (Tbl Campos)'!$F$2:$F$14000,$S$3:$S$910)>0),"X","-")} -> -
B74: VTIME | C74: LPG | D74: INSUDB | E74: CLAIM_AUTO | F74: ="SELECT * FROM "&D74&"."&E74 -> SELECT * FROM INSUDB.CLAIM_AUTO | G74: NO CATÁLOGO | J74: =CONCATENATE(B74,".",C74,".",D74,".",E74) -> VTIME.LPG.INSUDB.CLAIM_AUTO | K74: {=IF(AND(COUNTIF(LAKEHOUSE!$E$2:$E$13372,$J$3:$J$310)>0),"X","-")} -> - | M74: INSUNIX | N74: INSUNIX | O74: LPG | P74: INFORMIX | Q74: CLIENT | R74: CODE | S74: =CONCATENATE(M74,".",O74,".",P74,".",Q74,".",R74) -> INSUNIX.LPG.INFORMIX.CLIENT.CODE | V74: 1 | W74: {=IF(AND(COUNTIF('LAKEHOUSE (Tbl Campos)'!$F$2:$F$14000,$S$3:$S$910)>0),"X","-")} -> -
M75: INSUNIX | N75: INSUNIX | O75: LPG | P75: INFORMIX | Q75: CLIENT | R75: ELEC_BOOK | S75: =CONCATENATE(M75,".",O75,".",P75,".",Q75,".",R75) -> INSUNIX.LPG.INFORMIX.CLIENT.ELEC_BOOK | V75: 1 | W75: {=IF(AND(COUNTIF('LAKEHOUSE (Tbl Campos)'!$F$2:$F$14000,$S$3:$S$910)>0),"X","-")} -> -
M76: INSUNIX | N76: INSUNIX | O76: LPG | P76: INFORMIX | Q76: CLIENT | R76: RUC | S76: =CONCATENATE(M76,".",O76,".",P76,".",Q76,".",R76) -> INSUNIX.LPG.INFORMIX.CLIENT.RUC | V76: 1 | W76: {=IF(AND(COUNTIF('LAKEHOUSE (Tbl Campos)'!$F$2:$F$14000,$S$3:$S$910)>0),"X","-")} -> -
M77: INSUNIX | N77: INSUNIX | O77: LPG | P77: INFORMIX | Q77: CLIENT | R77: SEXCLIEN | S77: =CONCATENATE(M77,".",O77,".",P77,".",Q77,".",R77) -> INSUNIX.LPG.INFORMIX.CLIENT.SEXCLIEN | V77: 1 | W77: {=IF(AND(COUNTIF('LAKEHOUSE (Tbl Campos)'!$F$2:$F$14000,$S$3:$S$910)>0),"X","-")} -> -
M78: INSUNIX | N78: INSUNIX | O78: LPG | P78: INFORMIX | Q78: TABLE120 | R78: DESCRIPT | S78: =CONCATENATE(M78,".",O78,".",P78,".",Q78,".",R78) -> INSUNIX.LPG.INFORMIX.TABLE120.DESCRIPT | V78: 1 | W78: {=IF(AND(COUNTIF('LAKEHOUSE (Tbl Campos)'!$F$2:$F$14000,$S$3:$S$910)>0),"X","-")} -> -
M79: INSUNIX | N79: INSUNIX | O79: LPG | P79: INFORMIX | Q79: ROLES | R79: CLIENT | S79: =CONCATENATE(M79,".",O79,".",P79,".",Q79,".",R79) -> INSUNIX.LPG.INFORMIX .ROLES.CLIENT | V79: 1 | W79: {=IF(AND(COUNTIF('LAKEHOUSE (Tbl Campos)'!$F$2:$F$14000,$S$3:$S$910)>0),"X","-")} -> -
M80: INSUNIX | N80: INSUNIX | O80: LPG | P80: INFORMIX | Q80: ROLES | R80: ROLE | S80: =CONCATENATE(M80,".",O80,".",P80,".",Q80,".",R80) -> INSUNIX.LPG.INFORMIX .ROLES.ROLE | V80: j | W80: {=IF(AND(COUNTIF('LAKEHOUSE (Tbl Campos)'!$F$2:$F$14000,$S$3:$S$910)>0),"X","-")} -> -
M81: INSUNIX | N81: INSUNIX | O81: LPG | P81: INSUNIX | Q81: BENEFICIAR | R81: RELATION | S81: =CONCATENATE(M81,".",O81,".",P81,".",Q81,".",R81) -> INSUNIX.LPG.INSUNIX.BENEFICIAR.RELATION | V81: 1 | W81: {=IF(AND(COUNTIF('LAKEHOUSE (Tbl Campos)'!$F$2:$F$14000,$S$3:$S$910)>0),"X","-")} -> -
M82: INSUNIX | N82: INSUNIX | O82: LPG | P82: INSUNIX | Q82: CLAIMBENEF | R82: BENE_CODE | S82: =CONCATENATE(M82,".",O82,".",P82,".",Q82,".",R82) -> INSUNIX.LPG.INSUNIX.CLAIMBENEF.BENE_CODE | V82: 1 | W82: {=IF(AND(COUNTIF('LAKEHOUSE (Tbl Campos)'!$F$2:$F$14000,$S$3:$S$910)>0),"X","-")} -> -
M83: INSUNIX | N83: INSUNIX | O83: LPG | P83: INSUNIX | Q83: CLIENT_INTER | R83: EFFECDATE | S83: =CONCATENATE(M83,".",O83,".",P83,".",Q83,".",R83) -> INSUNIX.LPG.INSUNIX.CLIENT_INTER.EFFECDATE | V83: 1 | W83: {=IF(AND(COUNTIF('LAKEHOUSE (Tbl Campos)'!$F$2:$F$14000,$S$3:$S$910)>0),"X","-")} -> -
M84: INSUNIX | N84: INSUNIX | O84: LPG | P84: INSUNIX | Q84: CLIENT_INTER | R84: INTERMED | S84: =CONCATENATE(M84,".",O84,".",P84,".",Q84,".",R84) -> INSUNIX.LPG.INSUNIX.CLIENT_INTER.INTERMED | V84: 1 | W84: {=IF(AND(COUNTIF('LAKEHOUSE (Tbl Campos)'!$F$2:$F$14000,$S$3:$S$910)>0),"X","-")} -> -
M85: INSUNIX | N85: INSUNIX | O85: LPG | P85: INSUNIX | Q85: CLIENT_INTER | R85: NULLDATE | S85: =CONCATENATE(M85,".",O85,".",P85,".",Q85,".",R85) -> INSUNIX.LPG.INSUNIX.CLIENT_INTER.NULLDATE | V85: 1 | W85: {=IF(AND(COUNTIF('LAKEHOUSE (Tbl Campos)'!$F$2:$F$14000,$S$3:$S$910)>0),"X","-")} -> -
M86: INSUNIX | N86: INSUNIX | O86: LPG | P86: INSUNIX | Q86: INTERM_TYP | R86: DESCRIPT | S86: =CONCATENATE(M86,".",O86,".",P86,".",Q86,".",R86) -> INSUNIX.LPG.INSUNIX.INTERM_TYP.DESCRIPT | V86: 1 | W86: {=IF(AND(COUNTIF('LAKEHOUSE (Tbl Campos)'!$F$2:$F$14000,$S$3:$S$910)>0),"X","-")} -> -
M87: INSUNIX | N87: INSUNIX | O87: LPG | P87: INSUNIX | Q87: INTERMEDIA | R87: DESCRIPT | S87: =CONCATENATE(M87,".",O87,".",P87,".",Q87,".",R87) -> INSUNIX.LPG.INSUNIX.INTERMEDIA.DESCRIPT | V87: 1 | W87: {=IF(AND(COUNTIF('LAKEHOUSE (Tbl Campos)'!$F$2:$F$14000,$S$3:$S$910)>0),"X","-")} -> -
M88: INSUNIX | N88: INSUNIX | O88: LPG | P88: INSUNIX | Q88: INTERMEDIA | R88: INTERTYP | S88: =CONCATENATE(M88,".",O88,".",P88,".",Q88,".",R88) -> INSUNIX.LPG.INSUNIX.INTERMEDIA.INTERTYP | V88: 1 | W88: {=IF(AND(COUNTIF('LAKEHOUSE (Tbl Campos)'!$F$2:$F$14000,$S$3:$S$910)>0),"X","-")} -> -
M89: INSUNIX | N89: INSUNIX | O89: LPG | P89: INSUNIX | Q89: TABLE12 | R89: DESCRIPT | S89: =CONCATENATE(M89,".",O89,".",P89,".",Q89,".",R89) -> INSUNIX.LPG.INSUNIX.TABLE12.DESCRIPT | V89: 1 | W89: {=IF(AND(COUNTIF('LAKEHOUSE (Tbl Campos)'!$F$2:$F$14000,$S$3:$S$910)>0),"X","-")} -> -
M90: INSUNIX | N90: INSUNIX | O90: LPG | P90: INSUNIX | Q90: TABLE121 | R90: DESCRIPT | S90: =CONCATENATE(M90,".",O90,".",P90,".",Q90,".",R90) -> INSUNIX.LPG.INSUNIX.TABLE121.DESCRIPT | V90: 1 | W90: {=IF(AND(COUNTIF('LAKEHOUSE (Tbl Campos)'!$F$2:$F$14000,$S$3:$S$910)>0),"X","-")} -> -
M91: INSUNIX | N91: INSUNIX | O91: LPG | P91: INSUNIX | Q91: TABLE18 | R91: DESCRIPT | S91: =CONCATENATE(M91,".",O91,".",P91,".",Q91,".",R91) -> INSUNIX.LPG.INSUNIX.TABLE18.DESCRIPT | V91: 1 | W91: {=IF(AND(COUNTIF('LAKEHOUSE (Tbl Campos)'!$F$2:$F$14000,$S$3:$S$910)>0),"X","-")} -> -
M92: INSUNIX | N92: INSUNIX | O92: LPG | P92: INSUNIX | Q92: TABLE23 | R92: DESCRIPT | S92: =CONCATENATE(M92,".",O92,".",P92,".",Q92,".",R92) -> INSUNIX.LPG.INSUNIX.TABLE23.DESCRIPT | V92: 1 | W92: {=IF(AND(COUNTIF('LAKEHOUSE (Tbl Campos)'!$F$2:$F$14000,$S$3:$S$910)>0),"X","-")} -> -
... M126: VTIME | N126: INSUDB | O126: LPG | P126: INSUDB | Q126: TAB_BLOCKCLI | R126: SDESCRIPT | S126: =CONCATENATE(M126,".",O126,".",P126,".",Q126,".",R126) -> VTIME.LPG.INSUDB.TAB_BLOCKCLI.SDESCRIPT | V126: 1 | W126: {=IF(AND(COUNTIF('LAKEHOUSE (Tbl Campos)'!$F$2:$F$14000,$S$3:$S$910)>0),"X","-")} -> -
M127: VTIME | N127: INSUDB | O127: LPG | P127: INSUDB | Q127: TAB_BUSINESS | R127: SDESCRIPT | S127: =CONCATENATE(M127,".",O127,".",P127,".",Q127,".",R127) -> VTIME.LPG.INSUDB.TAB_BUSINESS.SDESCRIPT | W127: {=IF(AND(COUNTIF('LAKEHOUSE (Tbl Campos)'!$F$2:$F$14000,$S$3:$S$910)>0),"X","-")} -> -
M128: VTIME | N128: INSUDB | O128: LPG | P128: INSUDB | Q128: TABLE12 | R128: SDESCRIPT | S128: =CONCATENATE(M128,".",O128,".",P128,".",Q128,".",R128) -> VTIME.LPG.INSUDB.TABLE12.SDESCRIPT | W128: {=IF(AND(COUNTIF('LAKEHOUSE (Tbl Campos)'!$F$2:$F$14000,$S$3:$S$910)>0),"X","-")} -> -
M129: VTIME | N129: INSUDB | O129: LPG | P129: INSUDB | Q129: TABLE23 | R129: SDESCRIPT | S129: =CONCATENATE(M129,".",O129,".",P129,".",Q129,".",R129) -> VTIME.LPG.INSUDB.TABLE23.SDESCRIPT | W129: {=IF(AND(COUNTIF('LAKEHOUSE (Tbl Campos)'!$F$2:$F$14000,$S$3:$S$910)>0),"X","-")} -> -
M130: VTIME | N130: INSUDB | O130: LPG | P130: INSUDB | Q130: TABLE5006 | R130: SDESCRIPT | S130: =CONCATENATE(M130,".",O130,".",P130,".",Q130,".",R130) -> VTIME.LPG.INSUDB.TABLE5006.SDESCRIPT | W130: {=IF(AND(COUNTIF('LAKEHOUSE (Tbl Campos)'!$F$2:$F$14000,$S$3:$S$910)>0),"X","-")} -> -
M131: VTIME | N131: INSUDB | O131: LPG | P131: INSUDB | Q131: TABLE55 | R131: SDESCRIPT | S131: =CONCATENATE(M131,".",O131,".",P131,".",Q131,".",R131) -> VTIME.LPG.INSUDB.TABLE55.SDESCRIPT | W131: {=IF(AND(COUNTIF('LAKEHOUSE (Tbl Campos)'!$F$2:$F$14000,$S$3:$S$910)>0),"X","-")} -> -
M132: VTIME | N132: INSUDB | O132: LPG | P132: INSUDB | Q132: TABLE5503 | R132: SDESCRIPT | S132: =CONCATENATE(M132,".",O132,".",P132,".",Q132,".",R132) -> VTIME.LPG.INSUDB.TABLE5503.SDESCRIPT | W132: {=IF(AND(COUNTIF('LAKEHOUSE (Tbl Campos)'!$F$2:$F$14000,$S$3:$S$910)>0),"X","-")} -> -
M133: VTIME | N133: INSUDB | O133: LPG | P133: INSUDB | Q133: TABLE6000 | R133: SDESCRIPT | S133: =CONCATENATE(M133,".",O133,".",P133,".",Q133,".",R133) -> VTIME.LPG.INSUDB.TABLE6000.SDESCRIPT | W133: {=IF(AND(COUNTIF('LAKEHOUSE (Tbl Campos)'!$F$2:$F$14000,$S$3:$S$910)>0),"X","-")} -> -
S134: =CONCATENATE(M134,".",O134,".",P134,".",Q134,".",R134) -> .... | W134: {=IF(AND(COUNTIF('LAKEHOUSE (Tbl Campos)'!$F$2:$F$14000,$S$3:$S$910)>0),"X","-")} -> -
S135: =CONCATENATE(M135,".",O135,".",P135,".",Q135,".",R135) -> .... | W135: {=IF(AND(COUNTIF('LAKEHOUSE (Tbl Campos)'!$F$2:$F$14000,$S$3:$S$910)>0),"X","-")} -> -
S136: =CONCATENATE(M136,".",O136,".",P136,".",Q136,".",R136) -> .... | W136: {=IF(AND(COUNTIF('LAKEHOUSE (Tbl Campos)'!$F$2:$F$14000,$S$3:$S$910)>0),"X","-")} -> -
S137: =CONCATENATE(M137,".",O137,".",P137,".",Q137,".",R137) -> .... | W137: {=IF(AND(COUNTIF('LAKEHOUSE (Tbl Campos)'!$F$2:$F$14000,$S$3:$S$910)>0),"X","-")} -> -
S138: =CONCATENATE(M138,".",O138,".",P138,".",Q138,".",R138) -> .... | W138: {=IF(AND(COUNTIF('LAKEHOUSE (Tbl Campos)'!$F$2:$F$14000,$S$3:$S$910)>0),"X","-")} -> -
S139: =CONCATENATE(M139,".",O139,".",P139,".",Q139,".",R139) -> .... | W139: {=IF(AND(COUNTIF('LAKEHOUSE (Tbl Campos)'!$F$2:$F$14000,$S$3:$S$910)>0),"X","-")} -> -
S140: =CONCATENATE(M140,".",O140,".",P140,".",Q140,".",R140) -> .... | W140: {=IF(AND(COUNTIF('LAKEHOUSE (Tbl Campos)'!$F$2:$F$14000,$S$3:$S$910)>0),"X","-")} -> -
S141: =CONCATENATE(M141,".",O141,".",P141,".",Q141,".",R141) -> .... | W141: {=IF(AND(COUNTIF('LAKEHOUSE (Tbl Campos)'!$F$2:$F$14000,$S$3:$S$910)>0),"X","-")} -> -
S142: =CONCATENATE(M142,".",O142,".",P142,".",Q142,".",R142) -> .... | W142: {=IF(AND(COUNTIF('LAKEHOUSE (Tbl Campos)'!$F$2:$F$14000,$S$3:$S$910)>0),"X","-")} -> -
S143: =CONCATENATE(M143,".",O143,".",P143,".",Q143,".",R143) -> .... | W143: {=IF(AND(COUNTIF('LAKEHOUSE (Tbl Campos)'!$F$2:$F$14000,$S$3:$S$910)>0),"X","-")} -> -
S144: =CONCATENATE(M144,".",O144,".",P144,".",Q144,".",R144) -> .... | W144: {=IF(AND(COUNTIF('LAKEHOUSE (Tbl Campos)'!$F$2:$F$14000,$S$3:$S$910)>0),"X","-")} -> -
S145: =CONCATENATE(M145,".",O145,".",P145,".",Q145,".",R145) -> .... | W145: {=IF(AND(COUNTIF('LAKEHOUSE (Tbl Campos)'!$F$2:$F$14000,$S$3:$S$910)>0),"X","-")} -> -
... S151: =CONCATENATE(M151,".",O151,".",P151,".",Q151,".",R151) -> .... | W151: {=IF(AND(COUNTIF('LAKEHOUSE (Tbl Campos)'!$F$2:$F$14000,$S$3:$S$910)>0),"X","-")} -> -

Sheet 3. Reportes
A1: Caso de Uso | B1: ID Reporte | C1: Nombre del Entidad de Dato | D1: Nombre del reporte | E1: Responsable de la definición del reporte | F1: Descripción del reporte | G1: Dominio asociado | H1: ¿Es regulatorio? | I1: Periodicidad de Generación | J1: Dimensiones | K1: Indicadores | L1: ¿Se presenta en algún cuadro de mando? | M1: Nombre cuadro de mando | N1: Áreas que consumen el reporte | O1: Herramienta | P1: Validado por Propietario del reporte | Q1: Validado por Propietario del reporte
A2: Caso de uso que corresponde | B2: Identificador de Reporte | C2: Nombre único con el cual el Negocio identifica al Entidad de Dato | D2: Nombre del reporte | E2: Nombre de la persona responsable del reporte y área asociada | F2: Descripción del reporte a nivel de contenido | G2: Nombre del dominio al que corresponde el reporte | H2: Indica si se trata de un reporte regulatorio (Sí/No) | I2: Frecuencia de generación del reporte | J2: Listar las dimensiones por las que se puede visualizar el reporte (Fecha, Producto, Canal) | K2: Listar los indicadores que se tienen en el reporte | L2: Indica si es que se visualiza en algún cuadro de mando (Sí/No) | M2: Nombre del cuadro de mando | N2: Áreas que consumen el reporte | O2: Herramienta en la que se encuentra el reporte | P2: Una vez revisado por el propietario colocar Sí en señal de conformidad con la definición | Q2: Una vez revisado por el propietario colocar Sí en señal de conformidad con la definición
A3: CRM | B3: ="R00"&COUNTA($A$3:$A$5) -> R001 | C3: Número Documento | D3: Dashboard Producto sugerido AMF | E3: Analítica Clientes y Big Data | F3: Efectividad de la venta basado en la oferta de un producto sugerido | G3: Persona | H3: No | I3: Mensual | J3: Año, mes, producto de salud sugerido | K3: % de efectividad (N productos sugeridos/ Total de clientes) | L3: NO | M3: No aplica | N3: Analítica Clientes y Big Data | O3: Power BI | P3: Gaudy Sanchez
B4: ="R00"&COUNTA($A$3:$A$5) -> R001 | C4: RUC de persona natural | D4: Dashboard Producto sugerido AMF | E4: Analítica Clientes y Big Data | F4: Efectividad de la venta basado en la oferta de un producto sugerido | G4: Persona | H4: No | I4: Mensual | J4: Año, mes, producto de salud sugerido | K4: % de efectividad (N productos sugeridos/ Total de clientes) | L4: NO | M4: No aplica | N4: Analítica Clientes y Big Data | O4: Power BI | P4: Gaudy Sanchez
B5: ="R00"&COUNTA($A$3:$A$5) -> R001 | C5: Género | D5: Dashboard Producto sugerido AMF | E5: Analítica Clientes y Big Data | F5: Efectividad de la venta basado en la oferta de un producto sugerido | G5: Persona | H5: No | I5: Mensual | J5: Año, mes, producto de salud sugerido | K5: % de efectividad (N productos sugeridos/ Total de clientes) | L5: NO | M5: No aplica | N5: Analítica Clientes y Big Data | O5: Power BI | P5: Gaudy Sanchez
B6: ="R00"&COUNTA($A$3:$A$5) -> R001 | C6: Rol Persona | D6: Dashboard Producto sugerido AMF | E6: Analítica Clientes y Big Data | F6: Efectividad de la venta basado en la oferta de un producto sugerido | G6: Persona | H6: No | I6: Mensual | J6: Año, mes, producto de salud sugerido | K6: % de efectividad (N productos sugeridos/ Total de clientes) | L6: NO | M6: No aplica | N6: Analítica Clientes y Big Data | O6: Power BI | P6: Gaudy Sanchez
A7: CRM | B7: ="R0"&COUNTA($A$3:$A$7) -> R02 | C7: Rol Persona | D7: Perfil de cliente - VIDA LARGO PLAZO | E7: Analítica Clientes y Big Data | F7: Descripción del stock de clientes del ramo de vida largo plazo | G7: Persona | H7: No | I7: A demanda | J7: Canal comercial, zona, situación laboral, consentimiento, colaborador (S/N) | K7: Distribución porcentual (edades, situación laboral, zona, departamento), promedios de edades e indicadores crediticios | L7: NO | M7: No aplica | N7: Analítica Clientes y Big Data | O7: Power BI | P7: Gaudy Sanchez
A8: CRM | B8: ="R0"&COUNTA($A$3:$A$14) -> R03 | C8: Tipo de intermediario | D8: Producción Contable | E8: Inteligencia Comercial | F8: Producción Historica de corredores | G8: Persona | H8: No | I8: A demanda | J8: Producción Corredor, Canal, Oficina, Tipo de producto, Venta Nueva y Renovación. Información por Ejecutivos y Apoderados | K8: Primas; polizas y productos | L8: NO | M8: No aplica | N8: Inteligencia Comercial | O8: QW | P8: Arturo Yaipen | Q8: SI
B9: ="R0"&COUNTA($A$3:$A$14) -> R03 | C9: Número de intermediario | D9: Producción Contable | E9: Inteligencia Comercial | F9: Producción Historica de corredores | G9: Persona | H9: No | I9: A demanda | J9: Producción Corredor, Canal, Oficina, Tipo de producto, Venta Nueva y Renovación. Información por Ejecutivos y Apoderados | K9: Primas; polizas y productos | L9: NO | M9: No aplica | N9: Inteligencia Comercial | O9: QW | P9: Arturo Yaipen | Q9: SI
B10: ="R0"&COUNTA($A$3:$A$14) -> R03 | C10: Nombre del Intermediario | D10: Producción Contable | E10: Inteligencia Comercial | F10: Producción Historica de corredores | G10: Persona | H10: No | I10: A demanda | J10: Producción Corredor, Canal, Oficina, Tipo de producto, Venta Nueva y Renovación. Información por Ejecutivos y Apoderados | K10: Primas; polizas y productos | L10: NO | M10: No aplica | N10: Inteligencia Comercial | O10: QW | P10: Arturo Yaipen | Q10: SI
B11: ="R0"&COUNTA($A$3:$A$14) -> R03 | C11: Número ramo Agenciado | D11: Producción Contable | E11: Inteligencia Comercial | F11: Producción Historica de corredores | G11: Persona | H11: No | I11: A demanda | J11: Producción Corredor, Canal, Oficina, Tipo de producto, Venta Nueva y Renovación. Información por Ejecutivos y Apoderados | K11: Primas; polizas y productos | L11: NO | M11: No aplica | N11: Inteligencia Comercial | O11: QW | P11: Arturo Yaipen | Q11: SI
B12: ="R0"&COUNTA($A$3:$A$14) -> R03 | C12: Descripción de ramo Agenciado | D12: Producción Contable | E12: Inteligencia Comercial | F12: Producción Historica de corredores | G12: Persona | H12: No | I12: A demanda | J12: Producción Corredor, Canal, Oficina, Tipo de producto, Venta Nueva y Renovación. Información por Ejecutivos y Apoderados | K12: Primas; polizas y productos | L12: NO | M12: No aplica | N12: Inteligencia Comercial | O12: QW | P12: Arturo Yaipen | Q12: SI
B13: ="R0"&COUNTA($A$3:$A$14) -> R03 | C13: Fecha de inicio de agenciamiento | D13: Producción Contable | E13: Inteligencia Comercial | F13: Producción Historica de corredores | G13: Persona | H13: No | I13: A demanda | J13: Producción Corredor, Canal, Oficina, Tipo de producto, Venta Nueva y Renovación. Información por Ejecutivos y Apoderados | K13: Primas; polizas y productos | L13: NO | M13: No aplica | N13: Inteligencia Comercial | O13: QW | P13: Arturo Yaipen | Q13: SI
B14: ="R0"&COUNTA($A$3:$A$14) -> R03 | C14: Fecha fin agenciamiento | D14: Producción Contable | E14: Inteligencia Comercial | F14: Producción Historica de corredores | G14: Persona | H14: No | I14: A demanda | J14: Producción Corredor, Canal, Oficina, Tipo de producto, Venta Nueva y Renovación. Información por Ejecutivos y Apoderados | K14: Primas; polizas y productos | L14: NO | M14: No aplica | N14: Inteligencia Comercial | O14: QW | P14: Arturo Yaipen | Q14: SI
A15: CRM | B15: ="R0"&COUNTA($A$3:$A$21) -> R04 | C15: Tipo de intermediario | D15: Autogestión | E15: Emisión | F15: Nivel de autogestión de ramos | G15: Persona | H15: No | I15: A demanda | J15: Autogestión de Vida Ley, Fenix, Sel y SED | K15: Autogestion, Oficinas y Corredores. | L15: NO | M15: No aplica | N15: Inteligencia Comercial y Emisión | O15: Insunix | P15: Arturo Yaipen | Q15: SI
B16: ="R0"&COUNTA($A$3:$A$21) -> R04 | C16: Número de intermediario | D16: Autogestión | E16: Emisión | F16: Nivel de autogestión de ramos | G16: Persona | H16: No | I16: A demanda | J16: Autogestión de Vida Ley, Fenix, Sel y SED | K16: Autogestion, Oficinas y Corredores. | L16: NO | M16: No aplica | N16: Inteligencia Comercial y Emisión | O16: Insunix | P16: Arturo Yaipen | Q16: SI
B17: ="R0"&COUNTA($A$3:$A$21) -> R04 | C17: Nombre del Intermediario | D17: Autogestión | E17: Emisión | F17: Nivel de autogestión de ramos | G17: Persona | H17: No | I17: A demanda | J17: Autogestión de Vida Ley, Fenix, Sel y SED | K17: Autogestion, Oficinas y Corredores. | L17: NO | M17: No aplica | N17: Inteligencia Comercial y Emisión | O17: Insunix | P17: Arturo Yaipen | Q17: SI
B18: ="R0"&COUNTA($A$3:$A$21) -> R04 | C18: Número ramo Agenciado | D18: Autogestión | E18: Emisión | F18: Nivel de autogestión de ramos | G18: Persona | H18: No | I18: A demanda | J18: Autogestión de Vida Ley, Fenix, Sel y SED | K18: Autogestion, Oficinas y Corredores. | L18: NO | M18: No aplica | N18: Inteligencia Comercial y Emisión | O18: Insunix | P18: Arturo Yaipen | Q18: SI
B19: ="R0"&COUNTA($A$3:$A$21) -> R04 | C19: Descripción de ramo Agenciado | D19: Autogestión | E19: Emisión | F19: Nivel de autogestión de ramos | G19: Persona | H19: No | I19: A demanda | J19: Autogestión de Vida Ley, Fenix, Sel y SED | K19: Autogestion, Oficinas y Corredores. | L19: NO | M19: No aplica | N19: Inteligencia Comercial y Emisión | O19: Insunix | P19: Arturo Yaipen | Q19: SI
B20: ="R0"&COUNTA($A$3:$A$21) -> R04 | C20: Fecha de inicio de agenciamiento | D20: Autogestión | E20: Emisión | F20: Nivel de autogestión de ramos | G20: Persona | H20: No | I20: A demanda | J20: Autogestión de Vida Ley, Fenix, Sel y SED | K20: Autogestion, Oficinas y Corredores. | L20: NO | M20: No aplica | N20: Inteligencia Comercial y Emisión | O20: Insunix | P20: Arturo Yaipen | Q20: SI
B21: ="R0"&COUNTA($A$3:$A$21) -> R04 | C21: Fecha fin agenciamiento | D21: Autogestión | E21: Emisión | F21: Nivel de autogestión de ramos | G21: Persona | H21: No | I21: A demanda | J21: Autogestión de Vida Ley, Fenix, Sel y SED | K21: Autogestion, Oficinas y Corredores. | L21: NO | M21: No aplica | N21: Inteligencia Comercial y Emisión | O21: Insunix | P21: Arturo Yaipen | Q21: SI

Sheet Resumen_01
B1: Esquema | C1: Tablas del Diccionario | D1: Campos | E1: Campos encontrados en Lakehouse | F1: Campos faltantes dentro del diccionario | G1: Tablas faltantes en Lakehouse
B2: INSIS_CUST | C2: CFGLPV_DOCUMENT_TYPE | D2: NAME | G2: X
B3: INSIS_SYS_V10 | C3: DOC_DOCUMENTS | D3: DOC_NUM | G3: X
B4: INSIS_PEOPLE_V10 | C4: HST_PEOPLE_MAN_COMP | D4: NAME | G4: X
B5: INSIS_PEOPLE_V10 | C5: HST_PEOPLE_SEX | D5: NAME | G5: X
B6: INSIS_PEOPLE_V10 | C6: HT_ADDRESS_TYPE | D6: NAME | G6: X
B7: INSIS_PEOPLE_V10 | C7: HT_AGENT_TYPE | D7: NAME | G7: X
B8: INSIS_PEOPLE_V10 | C8: HT_CUSTOMER_CORP_STAT | D8: NAME | G8: X
B9: INSIS_PEOPLE_V10 | C9: HT_CUSTOMER_INTERNAL_STATUS | D9: NAME | G9: X
B10: INSIS_PEOPLE_V10 | C10: HT_PEOPLE_COMPANY_TYPES | D10: NAME | G10: X
B11: INSIS_PEOPLE_V10 | C11: HT_PEOPLE_GROUPS | D11: NAME | G11: X
B12: INSIS_PEOPLE_V10 | C12: HT_PEOPLE_OCCUP_CODE | D12: NAME | G12: X
B13: INSIS_PEOPLE_V10 | C13: HT_PEOPLE_RELATION | D13: REL_NAME | G13: X
B14: INSIS_PEOPLE_V10 | C14: P_ADDRESS | D14: ADDRESS | E14: X
B15: INSIS_PEOPLE_V10 | C15: P_ADDRESS | D15: ADDRESS_TYPE | E15: X
B16: INSIS_PEOPLE_V10 | C16: P_ADDRESS | D16: MAN_ID | F16: X
B17: INSIS_PEOPLE_V10 | C17: P_ADDRESS | D17: COUNTRY | F17: X
B18: INSIS_PEOPLE_V10 | C18: P_ADDRESS | D18: CITY | F18: X
B19: INSIS_PEOPLE_V10 | C19: P_ADDRESS | D19: POST_CODE | F19: X
B20: INSIS_PEOPLE_V10 | C20: P_ADDRESS | D20: NOTE | F20: X
B21: INSIS_PEOPLE_V10 | C21: P_ADDRESS | D21: COUNTRY_CODE | F21: X
B22: INSIS_PEOPLE_V10 | C22: P_ADDRESS | D22: ADDRESS_ID | F22: X
B23: INSIS_PEOPLE_V10 | C23: P_ADDRESS | D23: COUNTRY_STATE | F23: X
B24: INSIS_PEOPLE_V10 | C24: P_ADDRESS | D24: MAIL_YN | F24: X
B25: INSIS_PEOPLE_V10 | C25: P_ADDRESS | D25: INVOICE_YN | F25: X
B26: INSIS_PEOPLE_V10 | C26: P_ADDRESS | D26: STATE_REGION | F26: X
B27: INSIS_PEOPLE_V10 | C27: P_ADDRESS | D27: TERRITORY_CLASSIFICATION | F27: X
... B44: INSIS_PEOPLE_V10 | C44: P_ADDRESS | D44: PRIMARY_FLAG | F44: X
B45: INSIS_PEOPLE_V10 | C45: P_AGENTS | D45: AGENT_TYPE | E45: X
B46: INSIS_PEOPLE_V10 | C46: P_AGENTS | D46: AGENT_NO | E46: X
B47: INSIS_PEOPLE_V10 | C47: P_AGENTS | D47: AGENT_ID | F47: X
B48: INSIS_PEOPLE_V10 | C48: P_AGENTS | D48: MAN_ID | F48: X
B49: INSIS_PEOPLE_V10 | C49: P_AGENTS | D49: OFFICE_ID | F49: X
B50: INSIS_PEOPLE_V10 | C50: P_AGENTS | D50: QUALIF_LEVEL | F50: X
B51: INSIS_PEOPLE_V10 | C51: P_AGENTS | D51: HIRE_DATE | F51: X
B52: INSIS_PEOPLE_V10 | C52: P_AGENTS | D52: FIRE_DATE | F52: X
B53: INSIS_PEOPLE_V10 | C53: P_AGENTS | D53: AGENT_STATE | F53: X
B54: INSIS_PEOPLE_V10 | C54: P_AGENTS | D54: DEFAULT_AGENT | F54: X
B55: INSIS_PEOPLE_V10 | C55: P_AGENTS | D55: MAIN_AGENT | F55: X
B56: INSIS_PEOPLE_V10 | C56: P_AGENTS | D56: CONTRACT_TYPE | F56: X
B57: INSIS_PEOPLE_V10 | C57: P_AGENTS | D57: CONTRACT_MONTHS | F57: X
B58: INSIS_PEOPLE_V10 | C58: P_AGENTS | D58: ACCOUNT_NUMBER | F58: X
... B63: INSIS_PEOPLE_V10 | C63: P_AGENTS | D63: ACCOUNT_ID | F63: X
B64: INSIS_PEOPLE_V10 | C64: P_CLIENTS | D64: CLIENT_ID | E64: X
B65: INSIS_PEOPLE_V10 | C65: P_CLIENTS | D65: CORPORATE_IC_STATUS | E65: X
B66: INSIS_PEOPLE_V10 | C66: P_CLIENTS | D66: IC_STATUS | E66: X
B67: INSIS_PEOPLE_V10 | C67: P_CLIENTS | D67: MAN_ID | F67: X
B68: INSIS_PEOPLE_V10 | C68: P_CLIENTS | D68: OFFICIAL_STATUS | F68: X
B69: INSIS_PEOPLE_V10 | C69: P_CLIENTS | D69: EMPLOYEE_STATUS | F69: X
B70: INSIS_PEOPLE_V10 | C70: P_CLIENTS | D70: RISK_RATING | F70: X
B71: INSIS_PEOPLE_V10 | C71: P_CLIENTS | D71: SEGMENT | F71: X
B72: INSIS_PEOPLE_V10 | C72: P_CLIENTS | D72: CUSTOMER_TYPE | F72: X
